Workbook
Name Slicer_Month: #N/A

Sheet Total Sales IN&OUT
A3: Row Labels | B3: Sum of Total Out | C3: Sum of Total In
A4: January | B4: 446079 | C4: 412373
A5: February | B5: 332508 | C5: 236379
A6: March | B6: 360443 | C6: 318990
A7: April | B7: 375008 | C7: 381785
A8: May | B8: 423435 | C8: 428246
A9: June | B9: 318771 | C9: 321615
A10: July | B10: 418398 | C10: 414018
A11: August | B11: 532619 | C11: 485693
A12: September | B12: 352770 | C12: 277023
A13: October | B13: 363747 | C13: 382945
A14: November | B14: 241060 | C14: 219514
A15: December | B15: 301689 | C15: 256450
A16: Grand Total | B16: 4466527 | C16: 4135031

Sheet Summary
B4: Total | C4: January | D4: February | E4: March | F4: April | G4: May | H4: June | I4: July | J4: August | K4: September | L4: October | M4: November | N4: December
A5: Monthy Expenses | B5: =SUM(C5:Z5) -> 4466527 | C5: =January!B35 -> 446079 | D5: =Febraury!B35 -> 332508 | E5: =March!B35 -> 360443 | F5: =April!B35 -> 375008 | G5: =May!B35 -> 423435 | H5: =June!B35 -> 318771 | I5: =July!B35 -> 418398 | J5: =August!B35 -> 532619 | K5: =September!B35 -> 352770 | L5: =October!B35 -> 363747 | M5: =November!B35 -> 241060 | N5: =December!B35 -> 301689
A6: Monthly UPI | B6: =SUM(C6:Z6) -> 1719147 | C6: =January!B36 -> 202711 | D6: =Febraury!B36 -> 103017 | E6: =March!B36 -> 161780 | F6: =April!B36 -> 179193 | G6: =May!B36 -> 198977 | H6: =June!B36 -> 138259 | I6: =July!B36 -> 137405 | J6: =August!B36 -> 136248 | K6: =September!B36 -> 125267 | L6: =October!B36 -> 143462 | M6: =November!B36 -> 89420 | N6: =December!B36 -> 103408
A7: Monthly Cash | B7: =SUM(C7:Z7) -> 1695744 | C7: =January!B37 -> 172325 | D7: =Febraury!B37 -> 107353 | E7: =March!B37 -> 130212 | F7: =April!B37 -> 174719 | G7: =May!B37 -> 192297 | H7: =June!B37 -> 158111 | I7: =July!B37 -> 139836 | J7: =August!B37 -> 139181 | K7: =September!B37 -> 102373 | L7: =October!B37 -> 193388 | M7: =November!B37 -> 86502 | N7: =December!B37 -> 99447
A8: Monthly Sales | B8: =SUM(C8:Z8) -> 3414891 | C8: =January!B38 -> 375036 | D8: =Febraury!B38 -> 210370 | E8: =March!B38 -> 291992 | F8: =April!B38 -> 353912 | G8: =May!B38 -> 391274 | H8: =June!B38 -> 296370 | I8: =July!B38 -> 277241 | J8: =August!B38 -> 275429 | K8: =September!B38 -> 227640 | L8: =October!B38 -> 336850 | M8: =November!B38 -> 175922 | N8: =December!B38 -> 202855
A9: Rent, Salaries & others | B9: =SUM(C9:Z9) -> 1095294 | C9: =January!B39 -> 88972 | D9: =Febraury!B39 -> 90891 | E9: =March!B39 -> 94022 | F9: =April!B39 -> 90016 | G9: =May!B39 -> 98102 | H9: =June!B39 -> 95741 | I9: =July!B39 -> 104969 | J9: =August!B39 -> 105619 | K9: =September!B39 -> 96955 | L9: =October!B39 -> 90824 | M9: =November!B39 -> 71556 | N9: =December!B39 -> 67627
A10: Swiggy | B10: =SUM(C10:Z10) -> 516662 | C10: =January!B40 -> 23670 | D10: =Febraury!B40 -> 13455 | E10: =March!B40 -> 14648 | F10: =April!B40 -> 12085 | G10: =May!B40 -> 13612 | H10: =June!B40 -> 15441 | I10: =July!B40 -> 119593 | J10: =August!B40 -> 190054 | K10: =September!B40 -> 33874 | L10: =October!B40 -> 28853 | M10: =November!B40 -> 22814 | N10: =December!B40 -> 28563
A11: Zomato | B11: =SUM(C11:Z11) -> 203478 | C11: =January!B41 -> 13667 | D11: =Febraury!B41 -> 12554 | E11: =March!B41 -> 12350 | F11: =April!B41 -> 15788 | G11: =May!B41 -> 23360 | H11: =June!B41 -> 9804 | I11: =July!B41 -> 17184 | J11: =August!B41 -> 20210 | K11: =September!B41 -> 15509 | L11: =October!B41 -> 17242 | M11: =November!B41 -> 20778 | N11: =December!B41 -> 25032
A12: Stock | B12: =SUM(C12:Z12) -> 909295 | C12: =January!B42 -> 95268 | D12: =Febraury!B42 -> 67553 | E12: =March!B42 -> 54083 | F12: =Stock!R72 -> 70682 | G12: =May!B42 -> 95827 | H12: =June!B42 -> 54328 | I12: =July!B42 -> 85485 | J12: =August!B42 -> 127049 | K12: =September!B42 -> 81167 | L12: =October!B42 -> 90599 | M12: =November!B42 -> 27074 | N12: =December!B42 -> 60180
A13: Actual P/L | B13: =SUM(C13:Z13) -> -331496 | C13: =C8-C5+C10+C11 -> -33706 | D13: =D8-D5+D10+D11 -> -96129 | E13: =E8-E5+E10+E11 -> -41453 | F13: =F8-F5+F10+F11 -> 6777 | G13: =G8-G5+G10+G11 -> 4811 | H13: =H8-H5+H10+H11 -> 2844 | I13: =I8-I5+I10+I11 -> -4380 | J13: =J8-J5+J10+J11 -> -46926 | ... N13: =N8-N5+N10+N11 -> -45239
A15: Total In | B15: =SUM(C15:Z15) -> 4135031 | C15: =C8+C10+C11 -> 412373 | D15: =D8+D10+D11 -> 236379 | E15: =E8+E10+E11 -> 318990 | F15: =F8+F10+F11 -> 381785 | G15: =G8+G10+G11 -> 428246 | H15: =H8+H10+H11 -> 321615 | I15: =I8+I10+I11 -> 414018 | J15: =J8+J10+J11 -> 485693 | ... N15: =N8+N10+N11 -> 256450
A16: Total Out | B16: =SUM(C16:Z16) -> 4466527 | C16: =C5 -> 446079 | D16: =D5 -> 332508 | E16: =E5 -> 360443 | F16: =F5 -> 375008 | G16: =G5 -> 423435 | H16: =H5 -> 318771 | I16: =I5 -> 418398 | J16: =J5 -> 532619 | ... N16: =N5 -> 301689

Sheet Expenses
B2: Expenses - Monthly | E2: January | F2: Febraury | G2: March | H2: April | I2: May | J2: June | K2: July | L2: August | M2: September | N2: October | O2: November | P2: December
B3: Base Cost | C3: =SUM(C4:C11) -> 49700
B4: Rent | C4: 27500 | E4: 20000 | F4: 27500 | G4: 27500 | H4: 27500 | I4: 27500 | J4: 27500 | K4: 27500 | L4: 27500 | M4: 27500 | N4: 27500 | O4: 27500 | P4: 27500
B5: Maintenance | C5: 0 | E5: 0 | F5: 0 | G5: 0 | H5: 0 | I5: 0 | J5: 0 | K5: 0 | L5: 0 | M5: 0 | N5: 0 | O5: 0 | P5: 0
B6: Electricity | C6: 13000 | E6: 11662 | F6: 9296 | G6: 11001 | H6: 11516 | I6: 12288 | J6: 11469 | K6: 12218 | L6: 12590 | M6: 11419 | N6: 10050 | O6: 8949 | P6: 7207
B7: Room Rent | C7: 6000 | E7: 6000 | F7: 6000 | G7: 6000 | H7: 6000 | I7: 6000 | J7: 6000 | K7: 6000 | L7: 6000 | M7: 6000 | N7: 6000 | O7: 6000 | P7: 6000
B8: Staff - electricity | C8: 900 | E8: 730 | F8: 910 | G8: 1060 | H8: 900 | I8: 798 | J8: 642 | K8: 741 | L8: 603 | M8: 636 | N8: 474 | O8: 323 | P8: 314
B9: Wifi | C9: 500 | E9: 0 | F9: 0 | G9: 0 | H9: 0 | I9: 3000 | J9: 0 | K9: 0 | L9: 0 | M9: 0 | N9: 0 | O9: 0 | P9: 0
B10: Software | C10: 500 | E10: 0 | F10: 0 | G10: 0 | H10: 0 | I10: 0 | J10: 0 | K10: 0 | L10: 4500 | M10: 0 | N10: 0 | O10: 0 | P10: 0
B11: Pest Control | C11: 1300 | E11: 1300 | F11: 1300 | G11: 1300 | H11: 1300 | I11: 0 | J11: 1300 | K11: 0 | L11: 1300 | M11: 1200 | N11: 1300 | O11: 1300 | P11: 1800
B12: Marketing Cost | C12: 0 | E12: 0 | F12: 0 | G12: 0 | H12: 800 | I12: 0 | J12: 0 | K12: 0 | L12: 0 | M12: 0 | N12: 0 | O12: 0 | P12: 600
B13: Salaries | C13: =SUM(C14:C18) -> 56000
B14: Manager 1 | C14: 20000 | E14: 20000 | F14: 19285 | G14: 20000 | H14: 14000 | I14: 20000 | J14: 20000 | K14: 20000 | L14: 20000 | M14: 20000 | N14: 20000 | O14: 0 | P14: 0
B15: Waiter 1 | C15: 13000 | E15: 12180 | F15: 11600 | G15: 12161 | H15: 13000 | I15: 14516 | J15: 13500 | K15: 14510 | L15: 11026 | M15: 5200 | N15: 11500 | O15: 13000 | P15: 13000
B16: Waiter 2 | C16: 8000 | E16: 0 | F16: 0 | G16: 0 | H16: 0 | I16: 0 | J16: 2930 | K16: 8000 | L16: 8400 | M16: 11500 | N16: 4645 | O16: 0 | P16: 0
B17: Cleaning 1 | C17: 10000 | E17: 10000 | F17: 10000 | G17: 10000 | H17: 10000 | I17: 9000 | J17: 10000 | K17: 10000 | L17: 9670 | M17: 13000 | N17: 7420 | O17: 12330 | P17: 10000
B18: Cleaning 2 | C18: 5000 | E18: 7100 | F18: 5000 | G18: 5000 | H18: 5000 | I18: 5000 | J18: 2400 | K18: 6000 | L18: 4030 | M18: 500 | N18: 1935 | O18: =3360-1206 -> 2154 | P18: 1206
B20: Total | C20: =C3+C13 -> 105700 | E20: =SUM(E4:E18) -> 88972 | F20: =SUM(F4:F18) -> 90891 | G20: =SUM(G4:G18) -> 94022 | H20: =SUM(H4:H18) -> 90016 | I20: =SUM(I4:I18) -> 98102 | J20: =SUM(J4:J18) -> 95741 | K20: =SUM(K4:K18) -> 104969 | L20: =SUM(L4:L18) -> 105619 | ... P20: =SUM(P4:P18) -> 67627
B22: Per day | C22: =C20/30 -> 3523.3333
B24: Advance Paid to
B25: Mandi Prasad | C25: 12000
B26: Nagender Reddy | C26: 60000
B27: Nagaraju | C27: 8000
B28: Munna | C28: 0
B29: Mandi Master | C29: 0
B30: Susheela | C30: 0
B31: Munni | C31: 0
B32: Cold drinks deposit | C32: 2000
B33: Total | C33: =SUM(C25:C29) -> 80000
G37: Old | H37: New | I37: difference
F38: 45323 | G38: 550 | H38: 357 | I38: =G38-H38 -> 193
F39: 45352 | G39: 713 | H39: 463 | I39: =G39-H39 -> 250
F40: 45383 | G40: 780 | H40: =G40*0.65 -> 507 | I40: =G40-H40 -> 273
F41: 45413 | G41: 851 | H41: 553 | I41: =G41-H41 -> 298
F42: 45444 | G42: 780 | H42: =G42*0.65 -> 507 | I42: =G42-H42 -> 273
F43: 45474 | G43: 900 | H43: =G43*0.65 -> 585 | I43: =G43-H43 -> 315
F44: 45505 | G44: 924 | H44: 600 | I44: =G44-H44 -> 324
F45: 45536 | G45: 882 | H45: 573 | I45: =G45-H45 -> 309
F46: 45566 | G46: 767 | H46: 983 | I46: =G46-H46 -> -216
F47: 45597 | G47: 708 | H47: 437 | I47: =G47-H47 -> 271
F48: 45627 | G48: 800 | H48: 506 | I48: =G48-H48 -> 294
F49: 45658 | G49: 730 | H49: 410 | I49: =G49-H49 -> 320
F50: 45689 | G50: 910 | H50: 477 | I50: =G50-H50 -> 433
F51: 45717 | G51: 1060 | H51: 579 | I51: =G51-H51 -> 481
F52: 45748 | G52: 900 | H52: 580 | I52: =G52-H52 -> 320
F53: 45778 | G53: 798 | H53: 798 | I53: =G53-H53 -> 0
I55: =SUM(I38:I54) -> 4138

Sheet Stock
B2: January | G2: Febraury | L2: March | Q2: April | V2: May | AA2: June | AF2: July | AK2: August | AP2: September | AU2: October | AZ2: November | BE2: December
A3: Item | B3: Quantity | C3: Price | D3: Unit Price | E3: Balance | G3: Quantity | H3: Price | I3: Unit Price | J3: Balance | L3: Quantity | M3: Price | N3: Unit Price | O3: Balance | Q3: Quantity | R3: Price | S3: Unit Price | T3: Balance | V3: Quantity | W3: Price | X3: Unit Price | Y3: Balance | AA3: Quantity | AB3: Price | AC3: Unit Price | AD3: Balance | AF3: Quantity | AG3: Price | AH3: Unit Price | AI3: Balance | AK3: Quantity | AL3: Price | AM3: Unit Price | AN3: Balance | AP3: Quantity | AQ3: Price | AR3: Unit Price | AS3: Balance | AU3: Quantity | AV3: Price | AW3: Unit Price | AX3: Balance | AZ3: Quantity | BA3: Price | BB3: Unit Price | BC3: Balance | BE3: Quantity | BF3: Price | BG3: Unit Price | BH3: Balance
A4: Sauces
A5: Green Chilli Sauce | B5: 8 | C5: 288 | D5: =IFERROR(C5/B5,0) -> 36 | E5: 1 | G5: 10 | H5: 360 | I5: =IFERROR(H5/G5,0) -> 36 | J5: 3 | L5: 8 | M5: 288 | N5: =IFERROR(M5/L5,0) -> 36 | O5: 0 | Q5: 10 | R5: 360 | S5: =IFERROR(R5/Q5,0) -> 36 | T5: 0 | V5: 13 | W5: 468 | X5: =IFERROR(W5/V5,0) -> 36 | Y5: 1 | AA5: 12 | AB5: 432 | AC5: =IFERROR(AB5/AA5,0) -> 36 | AD5: 2 | AF5: 10 | AG5: 370 | AH5: =IFERROR(AG5/AF5,0) -> 37 | AI5: 2 | AK5: 12 | AL5: 444 | AM5: =IFERROR(AL5/AK5,0) -> 37 | AN5: 1 | AP5: 12 | AQ5: 444 | AR5: =IFERROR(AQ5/AP5,0) -> 37 | AS5: 4 | AU5: 8 | AV5: 296 | AW5: =IFERROR(AV5/AU5,0) -> 37 | AX5: 1 | AZ5: 12 | BA5: 444 | BB5: =IFERROR(BA5/AZ5,0) -> 37 | BC5: 1 | BE5: 11 | BF5: 407 | BG5: =IFERROR(BF5/BE5,0) -> 37 | BH5: 1
A6: Red Chilli Sauce | B6: 5 | C6: 200 | D6: =IFERROR(C6/B6,0) -> 40 | E6: 1 | G6: 12 | H6: 480 | I6: =IFERROR(H6/G6,0) -> 40 | J6: 5 | L6: 5 | M6: 200 | N6: =IFERROR(M6/L6,0) -> 40 | O6: 0 | Q6: 7 | R6: 280 | S6: =IFERROR(R6/Q6,0) -> 40 | T6: 1 | V6: 10 | W6: 400 | X6: =IFERROR(W6/V6,0) -> 40 | Y6: 1 | AA6: 10 | AB6: 400 | AC6: =IFERROR(AB6/AA6,0) -> 40 | AD6: 5 | AF6: 6 | AG6: 240 | AH6: =IFERROR(AG6/AF6,0) -> 40 | AI6: 3 | AK6: 8 | AL6: 320 | AM6: =IFERROR(AL6/AK6,0) -> 40 | AN6: 3 | AP6: 8 | AQ6: 320 | AR6: =IFERROR(AQ6/AP6,0) -> 40 | AS6: 6 | AU6: 6 | AV6: 240 | AW6: =IFERROR(AV6/AU6,0) -> 40 | AX6: 6 | AZ6: 6 | BA6: 240 | BB6: =IFERROR(BA6/AZ6,0) -> 40 | BC6: 10 | BE6: 2 | BF6: 80 | BG6: =IFERROR(BF6/BE6,0) -> 40 | BH6: 12
A7: Capsicum Sauce | B7: 0 | C7: 0 | D7: =IFERROR(C7/B7,0) -> 0 | E7: 2 | G7: 8 | H7: 320 | I7: =IFERROR(H7/G7,0) -> 40 | J7: 4 | L7: 4 | M7: 160 | N7: =IFERROR(M7/L7,0) -> 40 | O7: 0 | Q7: 8 | R7: 320 | S7: =IFERROR(R7/Q7,0) -> 40 | T7: 2 | V7: 10 | W7: 400 | X7: =IFERROR(W7/V7,0) -> 40 | Y7: 6 | AA7: 6 | AB7: 240 | AC7: =IFERROR(AB7/AA7,0) -> 40 | AD7: 6 | AF7: 6 | AG7: =AC7*AF7 -> 240 | AH7: =IFERROR(AG7/AF7,0) -> 40 | AI7: 6 | AK7: 6 | AL7: 240 | AM7: =IFERROR(AL7/AK7,0) -> 40 | AN7: 6 | AP7: 6 | AQ7: 240 | AR7: =IFERROR(AQ7/AP7,0) -> 40 | AS7: 5 | AU7: 7 | AV7: 280 | AW7: =IFERROR(AV7/AU7,0) -> 40 | AX7: 10 | AZ7: 0 | BA7: 0 | BB7: =IFERROR(BA7/AZ7,0) -> 0 | BC7: 6 | BE7: 4 | BF7: 160 | BG7: =IFERROR(BF7/BE7,0) -> 40 | BH7: 4
A8: Tomato Sauce | B8: 6 | C8: 480 | D8: =IFERROR(C8/B8,0) -> 80 | E8: 1 | G8: 12 | H8: 900 | I8: =IFERROR(H8/G8,0) -> 75 | J8: 8 | L8: 0 | M8: 0 | N8: =IFERROR(M8/L8,0) -> 0 | O8: 0 | Q8: 10 | R8: 800 | S8: =IFERROR(R8/Q8,0) -> 80 | T8: 1 | V8: 12 | W8: 960 | X8: =IFERROR(W8/V8,0) -> 80 | Y8: 2 | AA8: 9 | AB8: 720 | AC8: =IFERROR(AB8/AA8,0) -> 80 | AD8: 3 | AF8: 8 | AG8: =AC8*AF8 -> 640 | AH8: =IFERROR(AG8/AF8,0) -> 80 | AI8: 2 | AK8: 9 | AL8: 720 | AM8: =IFERROR(AL8/AK8,0) -> 80 | AN8: 2 | AP8: 9 | AQ8: 810 | AR8: =IFERROR(AQ8/AP8,0) -> 90 | AS8: 6 | AU8: 6 | AV8: 480 | AW8: =IFERROR(AV8/AU8,0) -> 80 | AX8: 1 | AZ8: 12 | BA8: 900 | BB8: =IFERROR(BA8/AZ8,0) -> 75 | BC8: 5 | BE8: 8 | BF8: 640 | BG8: =IFERROR(BF8/BE8,0) -> 80 | BH8: 4
A9: 8to8 Sauce | B9: 2 | C9: 110 | D9: =IFERROR(C9/B9,0) -> 55 | E9: 1 | G9: 5 | H9: 275 | I9: =IFERROR(H9/G9,0) -> 55 | J9: 2 | L9: 3 | M9: 165 | N9: =IFERROR(M9/L9,0) -> 55 | O9: 0 | Q9: 4 | R9: 220 | S9: =IFERROR(R9/Q9,0) -> 55 | T9: 0 | V9: 5 | W9: 275 | X9: =IFERROR(W9/V9,0) -> 55 | Y9: 1 | AA9: 4 | AB9: 220 | AC9: =IFERROR(AB9/AA9,0) -> 55 | AD9: 2 | AF9: 3 | AG9: =AC9*AF9 -> 165 | AH9: =IFERROR(AG9/AF9,0) -> 55 | AI9: 3 | AK9: 2 | AL9: 110 | AM9: =IFERROR(AL9/AK9,0) -> 55 | AN9: 4 | AP9: 1 | AQ9: 55 | AR9: =IFERROR(AQ9/AP9,0) -> 55 | AS9: 2 | AU9: 3 | AV9: 165 | AW9: =IFERROR(AV9/AU9,0) -> 55 | AX9: 0 | AZ9: 5 | BA9: 275 | BB9: =IFERROR(BA9/AZ9,0) -> 55 | BC9: 3 | BE9: 2 | BF9: 110 | BG9: =IFERROR(BF9/BE9,0) -> 55 | BH9: 2
A10: Soya Sauce | B10: 0 | C10: 0 | D10: =IFERROR(C10/B10,0) -> 0 | E10: 6 | G10: 0 | H10: 0 | I10: =IFERROR(H10/G10,0) -> 0 | J10: 4 | L10: 0 | M10: 0 | N10: =IFERROR(M10/L10,0) -> 0 | O10: 0 | Q10: 3 | R10: 114 | S10: =IFERROR(R10/Q10,0) -> 38 | T10: 1 | V10: 4 | W10: 152 | X10: =IFERROR(W10/V10,0) -> 38 | Y10: 2 | AA10: 3 | AB10: 120 | AC10: =IFERROR(AB10/AA10,0) -> 40 | AD10: 4 | AF10: 1 | AG10: 38 | AH10: =IFERROR(AG10/AF10,0) -> 38 | AI10: 3 | AK10: 2 | AL10: 76 | AM10: =IFERROR(AL10/AK10,0) -> 38 | AN10: 3 | AP10: 2 | AQ10: 76 | AR10: =IFERROR(AQ10/AP10,0) -> 38 | AS10: 4 | AU10: 2 | AV10: 76 | AW10: =IFERROR(AV10/AU10,0) -> 38 | AX10: 5 | AZ10: 0 | BA10: 0 | BB10: =IFERROR(BA10/AZ10,0) -> 0 | BC10: 3 | BE10: 2 | BF10: 76 | BG10: =IFERROR(BF10/BE10,0) -> 38 | BH10: 4
A11: Vinegar | B11: 0 | C11: 0 | D11: =IFERROR(C11/B11,0) -> 0 | E11: 3 | G11: 3 | H11: 75 | I11: =IFERROR(H11/G11,0) -> 25 | J11: 2 | L11: 3 | M11: 75 | N11: =IFERROR(M11/L11,0) -> 25 | O11: 0 | Q11: 3 | R11: 75 | S11: =IFERROR(R11/Q11,0) -> 25 | T11: 2 | V11: 6 | W11: 150 | X11: =IFERROR(W11/V11,0) -> 25 | Y11: 2 | AA11: 6 | AB11: 90 | AC11: =IFERROR(AB11/AA11,0) -> 15 | AD11: 6 | AF11: 2 | AG11: 50 | AH11: =IFERROR(AG11/AF11,0) -> 25 | AI11: 8 | AK11: 0 | AL11: 0 | AM11: =IFERROR(AL11/AK11,0) -> 0 | AN11: 6 | AP11: 0 | AQ11: 0 | AR11: =IFERROR(AQ11/AP11,0) -> 0 | AS11: 5 | AU11: 0 | AV11: 0 | AW11: =IFERROR(AV11/AU11,0) -> 0 | AX11: 3 | AZ11: 0 | BA11: 0 | BB11: =IFERROR(BA11/AZ11,0) -> 0 | BC11: 4 | BE11: 0 | BF11: 0 | BG11: =IFERROR(BF11/BE11,0) -> 0 | BH11: 2
A12: Schezwan Sauce | B12: 2 | C12: 180 | D12: =IFERROR(C12/B12,0) -> 90 | E12: 2 | G12: 2 | H12: 180 | I12: =IFERROR(H12/G12,0) -> 90 | J12: 1 | L12: 3 | M12: 270 | N12: =IFERROR(M12/L12,0) -> 90 | O12: 0 | Q12: 3 | R12: 270 | S12: =IFERROR(R12/Q12,0) -> 90 | T12: 1 | V12: 4 | W12: 360 | X12: =IFERROR(W12/V12,0) -> 90 | Y12: 1 | AA12: 4 | AB12: 360 | AC12: =IFERROR(AB12/AA12,0) -> 90 | AD12: 2 | AF12: 3 | AG12: =AC12*AF12 -> 270 | AH12: =IFERROR(AG12/AF12,0) -> 90 | AI12: 2 | AK12: 3 | AL12: 270 | AM12: =IFERROR(AL12/AK12,0) -> 90 | AN12: 1 | AP12: 4 | AQ12: 150 | AR12: =IFERROR(AQ12/AP12,0) -> 37.5 | AS12: 0 | AU12: 5 | AV12: 450 | AW12: =IFERROR(AV12/AU12,0) -> 90 | AX12: 1 | AZ12: 5 | BA12: 750 | BB12: =IFERROR(BA12/AZ12,0) -> 150 | BC12: 3 | BE12: 0 | BF12: 0 | BG12: =IFERROR(BF12/BE12,0) -> 0 | BH12: 2
A13: Rose Water | B13: 1 | C13: 70 | D13: =IFERROR(C13/B13,0) -> 70 | E13: 1 | G13: 2 | H13: 140 | I13: =IFERROR(H13/G13,0) -> 70 | J13: 0 | L13: 3 | M13: 210 | N13: =IFERROR(M13/L13,0) -> 70 | O13: 0 | Q13: 2 | R13: 140 | S13: =IFERROR(R13/Q13,0) -> 70 | T13: 2 | V13: 1 | W13: 70 | X13: =IFERROR(W13/V13,0) -> 70 | Y13: 0 | AA13: 3 | AB13: 210 | AC13: =IFERROR(AB13/AA13,0) -> 70 | AD13: 1 | AF13: 5 | AG13: =AC13*AF13 -> 350 | AH13: =IFERROR(AG13/AF13,0) -> 70 | AI13: 0 | AK13: 9 | AL13: 630 | AM13: =IFERROR(AL13/AK13,0) -> 70 | AN13: 3 | AP13: 3 | AQ13: 210 | AR13: =IFERROR(AQ13/AP13,0) -> 70 | AS13: 4 | AU13: 10 | AV13: 700 | AW13: =IFERROR(AV13/AU13,0) -> 70 | AX13: 3 | AZ13: 6 | BA13: 420 | BB13: =IFERROR(BA13/AZ13,0) -> 70 | BC13: 4 | BE13: 5 | BF13: 350 | BG13: =IFERROR(BF13/BE13,0) -> 70 | BH13: 3
A14: Kewada water | B14: 1 | C14: 70 | D14: =IFERROR(C14/B14,0) -> 70 | E14: 1 | G14: 2 | H14: 140 | I14: =IFERROR(H14/G14,0) -> 70 | J14: 1 | L14: 2 | M14: 140 | N14: =IFERROR(M14/L14,0) -> 70 | O14: 0 | Q14: 2 | R14: 140 | S14: =IFERROR(R14/Q14,0) -> 70 | T14: 1 | V14: 2 | W14: 140 | X14: =IFERROR(W14/V14,0) -> 70 | Y14: 0 | AA14: 3 | AB14: 210 | AC14: =IFERROR(AB14/AA14,0) -> 70 | AD14: 0 | AF14: 6 | AG14: =AC14*AF14 -> 420 | AH14: =IFERROR(AG14/AF14,0) -> 70 | AI14: 0 | AK14: 9 | AL14: 630 | AM14: =IFERROR(AL14/AK14,0) -> 70 | AN14: 3 | AP14: 3 | AQ14: 210 | AR14: =IFERROR(AQ14/AP14,0) -> 70 | AS14: 4 | AU14: 10 | AV14: 700 | AW14: =IFERROR(AV14/AU14,0) -> 70 | AX14: 3 | AZ14: 6 | BA14: 420 | BB14: =IFERROR(BA14/AZ14,0) -> 70 | BC14: 4 | BE14: 5 | BF14: 350 | BG14: =IFERROR(BF14/BE14,0) -> 70 | BH14: 3
A15: Garam Masala (kg) | B15: 0 | C15: 0 | D15: =IFERROR(C15/B15,0) -> 0 | E15: 2 | G15: 1 | H15: 250 | I15: =IFERROR(H15/G15,0) -> 250 | J15: 2 | L15: 0 | M15: 0 | N15: =IFERROR(M15/L15,0) -> 0 | O15: 0 | Q15: 1 | R15: 250 | S15: =IFERROR(R15/Q15,0) -> 250 | T15: 1 | V15: 1 | W15: 250 | X15: =IFERROR(W15/V15,0) -> 250 | Y15: 0 | AA15: 2 | AB15: 500 | AC15: =IFERROR(AB15/AA15,0) -> 250 | AD15: 1 | AF15: 1 | AG15: =AC15*AF15 -> 250 | AH15: =IFERROR(AG15/AF15,0) -> 250 | AI15: 0 | AK15: 3 | AL15: 780 | AM15: =IFERROR(AL15/AK15,0) -> 260 | AN15: 1 | AP15: 2 | AQ15: 500 | AR15: =IFERROR(AQ15/AP15,0) -> 250 | AS15: 4.4 | AU15: 0 | AV15: 0 | AW15: =IFERROR(AV15/AU15,0) -> 0 | AX15: 2 | AZ15: 0 | BA15: 0 | BB15: =IFERROR(BA15/AZ15,0) -> 0 | BC15: 2 | BE15: 0 | BF15: 0 | BG15: =IFERROR(BF15/BE15,0) -> 0 | BH15: 1
A16: White pepper (kg) | B16: 1 | C16: 130 | D16: =IFERROR(C16/B16,0) -> 130 | E16: 1.5 | G16: 1.5 | H16: 105 | I16: =IFERROR(H16/G16,0) -> 70 | J16: 2 | L16: 0 | M16: 0 | N16: =IFERROR(M16/L16,0) -> 0 | O16: 0 | Q16: 3 | R16: 390 | S16: =IFERROR(R16/Q16,0) -> 130 | T16: 0.5 | V16: 2.5 | W16: 325 | X16: =IFERROR(W16/V16,0) -> 130 | Y16: 0.5 | AA16: 3 | AB16: 210 | AC16: =IFERROR(AB16/AA16,0) -> 70 | AD16: 1 | AF16: 2.5 | AG16: 325 | AH16: =IFERROR(AG16/AF16,0) -> 130 | AI16: 1 | AK16: 2.5 | AL16: 325 | AM16: =IFERROR(AL16/AK16,0) -> 130 | AN16: 1 | AP16: 2.5 | AQ16: 325 | AR16: =IFERROR(AQ16/AP16,0) -> 130 | AS16: 2 | AU16: 2 | AV16: 260 | AW16: =IFERROR(AV16/AU16,0) -> 130 | AX16: 0.5 | AZ16: 3 | BA16: 210 | BB16: =IFERROR(BA16/AZ16,0) -> 70 | BC16: 2 | BE16: 2 | BF16: 140 | BG16: =IFERROR(BF16/BE16,0) -> 70 | BH16: 0.5
A17: Chicken Masala (kg) | B17: 2 | C17: 1300 | D17: =IFERROR(C17/B17,0) -> 650 | E17: 0.4 | G17: 3 | H17: 1950 | I17: =IFERROR(H17/G17,0) -> 650 | J17: 2 | L17: 1 | M17: 630 | N17: =IFERROR(M17/L17,0) -> 630 | O17: 0 | Q17: 2 | R17: 1260 | S17: =IFERROR(R17/Q17,0) -> 630 | T17: 1 | V17: 3 | W17: 1890 | X17: =IFERROR(W17/V17,0) -> 630 | Y17: 0 | AA17: 3 | AB17: 1950 | AC17: =IFERROR(AB17/AA17,0) -> 650 | AD17: 1 | AF17: 3 | AG17: =AC17*AF17 -> 1950 | AH17: =IFERROR(AG17/AF17,0) -> 650 | AI17: 0.5 | AK17: =6+1 -> 7 | AL17: =3900+300 -> 4200 | AM17: =IFERROR(AL17/AK17,0) -> 600 | AN17: 2 | AP17: 0 | AQ17: 0 | AR17: =IFERROR(AQ17/AP17,0) -> 0 | AS17: 1 | AU17: 2 | AV17: 1300 | AW17: =IFERROR(AV17/AU17,0) -> 650 | AX17: 0 | AZ17: 3 | BA17: 1950 | BB17: =IFERROR(BA17/AZ17,0) -> 650 | BC17: 1 | BE17: 2 | BF17: 1300 | BG17: =IFERROR(BF17/BE17,0) -> 650 | BH17: 0
A18: Mutton Masala (kg) | B18: 1 | C18: 650 | D18: =IFERROR(C18/B18,0) -> 650 | E18: 2 | G18: 1 | H18: 650 | I18: =IFERROR(H18/G18,0) -> 650 | J18: 2 | L18: 0 | M18: 0 | N18: =IFERROR(M18/L18,0) -> 0 | O18: 0 | Q18: 1 | R18: 630 | S18: =IFERROR(R18/Q18,0) -> 630 | T18: 0 | V18: 2 | W18: 1260 | X18: =IFERROR(W18/V18,0) -> 630 | Y18: 0 | AA18: 2 | AB18: 1300 | AC18: =IFERROR(AB18/AA18,0) -> 650 | AD18: 0 | AF18: 3 | AG18: =AC18*AF18 -> 1950 | AH18: =IFERROR(AG18/AF18,0) -> 650 | AI18: 0 | AK18: 4 | AL18: 2520 | AM18: =IFERROR(AL18/AK18,0) -> 630 | AN18: 2 | AP18: 0 | AQ18: 0 | AR18: =IFERROR(AQ18/AP18,0) -> 0 | AS18: 0 | AU18: 2 | AV18: 1300 | AW18: =IFERROR(AV18/AU18,0) -> 650 | AX18: 0 | AZ18: 3 | BA18: 1950 | BB18: =IFERROR(BA18/AZ18,0) -> 650 | BC18: 1 | BE18: 2 | BF18: 1300 | BG18: =IFERROR(BF18/BE18,0) -> 650 | BH18: 1
A19: Tandoori Chicken Masala (kg) | B19: 0 | C19: 0 | D19: =IFERROR(C19/B19,0) -> 0 | E19: 1 | G19: 0 | H19: 0 | I19: =IFERROR(H19/G19,0) -> 0 | J19: 0 | L19: 1 | M19: 630 | N19: =IFERROR(M19/L19,0) -> 630 | O19: 0 | Q19: 0 | R19: 0 | S19: =IFERROR(R19/Q19,0) -> 0 | T19: 1 | V19: 1 | W19: 650 | X19: =IFERROR(W19/V19,0) -> 650 | Y19: 2 | AA19: 0 | AB19: 0 | AC19: =IFERROR(AB19/AA19,0) -> 0 | AD19: 1 | AF19: 1 | AG19: =650*AF19 -> 650 | AH19: =IFERROR(AG19/AF19,0) -> 650 | AI19: 2 | AK19: 1 | AL19: 650 | AM19: =IFERROR(AL19/AK19,0) -> 650 | AN19: 2 | AP19: 0 | AQ19: 0 | AR19: =IFERROR(AQ19/AP19,0) -> 0 | AS19: 3 | AU19: 0 | AV19: 0 | AW19: =IFERROR(AV19/AU19,0) -> 0 | AX19: 1 | AZ19: 0 | BA19: 0 | BB19: =IFERROR(BA19/AZ19,0) -> 0 | BC19: 2 | BE19: 0 | BF19: 0 | BG19: =IFERROR(BF19/BE19,0) -> 0 | BH19: 1
A20: Chat Masala (kg) | B20: 1 | C20: 550 | D20: =IFERROR(C20/B20,0) -> 550 | E20: 1 | G20: 2 | H20: 1100 | I20: =IFERROR(H20/G20,0) -> 550 | J20: 3 | L20: 0 | M20: 0 | N20: =IFERROR(M20/L20,0) -> 0 | O20: 0 | Q20: 3 | R20: 1650 | S20: =IFERROR(R20/Q20,0) -> 550 | T20: 2 | V20: 1 | W20: 550 | X20: =IFERROR(W20/V20,0) -> 550 | Y20: 1 | AA20: 0 | AB20: 0 | AC20: =IFERROR(AB20/AA20,0) -> 0 | AD20: 2 | AF20: 0 | AG20: =AC20*AF20 -> 0 | AH20: =IFERROR(AG20/AF20,0) -> 0 | AI20: 0 | AK20: =2+0.2 -> 2.2 | AL20: =1100+150 -> 1250 | AM20: =IFERROR(AL20/AK20,0) -> 568.18182 | AN20: 0 | AP20: 1 | AQ20: 550 | AR20: =IFERROR(AQ20/AP20,0) -> 550 | AS20: 0 | AU20: 1 | AV20: 550 | AW20: =IFERROR(AV20/AU20,0) -> 550 | AX20: 0 | AZ20: 1 | BA20: 550 | BB20: =IFERROR(BA20/AZ20,0) -> 550 | BC20: 1 | BE20: 0 | BF20: 0 | BG20: =IFERROR(BF20/BE20,0) -> 0 | BH20: 1
A21: Corn Powder (kg) | B21: 12 | C21: 588 | D21: =IFERROR(C21/B21,0) -> 49 | E21: 0 | G21: 25 | H21: 1225 | I21: =IFERROR(H21/G21,0) -> 49 | J21: 11 | L21: 15 | M21: 720 | N21: =IFERROR(M21/L21,0) -> 48 | O21: 0 | Q21: 13 | R21: 611 | S21: =IFERROR(R21/Q21,0) -> 47 | T21: 6 | V21: 20 | W21: 940 | X21: =IFERROR(W21/V21,0) -> 47 | Y21: 5 | AA21: 20 | AB21: 940 | AC21: =IFERROR(AB21/AA21,0) -> 47 | AD21: 10 | AF21: 15 | AG21: =AC21*AF21 -> 705 | AH21: =IFERROR(AG21/AF21,0) -> 47 | AI21: 8 | AK21: 17 | AL21: 799 | AM21: =IFERROR(AL21/AK21,0) -> 47 | AN21: 5 | AP21: 20 | AQ21: 920 | AR21: =IFERROR(AQ21/AP21,0) -> 46 | AS21: 13 | AU21: 15 | AV21: 690 | AW21: =IFERROR(AV21/AU21,0) -> 46 | AX21: 10 | AZ21: 15 | BA21: 675 | BB21: =IFERROR(BA21/AZ21,0) -> 45 | BC21: 10 | BE21: 15 | BF21: 645 | BG21: =IFERROR(BF21/BE21,0) -> 43 | BH21: 14
A22: Tasting salt (kg) | B22: 5 | C22: 900 | D22: =IFERROR(C22/B22,0) -> 180 | E22: 0 | G22: 6 | H22: 1020 | I22: =IFERROR(H22/G22,0) -> 170 | J22: 2 | L22: 4 | M22: 680 | N22: =IFERROR(M22/L22,0) -> 170 | O22: 0 | Q22: 5 | R22: 850 | S22: =IFERROR(R22/Q22,0) -> 170 | T22: 0 | V22: 6 | W22: 1020 | X22: =IFERROR(W22/V22,0) -> 170 | Y22: 0 | AA22: 4 | AB22: 720 | AC22: =IFERROR(AB22/AA22,0) -> 180 | AD22: 0 | AF22: 7 | AG22: =680+510 -> 1190 | AH22: =IFERROR(AG22/AF22,0) -> 170 | AI22: 0 | AK22: =10+1 -> 11 | AL22: =1700+160 -> 1860 | AM22: =IFERROR(AL22/AK22,0) -> 169.09091 | AN22: 0 | AP22: 5 | AQ22: 850 | AR22: =IFERROR(AQ22/AP22,0) -> 170 | AS22: 1 | AU22: 5 | AV22: 850 | AW22: =IFERROR(AV22/AU22,0) -> 170 | AX22: 0 | AZ22: 3 | BA22: 510 | BB22: =IFERROR(BA22/AZ22,0) -> 170 | BC22: 0 | BE22: 3 | BF22: 510 | BG22: =IFERROR(BF22/BE22,0) -> 170 | BH22: 0
A23: Red Color (box) | B23: 0 | C23: 0 | D23: =IFERROR(C23/B23,0) -> 0 | E23: 2 | G23: 6 | H23: 360 | I23: =IFERROR(H23/G23,0) -> 60 | J23: 3 | L23: 5 | M23: 300 | N23: =IFERROR(M23/L23,0) -> 60 | O23: 0 | Q23: 5 | R23: 300 | S23: =IFERROR(R23/Q23,0) -> 60 | T23: 4 | V23: 4 | W23: 240 | X23: =IFERROR(W23/V23,0) -> 60 | Y23: 3 | AA23: 5 | AB23: 300 | AC23: =IFERROR(AB23/AA23,0) -> 60 | AD23: 3 | AF23: 5 | AG23: =AC23*AF23 -> 300 | AH23: =IFERROR(AG23/AF23,0) -> 60 | AI23: 4 | AK23: 5 | AL23: 300 | AM23: =IFERROR(AL23/AK23,0) -> 60 | AN23: 3 | AP23: 7 | AQ23: 420 | AR23: =IFERROR(AQ23/AP23,0) -> 60 | AS23: 5 | AU23: 5 | AV23: 300 | AW23: =IFERROR(AV23/AU23,0) -> 60 | AX23: 4 | AZ23: 2 | BA23: 120 | BB23: =IFERROR(BA23/AZ23,0) -> 60 | BC23: 8 | BE23: 0 | BF23: 0 | BG23: =IFERROR(BF23/BE23,0) -> 0 | BH23: 5
A24: Yellow Color (box) | B24: 5 | C24: 300 | D24: =IFERROR(C24/B24,0) -> 60 | E24: 4 | G24: 2 | H24: 120 | I24: =IFERROR(H24/G24,0) -> 60 | J24: 6 | L24: 0 | M24: 0 | N24: =IFERROR(M24/L24,0) -> 0 | O24: 0 | Q24: 6 | R24: 360 | S24: =IFERROR(R24/Q24,0) -> 60 | T24: 0 | V24: 6 | W24: 360 | X24: =IFERROR(W24/V24,0) -> 60 | Y24: 3 | AA24: 3 | AB24: 180 | AC24: =IFERROR(AB24/AA24,0) -> 60 | AD24: 3 | AF24: 3 | AG24: =AC24*AF24 -> 180 | AH24: =IFERROR(AG24/AF24,0) -> 60 | AI24: 0 | AK24: 10 | AL24: 600 | AM24: =IFERROR(AL24/AK24,0) -> 60 | AN24: 3 | AP24: 7 | AQ24: 420 | AR24: =IFERROR(AQ24/AP24,0) -> 60 | AS24: 6 | AU24: 6 | AV24: 360 | AW24: =IFERROR(AV24/AU24,0) -> 60 | AX24: 4 | AZ24: 6 | BA24: 360 | BB24: =IFERROR(BA24/AZ24,0) -> 60 | BC24: 8 | BE24: 0 | BF24: 0 | BG24: =IFERROR(BF24/BE24,0) -> 0 | BH24: 1
A25: Main Items
A26: Biryani Rice (kg) | B26: =338+25+75 -> 438 | C26: =30420+400+1600+3240 -> 35660 | D26: =IFERROR(C26/B26,0) -> 81.415525 | E26: 95 | G26: =(26*6)+(3*25) -> 231 | H26: =(26*8*90) -> 18720 | I26: =IFERROR(H26/G26,0) -> 81.038961 | J26: 166 | L26: 156 | M26: =26*90*6 -> 14040 | N26: =IFERROR(M26/L26,0) -> 90 | O26: 0 | Q26: 130 | R26: =26*90*5 -> 11700 | S26: =IFERROR(R26/Q26,0) -> 90 | T26: 26 | V26: =(26*12)+25 -> 337 | W26: =(26*12*90)+1600 -> 29680 | X26: =IFERROR(W26/V26,0) -> 88.071217 | Y26: 96 | AA26: =26*6 -> 156 | AB26: =AA26*90 -> 14040 | AC26: =IFERROR(AB26/AA26,0) -> 90 | AD26: 70 | AF26: =(26*9)+(30*2) -> 294 | AG26: =AC26*AF26 -> 26460 | AH26: =IFERROR(AG26/AF26,0) -> 90 | AI26: 199 | AK26: =30*18+52 -> 592 | AL26: =540*90+2060 -> 50660 | AM26: =IFERROR(AL26/AK26,0) -> 85.574324 | AN26: 0 | AP26: =12*30 -> 360 | AQ26: =AP26*93 -> 33480 | AR26: =IFERROR(AQ26/AP26,0) -> 93 | AS26: 90 | AU26: 300 | AV26: =AU26*91+2040 -> 29340 | AW26: =IFERROR(AV26/AU26,0) -> 97.8 | AX26: 115 | AZ26: =2*30 -> 60 | BA26: =AZ26*92 -> 5520 | BB26: =IFERROR(BA26/AZ26,0) -> 92 | BC26: 0 | BE26: =6*30 -> 180 | BF26: =BE26*92 -> 16560 | BG26: =IFERROR(BF26/BE26,0) -> 92 | BH26: 0
A27: Oil (L) | B27: 150 | C27: =9200+9350 -> 18550 | D27: =IFERROR(C27/B27,0) -> 123.66667 | E27: 6 | G27: 135 | H27: 16650 | I27: =IFERROR(H27/G27,0) -> 123.33333 | J27: 38 | L27: 105 | M27: 12600 | N27: =IFERROR(M27/L27,0) -> 120 | O27: 0 | Q27: 120 | R27: =1700*8 -> 13600 | S27: =IFERROR(R27/Q27,0) -> 113.33333 | T27: 5 | V27: =150+20 -> 170 | W27: =(113*150)+2200 -> 19150 | X27: =IFERROR(W27/V27,0) -> 112.64706 | Y27: 4 | AA27: 102 | AB27: =AA27*110 -> 11220 | AC27: =IFERROR(AB27/AA27,0) -> 110 | AD27: 15 | AF27: =48+10+10+10+10+10+10+10+10+10 -> 138 | AG27: =1320+3600+1240+1240+1240+1240+1240+1270+1260+1250+1270 -> 16170 | AH27: =IFERROR(AG27/AF27,0) -> 117.17391 | AI27: 0 | AK27: 320 | AL27: =17300+18500-7400 -> 28400 | AM27: =IFERROR(AL27/AK27,0) -> 88.75 | AN27: 16 | AP27: =64+48 -> 112 | AQ27: =7400+5490 -> 12890 | AR27: =IFERROR(AQ27/AP27,0) -> 115.08929 | AS27: 18 | AU27: =20+160 -> 180 | AV27: =2980+17900 -> 20880 | AW27: =IFERROR(AV27/AU27,0) -> 116 | AX27: 45 | AZ27: =2*16 -> 32 | BA27: =AZ27*112.5 -> 3600 | BB27: =IFERROR(BA27/AZ27,0) -> 112.5 | BC27: 0 | BE27: =8*16 -> 128 | BF27: =BE27*112.5 -> 14400 | BG27: =IFERROR(BF27/BE27,0) -> 112.5 | BH27: 14
A28: Maida (kg) | B28: 30 | C28: 1985 | D28: =IFERROR(C28/B28,0) -> 66.166667 | E28: 25 | G28: 25 | H28: 1050 | I28: =IFERROR(H28/G28,0) -> 42 | J28: 22 | L28: 0 | M28: 0 | N28: =IFERROR(M28/L28,0) -> 0 | O28: 0 | Q28: 25 | R28: 1050 | S28: =IFERROR(R28/Q28,0) -> 42 | T28: 0 | V28: 25 | W28: 1050 | X28: =IFERROR(W28/V28,0) -> 42 | Y28: 0 | AA28: 25 | AB28: 1000 | AC28: =IFERROR(AB28/AA28,0) -> 40 | AD28: 0 | AF28: 25 | AG28: =AC28*AF28 -> 1000 | AH28: =IFERROR(AG28/AF28,0) -> 40 | AI28: 2 | AK28: 0 | AL28: 0 | AM28: =IFERROR(AL28/AK28,0) -> 0 | AN28: 0 | AP28: 0 | AQ28: 0 | AR28: =IFERROR(AQ28/AP28,0) -> 0 | AS28: 3 | AU28: 25 | AV28: 1000 | AW28: =IFERROR(AV28/AU28,0) -> 40 | AX28: 10 | AZ28: 15 | BA28: 660 | BB28: =IFERROR(BA28/AZ28,0) -> 44 | BC28: 7 | BE28: 10 | BF28: 400 | BG28: =IFERROR(BF28/BE28,0) -> 40 | BH28: 5
A29: Aata (kg) | B29: 15 | C29: 820 | D29: =IFERROR(C29/B29,0) -> 54.666667 | E29: 5 | G29: 15 | H29: 630 | I29: =IFERROR(H29/G29,0) -> 42 | J29: 8 | L29: 15 | M29: 615 | N29: =IFERROR(M29/L29,0) -> 41 | O29: 0 | Q29: 15 | R29: 630 | S29: =IFERROR(R29/Q29,0) -> 42 | T29: 5 | V29: 15 | W29: 585 | X29: =IFERROR(W29/V29,0) -> 39 | Y29: 8 | AA29: 20 | AB29: 760 | AC29: =IFERROR(AB29/AA29,0) -> 38 | AD29: 7 | AF29: 28 | AG29: =AC29*AF29 -> 1064 | AH29: =IFERROR(AG29/AF29,0) -> 38 | AI29: 25 | AK29: 0 | AL29: 0 | AM29: =IFERROR(AL29/AK29,0) -> 0 | AN29: 10 | AP29: 0 | AQ29: 0 | AR29: =IFERROR(AQ29/AP29,0) -> 0 | AS29: 7 | AU29: 5 | AV29: 200 | AW29: =IFERROR(AV29/AU29,0) -> 40 | AX29: 0 | AZ29: 5 | BA29: 0 | BB29: =IFERROR(BA29/AZ29,0) -> 0 | BC29: 0 | BE29: 3 | BF29: 120 | BG29: =IFERROR(BF29/BE29,0) -> 40 | BH29: 0.5
A30: Cold Drinks (cases) | B30: 15 | C30: 7275 | D30: =IFERROR(C30/B30,0) -> 485 | E30: 7 | G30: 9 | H30: 4365 | I30: =IFERROR(H30/G30,0) -> 485 | J30: 0 | L30: 8 | M30: 3880 | N30: =IFERROR(M30/L30,0) -> 485 | O30: 0 | Q30: 12 | R30: =12*485 -> 5820 | S30: =IFERROR(R30/Q30,0) -> 485 | T30: 0 | V30: 12 | W30: 5820 | X30: =IFERROR(W30/V30,0) -> 485 | Y30: 0 | AA30: 12 | AB30: 0 | AC30: =IFERROR(AB30/AA30,0) -> 0 | AD30: 0 | AF30: 12 | AG30: 5820 | AH30: =IFERROR(AG30/AF30,0) -> 485 | AI30: 0 | AK30: 0 | AL30: 0 | AM30: =IFERROR(AL30/AK30,0) -> 0 | AN30: 0 | AP30: 10 | AQ30: =AP30*486 -> 4860 | AR30: =IFERROR(AQ30/AP30,0) -> 486 | AS30: 0 | AU30: 17 | AV30: =AU30*485 -> 8245 | AW30: =IFERROR(AV30/AU30,0) -> 485 | AX30: 0 | AZ30: 0 | BA30: 0 | BB30: =IFERROR(BA30/AZ30,0) -> 0 | BC30: 0 | BE30: 0 | BF30: 0 | BG30: =IFERROR(BF30/BE30,0) -> 0 | BH30: 0
A31: Cold Drinks (bottles) | B31: 6 | C31: 1182 | D31: =IFERROR(C31/B31,0) -> 197 | E31: 1 | G31: 9 | H31: 1773 | I31: =IFERROR(H31/G31,0) -> 197 | J31: 0 | L31: 8 | M31: 1576 | N31: =IFERROR(M31/L31,0) -> 197 | O31: 0 | Q31: 12 | R31: =12*197 -> 2364 | S31: =IFERROR(R31/Q31,0) -> 197 | T31: 0 | V31: 16 | W31: 3152 | X31: =IFERROR(W31/V31,0) -> 197 | Y31: 0 | AA31: 12 | AB31: 0 | AC31: =IFERROR(AB31/AA31,0) -> 0 | AD31: 0 | AF31: 16 | AG31: 3152 | AH31: =IFERROR(AG31/AF31,0) -> 197 | AI31: 0 | AK31: 0 | AL31: 0 | AM31: =IFERROR(AL31/AK31,0) -> 0 | AN31: 0 | AP31: 14 | AQ31: =AP31*198 -> 2772 | AR31: =IFERROR(AQ31/AP31,0) -> 198 | AS31: 0 | AU31: 10 | AV31: =AU31*197 -> 1970 | AW31: =IFERROR(AV31/AU31,0) -> 197 | AX31: 0 | AZ31: 0 | BA31: 0 | BB31: =IFERROR(BA31/AZ31,0) -> 0 | BC31: 0 | BE31: 0 | BF31: 0 | BG31: =IFERROR(BF31/BE31,0) -> 0 | BH31: 0
A32: Cold Drinks (cans) | B32: 0 | C32: 0 | D32: =IFERROR(C32/B32,0) -> 0 | E32: 0 | G32: 0 | H32: 0 | I32: =IFERROR(H32/G32,0) -> 0 | J32: 0 | L32: 0 | M32: 0 | N32: =IFERROR(M32/L32,0) -> 0 | O32: 0 | Q32: 0 | R32: 0 | S32: =IFERROR(R32/Q32,0) -> 0 | T32: 0 | V32: 0 | W32: 0 | X32: =IFERROR(W32/V32,0) -> 0 | Y32: 0 | AA32: 0 | AB32: 0 | AC32: =IFERROR(AB32/AA32,0) -> 0 | AD32: 0 | AF32: 0 | AG32: 0 | AH32: =IFERROR(AG32/AF32,0) -> 0 | AI32: 0 | AK32: 0 | AL32: 0 | AM32: =IFERROR(AL32/AK32,0) -> 0 | AN32: 0 | AP32: 0 | AQ32: 0 | AR32: =IFERROR(AQ32/AP32,0) -> 0 | AS32: 0 | AU32: 0 | AV32: 0 | AW32: =IFERROR(AV32/AU32,0) -> 0 | AX32: 0 | AZ32: 0 | BA32: 0 | BB32: =IFERROR(BA32/AZ32,0) -> 0 | BC32: 0 | BE32: 0 | BF32: 0 | BG32: =IFERROR(BF32/BE32,0) -> 0 | BH32: 0
A33: Water Bottles (cases) | B33: 100 | C33: 13200 | D33: =IFERROR(C33/B33,0) -> 132 | E33: 43 | G33: 0 | H33: 0 | I33: =IFERROR(H33/G33,0) -> 0 | J33: 0 | L33: 40 | M33: =L33*132 -> 5280 | N33: =IFERROR(M33/L33,0) -> 132 | O33: 0 | Q33: 90 | R33: =Q33*132 -> 11880 | S33: =IFERROR(R33/Q33,0) -> 132 | T33: 0 | V33: 50 | W33: 6600 | X33: =IFERROR(W33/V33,0) -> 132 | Y33: 0 | AA33: 58 | AB33: =6600+960 -> 7560 | AC33: =IFERROR(AB33/AA33,0) -> 130.34483 | AD33: 0 | AF33: 59 | AG33: 7788 | AH33: =IFERROR(AG33/AF33,0) -> 132 | AI33: 0 | AK33: 50 | AL33: 6600 | AM33: =IFERROR(AL33/AK33,0) -> 132 | AN33: 0 | AP33: 50 | AQ33: 6600 | AR33: =IFERROR(AQ33/AP33,0) -> 132 | AS33: 0 | AU33: 50 | AV33: =50*132 -> 6600 | AW33: =IFERROR(AV33/AU33,0) -> 132 | AX33: 0 | AZ33: 0 | BA33: 0 | BB33: 0 | BC33: 0 | BE33: 50 | BF33: 6600 | BG33: =IFERROR(BF33/BE33,0) -> 132 | BH33: 0
A34: Alibeg
A35: Baby Kaju (kg) | B35: 2 | C35: 640 | D35: =IFERROR(C35/B35,0) -> 320 | E35: 0 | G35: 2 | H35: 600 | I35: =IFERROR(H35/G35,0) -> 300 | J35: 0 | L35: 2 | M35: 600 | N35: =IFERROR(M35/L35,0) -> 300 | O35: 0 | Q35: 2 | R35: 0 | S35: =IFERROR(R35/Q35,0) -> 0 | T35: 0 | V35: 2 | W35: 0 | X35: =IFERROR(W35/V35,0) -> 0 | Y35: 0 | AA35: 2 | AB35: 600 | AC35: =IFERROR(AB35/AA35,0) -> 300 | AD35: 0 | AF35: 2 | AG35: 620 | AH35: =IFERROR(AG35/AF35,0) -> 310 | AI35: 0 | AK35: 2 | AL35: 660 | AM35: =IFERROR(AL35/AK35,0) -> 330 | AN35: 0 | AP35: 2 | AQ35: 640 | AR35: =IFERROR(AQ35/AP35,0) -> 320 | AS35: 0 | AU35: 2 | AV35: 680 | AW35: =IFERROR(AV35/AU35,0) -> 340 | AX35: 0 | AZ35: 0 | BA35: 0 | BB35: =IFERROR(BA35/AZ35,0) -> 0 | BC35: 0 | BE35: 2 | BF35: 0 | BG35: =IFERROR(BF35/BE35,0) -> 0 | BH35: 0
A36: Kaju 4 pieces (kg) | B36: 4 | C36: 3080 | D36: =IFERROR(C36/B36,0) -> 770 | E36: 0 | G36: 7 | H36: 4970 | I36: =IFERROR(H36/G36,0) -> 710 | J36: 2 | L36: 5 | M36: 3750 | N36: =IFERROR(M36/L36,0) -> 750 | O36: 0 | Q36: 8 | R36: 5920 | S36: =IFERROR(R36/Q36,0) -> 740 | T36: 0 | V36: 10 | W36: 7500 | X36: =IFERROR(W36/V36,0) -> 750 | Y36: 0 | AA36: 6 | AB36: 4475 | AC36: =IFERROR(AB36/AA36,0) -> 745.83333 | AD36: 0.5 | AF36: 6 | AG36: 4320 | AH36: =IFERROR(AG36/AF36,0) -> 720 | AI36: 0 | AK36: =10+0.1 -> 10.1 | AL36: =7100+90 -> 7190 | AM36: =IFERROR(AL36/AK36,0) -> 711.88119 | AN36: 0 | AP36: 10 | AQ36: 7100 | AR36: =IFERROR(AQ36/AP36,0) -> 710 | AS36: 3 | AU36: 10 | AV36: 7100 | AW36: =IFERROR(AV36/AU36,0) -> 710 | AX36: 7.5 | AZ36: 2 | BA36: 0 | BB36: =IFERROR(BA36/AZ36,0) -> 0 | BC36: 0.5 | BE36: 10 | BF36: 7100 | BG36: =IFERROR(BF36/BE36,0) -> 710 | BH36: 8
A37: Haldi (kg) | B37: 0 | C37: 0 | D37: =IFERROR(C37/B37,0) -> 0 | E37: 1 | G37: 1 | H37: 250 | I37: =IFERROR(H37/G37,0) -> 250 | J37: 1.5 | L37: 0 | M37: 0 | N37: =IFERROR(M37/L37,0) -> 0 | O37: 0 | Q37: 1 | R37: 250 | S37: =IFERROR(R37/Q37,0) -> 250 | T37: 0.5 | V37: 1 | W37: 240 | X37: =IFERROR(W37/V37,0) -> 240 | Y37: 0.5 | AA37: 1 | AB37: 220 | AC37: =IFERROR(AB37/AA37,0) -> 220 | AD37: 0 | AF37: 1.5 | AG37: 360 | AH37: =IFERROR(AG37/AF37,0) -> 240 | AI37: 0 | AK37: 2 | AL37: 450 | AM37: =IFERROR(AL37/AK37,0) -> 225 | AN37: 0 | AP37: 2 | AQ37: 460 | AR37: =IFERROR(AQ37/AP37,0) -> 230 | AS37: 2 | AU37: 0 | AV37: 0 | AW37: =IFERROR(AV37/AU37,0) -> 0 | AX37: 1 | AZ37: 0 | BA37: 0 | BB37: =IFERROR(BA37/AZ37,0) -> 0 | BC37: 1 | BE37: 0 | BF37: 0 | BG37: =IFERROR(BF37/BE37,0) -> 0 | BH37: 0.5
A38: Jeera (kg) | B38: 0 | C38: 0 | D38: =IFERROR(C38/B38,0) -> 0 | E38: 0.5 | G38: 1 | H38: 330 | I38: =IFERROR(H38/G38,0) -> 330 | J38: 0.7 | L38: 1 | M38: 280 | N38: =IFERROR(M38/L38,0) -> 280 | O38: 0 | Q38: 0.2 | R38: 75 | S38: =IFERROR(R38/Q38,0) -> 375 | T38: 0 | V38: 2 | W38: 700 | X38: =IFERROR(W38/V38,0) -> 350 | Y38: 0.4 | AA38: 1 | AB38: 320 | AC38: =IFERROR(AB38/AA38,0) -> 320 | AD38: 1 | AF38: 0.5 | AG38: 180 | AH38: =IFERROR(AG38/AF38,0) -> 360 | AI38: 0.4 | AK38: 1.6 | AL38: 450 | AM38: =IFERROR(AL38/AK38,0) -> 281.25 | AN38: 0.9 | AP38: 1 | AQ38: 380 | AR38: =IFERROR(AQ38/AP38,0) -> 380 | AS38: 1 | AU38: 0 | AV38: 0 | AW38: =IFERROR(AV38/AU38,0) -> 0 | AX38: 1.1 | AZ38: 0 | BA38: 0 | BB38: =IFERROR(BA38/AZ38,0) -> 0 | BC38: 1 | BE38: 0 | BF38: 0 | BG38: =IFERROR(BF38/BE38,0) -> 0 | BH38: 0.9
A39: Til (kg) | B39: 1 | C39: 190 | D39: =IFERROR(C39/B39,0) -> 190 | E39: 0 | G39: 1 | H39: 250 | I39: =IFERROR(H39/G39,0) -> 250 | J39: 0 | L39: 1 | M39: 280 | N39: =IFERROR(M39/L39,0) -> 280 | O39: 0 | Q39: 1 | R39: 240 | S39: =IFERROR(R39/Q39,0) -> 240 | T39: 0 | V39: 1 | W39: 210 | X39: =IFERROR(W39/V39,0) -> 210 | Y39: 0 | AA39: 1 | AB39: 200 | AC39: =IFERROR(AB39/AA39,0) -> 200 | AD39: 0 | AF39: =1+1 -> 2 | AG39: =230+180 -> 410 | AH39: =IFERROR(AG39/AF39,0) -> 205 | AI39: 0 | AK39: 1 | AL39: 225 | AM39: =IFERROR(AL39/AK39,0) -> 225 | AN39: 0 | AP39: 1 | AQ39: 200 | AR39: =IFERROR(AQ39/AP39,0) -> 200 | AS39: 0 | AU39: 1 | AV39: 220 | AW39: =IFERROR(AV39/AU39,0) -> 220 | AX39: 0 | AZ39: 1 | BA39: 230 | BB39: =IFERROR(BA39/AZ39,0) -> 230 | BC39: 0 | BE39: 1 | BF39: 200 | BG39: =IFERROR(BF39/BE39,0) -> 200 | BH39: 0
A40: Charmagash (kg) | B40: 1 | C40: 650 | D40: =IFERROR(C40/B40,0) -> 650 | E40: 0 | G40: 1 | H40: 630 | I40: =IFERROR(H40/G40,0) -> 630 | J40: 0 | L40: 1 | M40: 630 | N40: =IFERROR(M40/L40,0) -> 630 | O40: 0 | Q40: 1 | R40: 630 | S40: =IFERROR(R40/Q40,0) -> 630 | T40: 0 | V40: 1 | W40: 660 | X40: =IFERROR(W40/V40,0) -> 660 | Y40: 0 | AA40: 1 | AB40: 770 | AC40: =IFERROR(AB40/AA40,0) -> 770 | AD40: 0 | AF40: =1+1 -> 2 | AG40: =760+662 -> 1422 | AH40: =IFERROR(AG40/AF40,0) -> 711 | AI40: 0 | AK40: 1 | AL40: 760 | AM40: =IFERROR(AL40/AK40,0) -> 760 | AN40: 0 | AP40: 1 | AQ40: 750 | AR40: =IFERROR(AQ40/AP40,0) -> 750 | AS40: 0 | AU40: 1 | AV40: 790 | AW40: =IFERROR(AV40/AU40,0) -> 790 | AX40: 0 | AZ40: 1 | BA40: 680 | BB40: =IFERROR(BA40/AZ40,0) -> 680 | BC40: 0 | BE40: 1 | BF40: 750 | BG40: =IFERROR(BF40/BE40,0) -> 750 | BH40: 0
A41: Kash Kash (kg) | B41: 0 | C41: 0 | D41: =IFERROR(C41/B41,0) -> 0 | E41: 0 | G41: 0.1 | H41: 130 | I41: =IFERROR(H41/G41,0) -> 1300 | J41: 0 | L41: 0.1 | M41: 130 | N41: =IFERROR(M41/L41,0) -> 1300 | O41: 0 | Q41: 0.1 | R41: 150 | S41: =IFERROR(R41/Q41,0) -> 1500 | T41: 0 | V41: 0.1 | W41: 145 | X41: =IFERROR(W41/V41,0) -> 1450 | Y41: 0 | AA41: 0.1 | AB41: 160 | AC41: =IFERROR(AB41/AA41,0) -> 1600 | AD41: 0 | AF41: =0.1+0.2 -> 0.3 | AG41: =190+360 -> 550 | AH41: =IFERROR(AG41/AF41,0) -> 1833.3333 | AI41: 0 | AK41: 0.1 | AL41: 220 | AM41: =IFERROR(AL41/AK41,0) -> 2200 | AN41: 0 | AP41: 0.1 | AQ41: 200 | AR41: =IFERROR(AQ41/AP41,0) -> 2000 | AS41: 0 | AU41: 0.1 | AV41: 160 | AW41: =IFERROR(AV41/AU41,0) -> 1600 | AX41: 0 | AZ41: 0.1 | BA41: 200 | BB41: =IFERROR(BA41/AZ41,0) -> 2000 | BC41: 0 | BE41: 0.1 | BF41: 165 | BG41: =IFERROR(BF41/BE41,0) -> 1650 | BH41: 0
A42: Salt (kg) | B42: 10 | C42: 100 | D42: =IFERROR(C42/B42,0) -> 10 | E42: 3 | G42: 25 | H42: 350 | I42: =IFERROR(H42/G42,0) -> 14 | J42: 20 | L42: 0 | M42: 0 | N42: =IFERROR(M42/L42,0) -> 0 | O42: 0 | Q42: 10 | R42: 150 | S42: =IFERROR(R42/Q42,0) -> 15 | T42: 9 | V42: 12 | W42: 170 | X42: =IFERROR(W42/V42,0) -> 14.166667 | Y42: 8 | AA42: 13 | AB42: 195 | AC42: =IFERROR(AB42/AA42,0) -> 15 | AD42: 12 | AF42: 10 | AG42: =AC42*AF42 -> 150 | AH42: =IFERROR(AG42/AF42,0) -> 15 | AI42: 10 | AK42: 15 | AL42: 0 | AM42: =IFERROR(AL42/AK42,0) -> 0 | AN42: 10 | AP42: 15 | AQ42: 210 | AR42: =IFERROR(AQ42/AP42,0) -> 14 | AS42: 18 | AU42: 0 | AV42: 0 | AW42: =IFERROR(AV42/AU42,0) -> 0 | AX42: 8 | AZ42: 10 | BA42: 225 | BB42: =IFERROR(BA42/AZ42,0) -> 22.5 | BC42: 10 | BE42: 8 | BF42: 112 | BG42: =IFERROR(BF42/BE42,0) -> 14 | BH42: 15
A43: Big salt (kg) | B43: 10 | C43: 130 | D43: =IFERROR(C43/B43,0) -> 13 | E43: 0 | G43: 25 | H43: 350 | I43: =IFERROR(H43/G43,0) -> 14 | J43: 12 | L43: 15 | M43: 210 | N43: =IFERROR(M43/L43,0) -> 14 | O43: 0 | Q43: 17 | R43: 238 | S43: =IFERROR(R43/Q43,0) -> 14 | T43: 10 | V43: 15 | W43: 210 | X43: =IFERROR(W43/V43,0) -> 14 | Y43: 4 | AA43: 10 | AB43: 140 | AC43: =IFERROR(AB43/AA43,0) -> 14 | AD43: 2 | AF43: 22 | AG43: =180+120 -> 300 | AH43: =IFERROR(AG43/AF43,0) -> 13.636364 | AI43: 2 | AK43: 30 | AL43: 330 | AM43: =IFERROR(AL43/AK43,0) -> 11 | AN43: 2 | AP43: 30 | AQ43: 390 | AR43: =IFERROR(AQ43/AP43,0) -> 13 | AS43: 13 | AU43: 15 | AV43: 210 | AW43: =IFERROR(AV43/AU43,0) -> 14 | AX43: 12 | AZ43: 15 | BA43: 225 | BB43: =IFERROR(BA43/AZ43,0) -> 15 | BC43: 12 | BE43: 15 | BF43: 210 | BG43: =IFERROR(BF43/BE43,0) -> 14 | BH43: 10
A44: Elaichi (kg) | B44: 0.4 | C44: 1400 | D44: =IFERROR(C44/B44,0) -> 3500 | E44: 0.35 | G44: 0.5 | H44: 1800 | I44: =IFERROR(H44/G44,0) -> 3600 | J44: 0.4 | L44: 0.5 | M44: 1770 | N44: =IFERROR(M44/L44,0) -> 3540 | O44: 0 | Q44: 0.6 | R44: 1440 | S44: =IFERROR(R44/Q44,0) -> 2400 | T44: 0 | V44: 1 | W44: 3300 | X44: =IFERROR(W44/V44,0) -> 3300 | Y44: 0.4 | AA44: 0.4 | AB44: 1320 | AC44: =IFERROR(AB44/AA44,0) -> 3300 | AD44: 0.26 | AF44: 0.5 | AG44: 1700 | AH44: =IFERROR(AG44/AF44,0) -> 3400 | AI44: 0.2 | AK44: 1.5 | AL44: 3250 | AM44: =IFERROR(AL44/AK44,0) -> 2166.6667 | AN44: 0.9 | AP44: 0 | AQ44: 0 | AR44: =IFERROR(AQ44/AP44,0) -> 0 | AS44: 0.75 | AU44: 0.5 | AV44: 0 | AW44: =IFERROR(AV44/AU44,0) -> 0 | AX44: 0.45 | AZ44: 0.5 | BA44: 1700 | BB44: =IFERROR(BA44/AZ44,0) -> 3400 | BC44: 0.4 | BE44: 0.5 | BF44: 1700 | BG44: =IFERROR(BF44/BE44,0) -> 3400 | BH44: 0.8
A45: Loung (kg) | B45: 0.5 | C45: 145 | D45: =IFERROR(C45/B45,0) -> 290 | E45: 0.8 | G45: 0.5 | H45: 450 | I45: =IFERROR(H45/G45,0) -> 900 | J45: 1 | L45: 0.3 | M45: 300 | N45: =IFERROR(M45/L45,0) -> 1000 | O45: 0 | Q45: 0.2 | R45: 200 | S45: =IFERROR(R45/Q45,0) -> 1000 | T45: 0 | V45: 0 | W45: 0 | X45: =IFERROR(W45/V45,0) -> 0 | Y45: 0.7 | AA45: 0 | AB45: 0 | AC45: =IFERROR(AB45/AA45,0) -> 0 | AD45: 0.5 | AF45: 0.5 | AG45: 475 | AH45: =IFERROR(AG45/AF45,0) -> 950 | AI45: 0.5 | AK45: 0.5 | AL45: 450 | AM45: =IFERROR(AL45/AK45,0) -> 900 | AN45: 0.5 | AP45: 0 | AQ45: 0 | AR45: =IFERROR(AQ45/AP45,0) -> 0 | AS45: 0.65 | AU45: 0 | AV45: 0 | AW45: =IFERROR(AV45/AU45,0) -> 0 | AX45: 0.5 | AZ45: 0 | BA45: 0 | BB45: =IFERROR(BA45/AZ45,0) -> 0 | BC45: 0.36 | BE45: 0.25 | BF45: 250 | BG45: =IFERROR(BF45/BE45,0) -> 1000 | BH45: 0.6
A46: Dalchini (kg) | B46: 0 | C46: 0 | D46: =IFERROR(C46/B46,0) -> 0 | E46: 0.4 | G46: 0.5 | H46: 180 | I46: =IFERROR(H46/G46,0) -> 360 | J46: 7 | L46: 0 | M46: 0 | N46: =IFERROR(M46/L46,0) -> 0 | O46: 0 | Q46: 0.5 | R46: 150 | S46: =IFERROR(R46/Q46,0) -> 300 | T46: 0 | V46: 1 | W46: 350 | X46: =IFERROR(W46/V46,0) -> 350 | Y46: 0.1 | AA46: 1 | AB46: 350 | AC46: =IFERROR(AB46/AA46,0) -> 350 | AD46: 0.37 | AF46: 0.6 | AG46: 240 | AH46: =IFERROR(AG46/AF46,0) -> 400 | AI46: 0.3 | AK46: 1 | AL46: 320 | AM46: =IFERROR(AL46/AK46,0) -> 320 | AN46: 0.4 | AP46: 0.5 | AQ46: 155 | AR46: =IFERROR(AQ46/AP46,0) -> 310 | AS46: 1.4 | AU46: 0 | AV46: 0 | AW46: =IFERROR(AV46/AU46,0) -> 0 | AX46: 0.8 | AZ46: 0.5 | BA46: 220 | BB46: =IFERROR(BA46/AZ46,0) -> 440 | BC46: 0.6 | BE46: 0.5 | BF46: 200 | BG46: =IFERROR(BF46/BE46,0) -> 400 | BH46: 0.9
A47: Star Phool (kg) | B47: 0 | C47: 0 | D47: =IFERROR(C47/B47,0) -> 0 | E47: 0.1 | G47: 1 | H47: 550 | I47: =IFERROR(H47/G47,0) -> 550 | J47: 0.8 | L47: 0 | M47: 0 | N47: =IFERROR(M47/L47,0) -> 0 | O47: 0 | Q47: 0.3 | R47: 255 | S47: =IFERROR(R47/Q47,0) -> 850 | T47: 0 | V47: 0.4 | W47: 340 | X47: =IFERROR(W47/V47,0) -> 850 | Y47: 0.4 | AA47: 0 | AB47: 0 | AC47: =IFERROR(AB47/AA47,0) -> 0 | AD47: 0.1 | AF47: 0.3 | AG47: =X47*AF47 -> 255 | AH47: =IFERROR(AG47/AF47,0) -> 850 | AI47: 0.15 | AK47: 1 | AL47: 620 | AM47: =IFERROR(AL47/AK47,0) -> 620 | AN47: 0.5 | AP47: 0.5 | AQ47: 350 | AR47: =IFERROR(AQ47/AP47,0) -> 700 | AS47: 1.3 | AU47: 0.4 | AV47: 280 | AW47: =IFERROR(AV47/AU47,0) -> 700 | AX47: 1 | AZ47: 0 | BA47: 0 | BB47: =IFERROR(BA47/AZ47,0) -> 0 | BC47: 0.8 | BE47: 0.2 | BF47: 150 | BG47: =IFERROR(BF47/BE47,0) -> 750 | BH47: 1.4
A48: Jai Phool (kg) | B48: 0 | C48: 0 | D48: =IFERROR(C48/B48,0) -> 0 | E48: 0 | G48: 0 | H48: 0 | I48: =IFERROR(H48/G48,0) -> 0 | J48: 0 | L48: 0 | M48: 0 | N48: =IFERROR(M48/L48,0) -> 0 | O48: 0 | Q48: 0 | R48: 0 | S48: =IFERROR(R48/Q48,0) -> 0 | T48: 0 | V48: 0 | W48: 0 | X48: =IFERROR(W48/V48,0) -> 0 | Y48: 0 | AA48: 0 | AB48: 0 | AC48: =IFERROR(AB48/AA48,0) -> 0 | AD48: 0 | AF48: 0 | AG48: =AC48*AF48 -> 0 | AH48: =IFERROR(AG48/AF48,0) -> 0 | AI48: 0 | AK48: 0 | AL48: 0 | AM48: =IFERROR(AL48/AK48,0) -> 0 | AN48: 0 | AP48: 0 | AQ48: 0 | AR48: =IFERROR(AQ48/AP48,0) -> 0 | AS48: 0 | AU48: 0 | AV48: 0 | AW48: =IFERROR(AV48/AU48,0) -> 0 | AX48: 0 | AZ48: 0 | BA48: 0 | BB48: =IFERROR(BA48/AZ48,0) -> 0 | BC48: 0 | BE48: 0 | BF48: 0 | BG48: =IFERROR(BF48/BE48,0) -> 0 | BH48: 0
A49: Shazira (kg) | B49: 0 | C49: 0 | D49: =IFERROR(C49/B49,0) -> 0 | E49: 0.6 | G49: 0.5 | H49: 165 | I49: =IFERROR(H49/G49,0) -> 330 | J49: 0.6 | L49: 0.3 | M49: 85 | N49: =IFERROR(M49/L49,0) -> 283.33333 | O49: 0 | Q49: 0.6 | R49: 215 | S49: =IFERROR(R49/Q49,0) -> 358.33333 | T49: 0 | V49: 0.7 | W49: 240 | X49: =IFERROR(W49/V49,0) -> 342.85714 | Y49: 0 | AA49: 1 | AB49: 350 | AC49: =IFERROR(AB49/AA49,0) -> 350 | AD49: 0 | AF49: 1 | AG49: 380 | AH49: =IFERROR(AG49/AF49,0) -> 380 | AI49: 0.5 | AK49: 0.5 | AL49: 160 | AM49: =IFERROR(AL49/AK49,0) -> 320 | AN49: 0 | AP49: 1 | AQ49: 350 | AR49: =IFERROR(AQ49/AP49,0) -> 350 | AS49: 0.6 | AU49: 1 | AV49: 390 | AW49: =IFERROR(AV49/AU49,0) -> 390 | AX49: 1 | AZ49: 0.5 | BA49: 190 | BB49: =IFERROR(BA49/AZ49,0) -> 380 | BC49: 0.5 | BE49: 1 | BF49: 330 | BG49: =IFERROR(BF49/BE49,0) -> 330 | BH49: 1.9
A50: Biryani patta (kg) | B50: 0 | C50: 0 | D50: =IFERROR(C50/B50,0) -> 0 | E50: 0.15 | G50: 0.3 | H50: 50 | I50: =IFERROR(H50/G50,0) -> 166.66667 | J50: 0.4 | L50: 0 | M50: 0 | N50: =IFERROR(M50/L50,0) -> 0 | O50: 0 | Q50: 0 | R50: 0 | S50: =IFERROR(R50/Q50,0) -> 0 | T50: 0 | V50: 0.2 | W50: 35 | X50: =IFERROR(W50/V50,0) -> 175 | Y50: 0.4 | AA50: 0 | AB50: 0 | AC50: =IFERROR(AB50/AA50,0) -> 0 | AD50: 0.2 | AF50: 0.2 | AG50: 50 | AH50: =IFERROR(AG50/AF50,0) -> 250 | AI50: 0.2 | AK50: 0.5 | AL50: 90 | AM50: =IFERROR(AL50/AK50,0) -> 180 | AN50: 0.6 | AP50: 0 | AQ50: 0 | AR50: =IFERROR(AQ50/AP50,0) -> 0 | AS50: 0.5 | AU50: 0 | AV50: 0 | AW50: =IFERROR(AV50/AU50,0) -> 0 | AX50: 0.5 | AZ50: 0 | BA50: 0 | BB50: =IFERROR(BA50/AZ50,0) -> 0 | BC50: 0.2 | BE50: 0.2 | BF50: 400 | BG50: =IFERROR(BF50/BE50,0) -> 2000 | BH50: 0.6
A51: Kastur methi (kg) | B51: 0.5 | C51: 200 | D51: =IFERROR(C51/B51,0) -> 400 | E51: 0.5 | G51: 0.5 | H51: 350 | I51: =IFERROR(H51/G51,0) -> 700 | J51: 0.8 | L51: 0 | M51: 0 | N51: =IFERROR(M51/L51,0) -> 0 | O51: 0 | Q51: 1 | R51: 350 | S51: =IFERROR(R51/Q51,0) -> 350 | T51: 1 | V51: 1 | W51: 720 | X51: =IFERROR(W51/V51,0) -> 720 | Y51: 2 | AA51: 0 | AB51: 0 | AC51: =IFERROR(AB51/AA51,0) -> 0 | AD51: 2 | AF51: 0 | AG51: =AC51*AF51 -> 0 | AH51: =IFERROR(AG51/AF51,0) -> 0 | AI51: 0 | AK51: 3 | AL51: 2100 | AM51: =IFERROR(AL51/AK51,0) -> 700 | AN51: 2 | AP51: 0 | AQ51: 0 | AR51: =IFERROR(AQ51/AP51,0) -> 0 | AS51: 0 | AU51: 0 | AV51: 0 | AW51: =IFERROR(AV51/AU51,0) -> 0 | AX51: 1.5 | AZ51: 0 | BA51: 0 | BB51: =IFERROR(BA51/AZ51,0) -> 0 | BC51: 1 | BE51: 0 | BF51: 0 | BG51: =IFERROR(BF51/BE51,0) -> 0 | BH51: 0.5
A52: Japhal (kg) | B52: 0 | C52: 0 | D52: =IFERROR(C52/B52,0) -> 0 | E52: 1.3 | G52: 0 | H52: 0 | I52: =IFERROR(H52/G52,0) -> 0 | J52: 0 | L52: 0 | M52: 0 | N52: =IFERROR(M52/L52,0) -> 0 | O52: 0 | Q52: 0 | R52: 0 | S52: =IFERROR(R52/Q52,0) -> 0 | T52: 0 | V52: 0 | W52: 0 | X52: =IFERROR(W52/V52,0) -> 0 | Y52: 0.6 | AA52: 0 | AB52: 0 | AC52: =IFERROR(AB52/AA52,0) -> 0 | AD52: 0 | AF52: 0 | AG52: =AC52*AF52 -> 0 | AH52: =IFERROR(AG52/AF52,0) -> 0 | AI52: 0 | AK52: 0 | AL52: 0 | AM52: =IFERROR(AL52/AK52,0) -> 0 | AN52: 0 | AP52: 0 | AQ52: 0 | AR52: =IFERROR(AQ52/AP52,0) -> 0 | AS52: 0 | AU52: 0 | AV52: 0 | AW52: =IFERROR(AV52/AU52,0) -> 0 | AX52: 0 | AZ52: 0 | BA52: 0 | BB52: =IFERROR(BA52/AZ52,0) -> 0 | BC52: 0 | BE52: 0 | BF52: 0 | BG52: =IFERROR(BF52/BE52,0) -> 0 | BH52: 0
A53: Japatri | B53: 0 | C53: 0 | D53: =IFERROR(C53/B53,0) -> 0 | E53: 0.6 | G53: 0.5 | H53: 1100 | I53: =IFERROR(H53/G53,0) -> 2200 | J53: 0.7 | L53: 0 | M53: 0 | N53: =IFERROR(M53/L53,0) -> 0 | O53: 0 | Q53: 0.3 | R53: 765 | S53: =IFERROR(R53/Q53,0) -> 2550 | T53: 0 | V53: 0.2 | W53: 450 | X53: =IFERROR(W53/V53,0) -> 2250 | Y53: 0.32 | AA53: 0.3 | AB53: 700 | AC53: =IFERROR(AB53/AA53,0) -> 2333.3333 | AD53: 0 | AF53: 0.6 | AG53: 1380 | AH53: =IFERROR(AG53/AF53,0) -> 2300 | AI53: 0.1 | AK53: 1.2 | AL53: 2760 | AM53: =IFERROR(AL53/AK53,0) -> 2300 | AN53: 0.35 | AP53: 1 | AQ53: 2250 | AR53: =IFERROR(AQ53/AP53,0) -> 2250 | AS53: 2 | AU53: 0 | AV53: 0 | AW53: =IFERROR(AV53/AU53,0) -> 0 | AX53: 1.1 | AZ53: 0 | BA53: 0 | BB53: =IFERROR(BA53/AZ53,0) -> 0 | BC53: 0.8 | BE53: 0.3 | BF53: 780 | BG53: =IFERROR(BF53/BE53,0) -> 2600 | BH53: 0.7
A54: Kabab Chini | B54: 0 | C54: 0 | D54: =IFERROR(C54/B54,0) -> 0 | E54: 0.6 | G54: 0 | H54: 0 | I54: =IFERROR(H54/G54,0) -> 0 | J54: 0.6 | L54: 0 | M54: 0 | N54: =IFERROR(M54/L54,0) -> 0 | O54: 0 | Q54: 0 | R54: 0 | S54: =IFERROR(R54/Q54,0) -> 0 | T54: 0 | V54: 0 | W54: 0 | X54: =IFERROR(W54/V54,0) -> 0 | Y54: 0 | AA54: 0 | AB54: 0 | AC54: =IFERROR(AB54/AA54,0) -> 0 | AD54: 0 | AF54: 0 | AG54: =AC54*AF54 -> 0 | AH54: =IFERROR(AG54/AF54,0) -> 0 | AI54: 0.25 | AK54: 0 | AL54: 0 | AM54: =IFERROR(AL54/AK54,0) -> 0 | AN54: 0 | AP54: 0 | AQ54: 0 | AR54: =IFERROR(AQ54/AP54,0) -> 0 | AS54: 0 | AU54: 0 | AV54: 0 | AW54: =IFERROR(AV54/AU54,0) -> 0 | AX54: 0 | AZ54: 0 | BA54: 0 | BB54: =IFERROR(BA54/AZ54,0) -> 0 | BC54: 0 | BE54: 0 | BF54: 0 | BG54: =IFERROR(BF54/BE54,0) -> 0 | BH54: 0
A55: Kali Mirch/Miryalu | B55: 0 | C55: 0 | D55: =IFERROR(C55/B55,0) -> 0 | E55: 0.4 | G55: 0 | H55: 0 | I55: =IFERROR(H55/G55,0) -> 0 | J55: 0.3 | L55: 0 | M55: 0 | N55: =IFERROR(M55/L55,0) -> 0 | O55: 0 | Q55: 0 | R55: 0 | S55: =IFERROR(R55/Q55,0) -> 0 | T55: 0 | V55: 1 | W55: 880 | X55: =IFERROR(W55/V55,0) -> 880 | Y55: 0 | AA55: 0 | AB55: 0 | AC55: =IFERROR(AB55/AA55,0) -> 0 | AD55: 0 | AF55: 0 | AG55: =AC55*AF55 -> 0 | AH55: =IFERROR(AG55/AF55,0) -> 0 | AI55: 0 | AK55: 0.5 | AL55: 410 | AM55: =IFERROR(AL55/AK55,0) -> 820 | AN55: 0.3 | AP55: 0 | AQ55: 0 | AR55: =IFERROR(AQ55/AP55,0) -> 0 | AS55: 0 | AU55: 0 | AV55: 0 | AW55: =IFERROR(AV55/AU55,0) -> 0 | AX55: 0 | AZ55: 0 | BA55: 0 | BB55: =IFERROR(BA55/AZ55,0) -> 0 | BC55: 0 | BE55: 0 | BF55: 0 | BG55: =IFERROR(BF55/BE55,0) -> 0 | BH55: 0
A56: Big Elaichi | B56: 0 | C56: 0 | D56: =IFERROR(C56/B56,0) -> 0 | E56: 0 | G56: 0 | H56: 0 | I56: =IFERROR(H56/G56,0) -> 0 | J56: 0 | L56: 0 | M56: 0 | N56: =IFERROR(M56/L56,0) -> 0 | O56: 0 | Q56: 0 | R56: 0 | S56: =IFERROR(R56/Q56,0) -> 0 | T56: 0 | V56: 0.4 | W56: 880 | X56: =IFERROR(W56/V56,0) -> 2200 | Y56: 0 | AA56: 0 | AB56: 0 | AC56: =IFERROR(AB56/AA56,0) -> 0 | AD56: 0 | AF56: 0 | AG56: =AC56*AF56 -> 0 | AH56: =IFERROR(AG56/AF56,0) -> 0 | AI56: 0 | AK56: 0 | AL56: 0 | AM56: =IFERROR(AL56/AK56,0) -> 0 | AN56: 0 | AP56: 0 | AQ56: 0 | AR56: =IFERROR(AQ56/AP56,0) -> 0 | AS56: 0 | AU56: 0 | AV56: 0 | AW56: =IFERROR(AV56/AU56,0) -> 0 | AX56: 0 | AZ56: 0 | BA56: 0 | BB56: =IFERROR(BA56/AZ56,0) -> 0 | BC56: 0 | BE56: 0 | BF56: 0 | BG56: =IFERROR(BF56/BE56,0) -> 0 | BH56: 0
A57: Phatar ka Phool (kg) | B57: 0 | C57: 0 | D57: =IFERROR(C57/B57,0) -> 0 | E57: 0.1 | G57: 0 | H57: 0 | I57: =IFERROR(H57/G57,0) -> 0 | J57: 0.1 | L57: 0 | M57: 0 | N57: =IFERROR(M57/L57,0) -> 0 | O57: 0 | Q57: 0 | R57: 0 | S57: =IFERROR(R57/Q57,0) -> 0 | T57: 0 | V57: 0.1 | W57: 60 | X57: =IFERROR(W57/V57,0) -> 600 | Y57: 0 | AA57: 0 | AB57: 0 | AC57: =IFERROR(AB57/AA57,0) -> 0 | AD57: 0 | AF57: 0 | AG57: =AC57*AF57 -> 0 | AH57: =IFERROR(AG57/AF57,0) -> 0 | AI57: 0 | AK57: 0 | AL57: 0 | AM57: =IFERROR(AL57/AK57,0) -> 0 | AP57: 0 | AQ57: 0 | AR57: =IFERROR(AQ57/AP57,0) -> 0 | AS57: 0 | AU57: 0 | AV57: 0 | AW57: =IFERROR(AV57/AU57,0) -> 0 | AX57: 0 | AZ57: 0 | BA57: 0 | BB57: =IFERROR(BA57/AZ57,0) -> 0 | BC57: 0 | BE57: 0 | BF57: 0 | BG57: =IFERROR(BF57/BE57,0) -> 0 | BH57: 0
A58: Gulab Ka phool | B58: 0 | C58: 0 | D58: =IFERROR(C58/B58,0) -> 0 | E58: 0.2 | G58: 0 | H58: 0 | I58: =IFERROR(H58/G58,0) -> 0 | J58: 0.2 | L58: 0 | M58: 0 | N58: =IFERROR(M58/L58,0) -> 0 | O58: 0 | Q58: 0 | R58: 0 | S58: =IFERROR(R58/Q58,0) -> 0 | T58: 0 | V58: 0 | W58: 0 | X58: =IFERROR(W58/V58,0) -> 0 | Y58: 0 | AA58: 0 | AB58: 0 | AC58: =IFERROR(AB58/AA58,0) -> 0 | AD58: 0 | AF58: 0 | AG58: =AC58*AF58 -> 0 | AH58: =IFERROR(AG58/AF58,0) -> 0 | AI58: 0 | AK58: 0 | AL58: 0 | AM58: =IFERROR(AL58/AK58,0) -> 0 | AN58: 0 | AP58: 0 | AQ58: 0 | AR58: =IFERROR(AQ58/AP58,0) -> 0 | AS58: 0 | AU58: 0 | AV58: 0 | AW58: =IFERROR(AV58/AU58,0) -> 0 | AX58: 0 | AZ58: 0 | BA58: 0 | BB58: =IFERROR(BA58/AZ58,0) -> 0 | BC58: 0 | BE58: 0 | BF58: 0 | BG58: =IFERROR(BF58/BE58,0) -> 0 | BH58: 0
A59: Bread Crumbs (kg) | B59: 1 | C59: 150 | D59: =IFERROR(C59/B59,0) -> 150 | E59: 1 | G59: 2 | H59: 300 | I59: =IFERROR(H59/G59,0) -> 150 | J59: 2 | L59: 0 | M59: 0 | N59: =IFERROR(M59/L59,0) -> 0 | O59: 0 | Q59: 1 | R59: 140 | S59: =IFERROR(R59/Q59,0) -> 140 | T59: 0 | V59: 1 | W59: 150 | X59: =IFERROR(W59/V59,0) -> 150 | Y59: 0 | AA59: 0 | AB59: 0 | AC59: =IFERROR(AB59/AA59,0) -> 0 | AD59: 0 | AF59: 0 | AG59: =AC59*AF59 -> 0 | AH59: =IFERROR(AG59/AF59,0) -> 0 | AI59: 0 | AK59: 2 | AL59: 280 | AM59: =IFERROR(AL59/AK59,0) -> 140 | AN59: 0 | AP59: 0 | AQ59: 0 | AR59: =IFERROR(AQ59/AP59,0) -> 0 | AS59: 0 | AU59: 0 | AV59: 0 | AW59: =IFERROR(AV59/AU59,0) -> 0 | AX59: 0 | AZ59: 0 | BA59: 0 | BB59: =IFERROR(BA59/AZ59,0) -> 0 | BC59: 0 | BE59: 0 | BF59: 0 | BG59: =IFERROR(BF59/BE59,0) -> 0 | BH59: 0
A60: Kismis | B60: 3 | C60: 780 | D60: =IFERROR(C60/B60,0) -> 260 | E60: 0.8 | G60: 2 | H60: 560 | I60: =IFERROR(H60/G60,0) -> 280 | J60: 0.8 | L60: 2 | M60: 520 | N60: =IFERROR(M60/L60,0) -> 260 | O60: 0 | Q60: 1.5 | R60: 480 | S60: =IFERROR(R60/Q60,0) -> 320 | T60: 0 | V60: 1.5 | W60: 490 | X60: =IFERROR(W60/V60,0) -> 326.66667 | Y60: 0 | AA60: 0 | AB60: 0 | AC60: =IFERROR(AB60/AA60,0) -> 0 | AD60: 0 | AF60: 0 | AG60: =AC60*AF60 -> 0 | AH60: =IFERROR(AG60/AF60,0) -> 0 | AI60: 0 | AK60: 2 | AL60: 960 | AM60: =IFERROR(AL60/AK60,0) -> 480 | AN60: 0.8 | AP60: 0 | AQ60: 0 | AR60: =IFERROR(AQ60/AP60,0) -> 0 | AS60: 0 | AU60: 0 | AV60: 0 | AW60: =IFERROR(AV60/AU60,0) -> 0 | AX60: 0 | AZ60: 0 | BA60: 0 | BB60: =IFERROR(BA60/AZ60,0) -> 0 | BC60: 0 | BE60: 0 | BF60: 0 | BG60: =IFERROR(BF60/BE60,0) -> 0 | BH60: 0
A61: Maggi Cube | B61: 24 | C61: 470 | D61: =IFERROR(C61/B61,0) -> 19.583333 | E61: 15 | G61: 24 | H61: 500 | I61: =IFERROR(H61/G61,0) -> 20.833333 | J61: 24 | L61: 0 | M61: 0 | N61: =IFERROR(M61/L61,0) -> 0 | O61: 0 | Q61: 14 | R61: 0 | S61: =IFERROR(R61/Q61,0) -> 0 | T61: 0 | V61: 24 | W61: 480 | X61: =IFERROR(W61/V61,0) -> 20 | Y61: 0 | AA61: 0 | AB61: 0 | AC61: =IFERROR(AB61/AA61,0) -> 0 | AD61: 0 | AF61: 0 | AG61: =AC61*AF61 -> 0 | AH61: =IFERROR(AG61/AF61,0) -> 0 | AI61: 0 | AK61: 24 | AL61: 420 | AM61: =IFERROR(AL61/AK61,0) -> 17.5 | AN61: 0 | AP61: 0 | AQ61: 0 | AR61: =IFERROR(AQ61/AP61,0) -> 0 | AS61: 0 | AU61: 0 | AV61: 0 | AW61: =IFERROR(AV61/AU61,0) -> 0 | AX61: 0 | AZ61: 0 | BA61: 0 | BB61: =IFERROR(BA61/AZ61,0) -> 0 | BC61: 0 | BE61: 0 | BF61: 0 | BG61: =IFERROR(BF61/BE61,0) -> 0 | BH61: 0
A62: S Mart
A63: Dhaniya (kg) | B63: 0.5 | C63: 80 | D63: =IFERROR(C63/B63,0) -> 160 | E63: 1.3 | G63: 2 | H63: 300 | I63: =IFERROR(H63/G63,0) -> 150 | J63: 1.5 | L63: 0 | M63: 0 | N63: =IFERROR(M63/L63,0) -> 0 | O63: 0 | Q63: 0 | R63: 0 | S63: =IFERROR(R63/Q63,0) -> 0 | T63: 0 | V63: 0.5 | W63: 60 | X63: =IFERROR(W63/V63,0) -> 120 | Y63: 0 | AA63: 0 | AB63: 0 | AC63: =IFERROR(AB63/AA63,0) -> 0 | AD63: 0 | AF63: 0 | AG63: =AC63*AF63 -> 0 | AH63: =IFERROR(AG63/AF63,0) -> 0 | AI63: 0 | AK63: 0.5 | AL63: 60 | AM63: =IFERROR(AL63/AK63,0) -> 120 | AN63: 0 | AP63: 0 | AQ63: 0 | AR63: =IFERROR(AQ63/AP63,0) -> 0 | AS63: 0 | AU63: 0 | AV63: 0 | AW63: =IFERROR(AV63/AU63,0) -> 0 | AX63: 0 | AZ63: 0 | BA63: 0 | BB63: =IFERROR(BA63/AZ63,0) -> 0 | BC63: 0 | BE63: 0 | BF63: 0 | BG63: =IFERROR(BF63/BE63,0) -> 0 | BH63: 0
A64: Sugar (kg) | B64: 5 | C64: 205 | D64: =IFERROR(C64/B64,0) -> 41 | E64: 0.8 | G64: 5 | H64: 210 | I64: =IFERROR(H64/G64,0) -> 42 | J64: 2.5 | L64: 3 | M64: 129 | N64: =IFERROR(M64/L64,0) -> 43 | O64: 0 | Q64: 5 | R64: 220 | S64: =IFERROR(R64/Q64,0) -> 44 | T64: 0 | V64: 5 | W64: 220 | X64: =IFERROR(W64/V64,0) -> 44 | Y64: 0 | AA64: 4 | AB64: 176 | AC64: =IFERROR(AB64/AA64,0) -> 44 | AD64: 1 | AF64: 4 | AG64: =AC64*AF64 -> 176 | AH64: =IFERROR(AG64/AF64,0) -> 44 | AI64: 1 | AK64: 5 | AL64: 220 | AM64: =IFERROR(AL64/AK64,0) -> 44 | AN64: 0 | AP64: 3 | AQ64: 0 | AR64: =IFERROR(AQ64/AP64,0) -> 0 | AS64: 1 | AU64: 0 | AV64: 0 | AW64: =IFERROR(AV64/AU64,0) -> 0 | AX64: 1 | AZ64: 2 | BA64: 180 | BB64: =IFERROR(BA64/AZ64,0) -> 90 | BC64: 0 | BE64: 3 | BF64: 135 | BG64: =IFERROR(BF64/BE64,0) -> 45 | BH64: 0.25
A65: Dalda (kg) | B65: 1 | C65: 0 | D65: =IFERROR(C65/B65,0) -> 0 | E65: 0 | G65: 1 | H65: 140 | I65: =IFERROR(H65/G65,0) -> 140 | J65: 0 | L65: 1 | M65: 140 | N65: =IFERROR(M65/L65,0) -> 140 | O65: 0 | Q65: 1 | R65: 150 | S65: =IFERROR(R65/Q65,0) -> 150 | T65: 0 | V65: 1 | W65: 140 | X65: =IFERROR(W65/V65,0) -> 140 | Y65: 0 | AA65: 1 | AB65: 200 | AC65: =IFERROR(AB65/AA65,0) -> 200 | AD65: 0 | AF65: =1+1 -> 2 | AG65: =150+150 -> 300 | AH65: =IFERROR(AG65/AF65,0) -> 150 | AI65: 0 | AK65: 1 | AL65: 150 | AM65: =IFERROR(AL65/AK65,0) -> 150 | AN65: 0 | AP65: 1 | AQ65: 150 | AR65: =IFERROR(AQ65/AP65,0) -> 150 | AS65: 0 | AU65: 0 | AV65: 0 | AW65: =IFERROR(AV65/AU65,0) -> 0 | AX65: 0 | AZ65: 1 | BA65: 0 | BB65: =IFERROR(BA65/AZ65,0) -> 0 | BC65: 0 | BE65: 1 | BF65: 330 | BG65: =IFERROR(BF65/BE65,0) -> 330 | BH65: 0
A66: Red Chilli Powder (kg) | B66: 0 | C66: 0 | D66: =IFERROR(C66/B66,0) -> 0 | E66: 0 | G66: 0 | H66: 0 | I66: =IFERROR(H66/G66,0) -> 0 | J66: 0 | L66: 0 | M66: 0 | N66: =IFERROR(M66/L66,0) -> 0 | O66: 0 | Q66: 0 | R66: 0 | S66: =IFERROR(R66/Q66,0) -> 0 | T66: 0 | V66: 0 | W66: 0 | X66: =IFERROR(W66/V66,0) -> 0 | Y66: 0 | AA66: 0 | AB66: 0 | AC66: =IFERROR(AB66/AA66,0) -> 0 | AD66: 0 | AF66: 0 | AG66: =AC66*AF66 -> 0 | AH66: =IFERROR(AG66/AF66,0) -> 0 | AI66: 0 | AK66: 1 | AL66: 0 | AM66: =IFERROR(AL66/AK66,0) -> 0 | AN66: 0 | AP66: 0 | AQ66: 0 | AR66: =IFERROR(AQ66/AP66,0) -> 0 | AS66: 0 | AU66: 0 | AV66: 0 | AW66: =IFERROR(AV66/AU66,0) -> 0 | AX66: 0 | AZ66: 0 | BA66: 0 | BB66: =IFERROR(BA66/AZ66,0) -> 0 | BC66: 0 | BE66: 0 | BF66: 0 | BG66: =IFERROR(BF66/BE66,0) -> 0 | BH66: 0
A67: Dhaniya Powder (kg) | B67: 0 | C67: 0 | D67: =IFERROR(C67/B67,0) -> 0 | E67: 0 | G67: 0 | H67: 0 | I67: =IFERROR(H67/G67,0) -> 0 | J67: 0 | L67: 2 | M67: 320 | N67: =IFERROR(M67/L67,0) -> 160 | O67: 0 | Q67: 2 | R67: 300 | S67: =IFERROR(R67/Q67,0) -> 150 | T67: 0 | V67: 2 | W67: 300 | X67: =IFERROR(W67/V67,0) -> 150 | Y67: 0 | AA67: 2 | AB67: 320 | AC67: =IFERROR(AB67/AA67,0) -> 160 | AD67: 0 | AF67: 3 | AG67: =AC67*AF67 -> 480 | AH67: =IFERROR(AG67/AF67,0) -> 160 | AI67: 0 | AK67: 3 | AL67: 510 | AM67: =IFERROR(AL67/AK67,0) -> 170 | AN67: 0 | AP67: 3 | AQ67: 480 | AR67: =IFERROR(AQ67/AP67,0) -> 160 | AS67: 0 | AU67: 3 | AV67: 480 | AW67: =IFERROR(AV67/AU67,0) -> 160 | AX67: 0 | AZ67: 2 | BA67: 220 | BB67: =IFERROR(BA67/AZ67,0) -> 110 | BC67: 0.5 | BE67: 2 | BF67: 140 | BG67: =IFERROR(BF67/BE67,0) -> 70 | BH67: 1
A68: Coal (bags) | B68: 0 | C68: 0 | D68: =IFERROR(C68/B68,0) -> 0 | E68: 0 | G68: 1 | H68: 200 | I68: =IFERROR(H68/G68,0) -> 200 | J68: 0 | L68: 1 | M68: 180 | N68: =IFERROR(M68/L68,0) -> 180 | O68: 0 | Q68: 0 | R68: 0 | S68: =IFERROR(R68/Q68,0) -> 0 | T68: 0 | V68: 0 | W68: 0 | X68: =IFERROR(W68/V68,0) -> 0 | Y68: 0 | AA68: 1 | AB68: 150 | AC68: =IFERROR(AB68/AA68,0) -> 150 | AD68: 1 | AF68: 0 | AG68: =AC68*AF68 -> 0 | AH68: =IFERROR(AG68/AF68,0) -> 0 | AI68: 0 | AK68: 1 | AL68: 220 | AM68: =IFERROR(AL68/AK68,0) -> 220 | AN68: 0 | AP68: 1 | AQ68: 0 | AR68: =IFERROR(AQ68/AP68,0) -> 0 | AS68: 0 | AU68: 0 | AV68: 0 | AW68: =IFERROR(AV68/AU68,0) -> 0 | AX68: 0 | AZ68: 0 | BA68: 0 | BB68: =IFERROR(BA68/AZ68,0) -> 0 | BC68: 0 | BE68: 0 | BF68: 0 | BG68: =IFERROR(BF68/BE68,0) -> 0 | BH68: 0
A69: Boxes | B69: 400 | C69: 2560 | D69: =IFERROR(C69/B69,0) -> 6.4 | E69: 0 | H69: 0 | I69: =IFERROR(H69/G69,0) -> 0 | J69: 0 | L69: 400 | M69: 2300 | N69: =IFERROR(M69/L69,0) -> 5.75 | O69: 0 | Q69: 400 | R69: 2300 | S69: =IFERROR(R69/Q69,0) -> 5.75 | T69: 0 | V69: 0 | W69: 0 | X69: =IFERROR(W69/V69,0) -> 0 | Y69: 0 | AA69: 0 | AB69: 0 | AC69: =IFERROR(AB69/AA69,0) -> 0 | AD69: 0 | AF69: 0 | AG69: =AC69*AF69 -> 0 | AH69: =IFERROR(AG69/AF69,0) -> 0 | AI69: 0 | AK69: 200 | AL69: 1400 | AM69: =IFERROR(AL69/AK69,0) -> 7 | AN69: 0 | AP69: 0 | AQ69: 0 | AR69: =IFERROR(AQ69/AP69,0) -> 0 | AS69: 0 | AU69: 600 | AV69: 3057 | AW69: =IFERROR(AV69/AU69,0) -> 5.095 | AX69: 0 | AZ69: 600 | BA69: 3450 | BB69: =IFERROR(BA69/AZ69,0) -> 5.75 | BC69: 0 | BE69: 0 | BF69: 3080 | BG69: =IFERROR(BF69/BE69,0) -> 0 | BH69: 0
A72: Total | C72: =SUM(C5:C69) -> 95268 | H72: =SUM(H5:H69) -> 67553 | M72: =SUM(M5:M69) -> 54083 | R72: =SUM(R5:R69) -> 70682 | W72: =SUM(W5:W69) -> 95827 | AB72: =SUM(AB5:AB69) -> 54328 | AG72: =SUM(AG5:AG69) -> 85485 | AL72: =SUM(AL5:AL69) -> 127049 | AQ72: =SUM(AQ5:AQ69) -> 81167 | AV72: =SUM(AV5:AV69) -> 90599 | BA72: =SUM(BA5:BA69) -> 27074 | BF72: =SUM(BF5:BF69) -> 60180

Sheet Clean_Data
A1: Month | B1: Item Name | C1: Quantity
A3: January | B3: Green Chilli Sauce | C3: 8
A4: January | B4: Red Chilli Sauce | C4: 5
A5: January | B5: Capsicum Sauce | C5: 0
A6: January | B6: Tomato Sauce | C6: 6
A7: January | B7: 8to8 Sauce | C7: 2
A8: January | B8: Soya Sauce | C8: 0
A9: January | B9: Vinegar | C9: 0
A10: January | B10: Schezwan Sauce | C10: 2
A11: January | B11: Rose Water | C11: 1
A12: January | B12: Kewada water | C12: 1
A13: January | B13: Garam Masala (kg) | C13: 0
A14: January | B14: White pepper (kg) | C14: 1
... A757: December | B757: Boxes | C757: 0
A758: January | C758: Balance
A759: January | B759: Green Chilli Sauce | C759: 1
A760: January | B760: Red Chilli Sauce | C760: 1
A761: January | B761: Capsicum Sauce | C761: 2
A762: January | B762: Tomato Sauce | C762: 1
A763: January | B763: 8to8 Sauce | C763: 1
A764: January | B764: Soya Sauce | C764: 6
A765: January | B765: Vinegar | C765: 3
A766: January | B766: Schezwan Sauce | C766: 2
A767: January | B767: Rose Water | C767: 1
A768: January | B768: Kewada water | C768: 1
A769: January | B769: Garam Masala (kg) | C769: 2
A770: January | B770: White pepper (kg) | C770: 1.5
... A820: January | B820: Boxes | C820: 0
A821: Febraury | C821: Balance
A822: Febraury | B822: Green Chilli Sauce | C822: 3
A823: Febraury | B823: Red Chilli Sauce | C823: 5
A824: Febraury | B824: Capsicum Sauce | C824: 4
A825: Febraury | B825: Tomato Sauce | C825: 8
A826: Febraury | B826: 8to8 Sauce | C826: 2
A827: Febraury | B827: Soya Sauce | C827: 4
A828: Febraury | B828: Vinegar | C828: 2
A829: Febraury | B829: Schezwan Sauce | C829: 1
A830: Febraury | B830: Rose Water | C830: 0
A831: Febraury | B831: Kewada water | C831: 1
A832: Febraury | B832: Garam Masala (kg) | C832: 2
A833: Febraury | B833: White pepper (kg) | C833: 2
... A883: Febraury | B883: Boxes | C883: 0
A884: March | C884: Balance
A885: March | B885: Green Chilli Sauce | C885: 0
A886: March | B886: Red Chilli Sauce | C886: 0
A887: March | B887: Capsicum Sauce | C887: 0
A888: March | B888: Tomato Sauce | C888: 0
A889: March | B889: 8to8 Sauce | C889: 0
A890: March | B890: Soya Sauce | C890: 0
A891: March | B891: Vinegar | C891: 0
A892: March | B892: Schezwan Sauce | C892: 0
A893: March | B893: Rose Water | C893: 0
A894: March | B894: Kewada water | C894: 0
A895: March | B895: Garam Masala (kg) | C895: 0
A896: March | B896: White pepper (kg) | C896: 0
... A946: March | B946: Boxes | C946: 0
A947: April | C947: Balance
A948: April | B948: Green Chilli Sauce | C948: 0
A949: April | B949: Red Chilli Sauce | C949: 1
A950: April | B950: Capsicum Sauce | C950: 2
A951: April | B951: Tomato Sauce | C951: 1
A952: April | B952: 8to8 Sauce | C952: 0
A953: April | B953: Soya Sauce | C953: 1
A954: April | B954: Vinegar | C954: 2
A955: April | B955: Schezwan Sauce | C955: 1
A956: April | B956: Rose Water | C956: 2
A957: April | B957: Kewada water | C957: 1
A958: April | B958: Garam Masala (kg) | C958: 1
A959: April | B959: White pepper (kg) | C959: 0.5
... A1009: April | B1009: Boxes | C1009: 0
A1010: May | C1010: Balance
A1011: May | B1011: Green Chilli Sauce | C1011: 1
A1012: May | B1012: Red Chilli Sauce | C1012: 1
A1013: May | B1013: Capsicum Sauce | C1013: 6
A1014: May | B1014: Tomato Sauce | C1014: 2
A1015: May | B1015: 8to8 Sauce | C1015: 1
A1016: May | B1016: Soya Sauce | C1016: 2
A1017: May | B1017: Vinegar | C1017: 2
A1018: May | B1018: Schezwan Sauce | C1018: 1
A1019: May | B1019: Rose Water | C1019: 0
A1020: May | B1020: Kewada water | C1020: 0
A1021: May | B1021: Garam Masala (kg) | C1021: 0
A1022: May | B1022: White pepper (kg) | C1022: 0.5
... A1072: May | B1072: Boxes | C1072: 0
A1073: June | C1073: Balance
A1074: June | B1074: Green Chilli Sauce | C1074: 2
A1075: June | B1075: Red Chilli Sauce | C1075: 5
A1076: June | B1076: Capsicum Sauce | C1076: 6
A1077: June | B1077: Tomato Sauce | C1077: 3
A1078: June | B1078: 8to8 Sauce | C1078: 2
A1079: June | B1079: Soya Sauce | C1079: 4
A1080: June | B1080: Vinegar | C1080: 6
A1081: June | B1081: Schezwan Sauce | C1081: 2
A1082: June | B1082: Rose Water | C1082: 1
A1083: June | B1083: Kewada water | C1083: 0
A1084: June | B1084: Garam Masala (kg) | C1084: 1
A1085: June | B1085: White pepper (kg) | C1085: 1
... A1135: June | B1135: Boxes | C1135: 0
A1136: July | C1136: Balance
A1137: July | B1137: Green Chilli Sauce | C1137: 2
...

Sheet Stock Analysis
A1: Month+ | B1: Month | D1: Green Chilli Sauce | E1: Red Chilli Sauce | F1: Capsicum Sauce | G1: Tomato Sauce | H1: 8to8 Sauce | I1: Soya Sauce | J1: Vinegar | K1: Schezwan Sauce | L1: Rose Water | M1: Kewada water | N1: Garam Masala (kg) | O1: White pepper (kg) | P1: Chicken Masala (kg) | Q1: Mutton Masala (kg) | R1: Tandoori Chicken Masala (kg) | S1: Chat Masala (kg) | T1: Corn Powder (kg) | U1: Tasting salt (kg) | V1: Red Color (box) | W1: Yellow Color (box) | X1: Biryani Rice (kg) | Y1: Oil (L) | Z1: Maida (kg) | AA1: Aata (kg) | AB1: Cold Drinks (cases) | AC1: Cold Drinks (bottles) | AD1: Cold Drinks (cans) | AE1: Water Bottles (cases) | AF1: Baby Kaju (kg) | AG1: Kaju 4 pieces (kg) | AH1: Haldi (kg) | AI1: Jeera (kg) | AJ1: Til (kg) | AK1: Charmagash (kg) | AL1: Kash Kash (kg) | AM1: Salt (kg) | AN1: Big salt (kg) | AO1: Elaichi (kg) | AP1: Loung (kg) | AQ1: Dalchini (kg) | AR1: Star Phool (kg) | AS1: Jai Phool (kg) | AT1: Shazira (kg) | AU1: Biryani patta (kg) | AV1: Kastur methi (kg) | AW1: Japhal (kg) | AX1: Japatri | AY1: Kabab Chini | AZ1: Kali Mirch/Miryalu | BA1: Big Elaichi | BB1: Phatar ka Phool (kg) | BC1: Gulab Ka phool | BD1: Bread Crumbs (kg) | BE1: Kismis | BF1: Maggi Cube | BG1: Dhaniya (kg) | BH1: Sugar (kg) | BI1: Dalda (kg) | BJ1: Red Chilli Powder (kg) | BK1: Dhaniya Powder (kg) | BL1: Coal (bags) | BM1: Boxes
A2: January(Quantity) | B2: January | C2: Quantity | D2: 8 | E2: 5 | F2: 0 | G2: 6 | H2: 2 | I2: 0 | J2: 0 | K2: 2 | L2: 1 | M2: 1 | N2: 0 | O2: 1 | P2: 2 | Q2: 1 | R2: 0 | S2: 1 | T2: 12 | U2: 5 | V2: 0 | W2: 5 | X2: 438 | Y2: 150 | Z2: 30 | AA2: 15 | AB2: 15 | AC2: 6 | AD2: 0 | AE2: 100 | AF2: 2 | AG2: 4 | AH2: 0 | AI2: 0 | AJ2: 1 | AK2: 1 | AL2: 0 | AM2: 10 | AN2: 10 | AO2: 0.4 | AP2: 0.5 | AQ2: 0 | AR2: 0 | AS2: 0 | AT2: 0 | AU2: 0 | AV2: 0.5 | AW2: 0 | AX2: 0 | AY2: 0 | AZ2: 0 | BA2: 0 | BB2: 0 | BC2: 0 | BD2: 1 | BE2: 3 | BF2: 24 | BG2: 0.5 | BH2: 5 | BI2: 1 | BJ2: 0 | BK2: 0 | BL2: 0 | BM2: 400
A3: Febraury(Quantity) | B3: Febraury | C3: Quantity | D3: 10 | E3: 12 | F3: 8 | G3: 12 | H3: 5 | I3: 0 | J3: 3 | K3: 2 | L3: 2 | M3: 2 | N3: 1 | O3: 1.5 | P3: 3 | Q3: 1 | R3: 0 | S3: 2 | T3: 25 | U3: 6 | V3: 6 | W3: 2 | X3: 231 | Y3: 135 | Z3: 25 | AA3: 15 | AB3: 9 | AC3: 9 | AD3: 0 | AE3: 0 | AF3: 2 | AG3: 7 | AH3: 1 | AI3: 1 | AJ3: 1 | AK3: 1 | AL3: 0.1 | AM3: 25 | AN3: 25 | AO3: 0.5 | AP3: 0.5 | AQ3: 0.5 | AR3: 1 | AS3: 0 | AT3: 0.5 | AU3: 0.3 | AV3: 0.5 | AW3: 0 | AX3: 0.5 | AY3: 0 | AZ3: 0 | BA3: 0 | BB3: 0 | BC3: 0 | BD3: 2 | BE3: 2 | BF3: 24 | BG3: 2 | BH3: 5 | BI3: 1 | BJ3: 0 | BK3: 0 | BL3: 1 | BM3: 0
A4: March(Quantity) | B4: March | C4: Quantity | D4: 8 | E4: 5 | F4: 4 | G4: 0 | H4: 3 | I4: 0 | J4: 3 | K4: 3 | L4: 3 | M4: 2 | N4: 0 | O4: 0 | P4: 1 | Q4: 0 | R4: 1 | S4: 0 | T4: 15 | U4: 4 | V4: 5 | W4: 0 | X4: 156 | Y4: 105 | Z4: 0 | AA4: 15 | AB4: 8 | AC4: 8 | AD4: 0 | AE4: 40 | AF4: 2 | AG4: 5 | AH4: 0 | AI4: 1 | AJ4: 1 | AK4: 1 | AL4: 0.1 | AM4: 0 | AN4: 15 | AO4: 0.5 | AP4: 0.3 | AQ4: 0 | AR4: 0 | AS4: 0 | AT4: 0.3 | AU4: 0 | AV4: 0 | AW4: 0 | AX4: 0 | AY4: 0 | AZ4: 0 | BA4: 0 | BB4: 0 | BC4: 0 | BD4: 0 | BE4: 2 | BF4: 0 | BG4: 0 | BH4: 3 | BI4: 1 | BJ4: 0 | BK4: 2 | BL4: 1 | BM4: 400
A5: April(Quantity) | B5: April | C5: Quantity | D5: 10 | E5: 7 | F5: 8 | G5: 10 | H5: 4 | I5: 3 | J5: 3 | K5: 3 | L5: 2 | M5: 2 | N5: 1 | O5: 3 | P5: 2 | Q5: 1 | R5: 0 | S5: 3 | T5: 13 | U5: 5 | V5: 5 | W5: 6 | X5: 130 | Y5: 120 | Z5: 25 | AA5: 15 | AB5: 12 | AC5: 12 | AD5: 0 | AE5: 90 | AF5: 2 | AG5: 8 | AH5: 1 | AI5: 0.2 | AJ5: 1 | AK5: 1 | AL5: 0.1 | AM5: 10 | AN5: 17 | AO5: 0.6 | AP5: 0.2 | AQ5: 0.5 | AR5: 0.3 | AS5: 0 | AT5: 0.6 | AU5: 0 | AV5: 1 | AW5: 0 | AX5: 0.3 | AY5: 0 | AZ5: 0 | BA5: 0 | BB5: 0 | BC5: 0 | BD5: 1 | BE5: 1.5 | BF5: 14 | BG5: 0 | BH5: 5 | BI5: 1 | BJ5: 0 | BK5: 2 | BL5: 0 | BM5: 400
A6: May(Quantity) | B6: May | C6: Quantity | D6: 13 | E6: 10 | F6: 10 | G6: 12 | H6: 5 | I6: 4 | J6: 6 | K6: 4 | L6: 1 | M6: 2 | N6: 1 | O6: 2.5 | P6: 3 | Q6: 2 | R6: 1 | S6: 1 | T6: 20 | U6: 6 | V6: 4 | W6: 6 | X6: 337 | Y6: 170 | Z6: 25 | AA6: 15 | AB6: 12 | AC6: 16 | AD6: 0 | AE6: 50 | AF6: 2 | AG6: 10 | AH6: 1 | AI6: 2 | AJ6: 1 | AK6: 1 | AL6: 0.1 | AM6: 12 | AN6: 15 | AO6: 1 | AP6: 0 | AQ6: 1 | AR6: 0.4 | AS6: 0 | AT6: 0.7 | AU6: 0.2 | AV6: 1 | AW6: 0 | AX6: 0.2 | AY6: 0 | AZ6: 1 | BA6: 0.4 | BB6: 0.1 | BC6: 0 | BD6: 1 | BE6: 1.5 | BF6: 24 | BG6: 0.5 | BH6: 5 | BI6: 1 | BJ6: 0 | BK6: 2 | BL6: 0 | BM6: 0
A7: June(Quantity) | B7: June | C7: Quantity | D7: 12 | E7: 10 | F7: 6 | G7: 9 | H7: 4 | I7: 3 | J7: 6 | K7: 4 | L7: 3 | M7: 3 | N7: 2 | O7: 3 | P7: 3 | Q7: 2 | R7: 0 | S7: 0 | T7: 20 | U7: 4 | V7: 5 | W7: 3 | X7: 156 | Y7: 102 | Z7: 25 | AA7: 20 | AB7: 12 | AC7: 12 | AD7: 0 | AE7: 58 | AF7: 2 | AG7: 6 | AH7: 1 | AI7: 1 | AJ7: 1 | AK7: 1 | AL7: 0.1 | AM7: 13 | AN7: 10 | AO7: 0.4 | AP7: 0 | AQ7: 1 | AR7: 0 | AS7: 0 | AT7: 1 | AU7: 0 | AV7: 0 | AW7: 0 | AX7: 0.3 | AY7: 0 | AZ7: 0 | BA7: 0 | BB7: 0 | BC7: 0 | BD7: 0 | BE7: 0 | BF7: 0 | BG7: 0 | BH7: 4 | BI7: 1 | BJ7: 0 | BK7: 2 | BL7: 1 | BM7: 0
A8: July(Quantity) | B8: July | C8: Quantity | D8: 10 | E8: 6 | F8: 6 | G8: 8 | H8: 3 | I8: 1 | J8: 2 | K8: 3 | L8: 5 | M8: 6 | N8: 1 | O8: 2.5 | P8: 3 | Q8: 3 | R8: 1 | S8: 0 | T8: 15 | U8: 7 | V8: 5 | W8: 3 | X8: 294 | Y8: 138 | Z8: 25 | AA8: 28 | AB8: 12 | AC8: 16 | AD8: 0 | AE8: 59 | AF8: 2 | AG8: 6 | AH8: 1.5 | AI8: 0.5 | AJ8: 2 | AK8: 2 | AL8: 0.3 | AM8: 10 | AN8: 22 | AO8: 0.5 | AP8: 0.5 | AQ8: 0.6 | AR8: 0.3 | AS8: 0 | AT8: 1 | AU8: 0.2 | AV8: 0 | AW8: 0 | AX8: 0.6 | AY8: 0 | AZ8: 0 | BA8: 0 | BB8: 0 | BC8: 0 | BD8: 0 | BE8: 0 | BF8: 0 | BG8: 0 | BH8: 4 | BI8: 2 | BJ8: 0 | BK8: 3 | BL8: 0 | BM8: 0
A9: August (Quantity) | B9: August | C9: Quantity | D9: 12 | E9: 8 | F9: 6 | G9: 9 | H9: 2 | I9: 2 | J9: 0 | K9: 3 | L9: 9 | M9: 9 | N9: 3 | O9: 2.5 | P9: 7 | Q9: 4 | R9: 1 | S9: 2.2 | T9: 17 | U9: 11 | V9: 5 | W9: 10 | X9: 592 | Y9: 320 | Z9: 0 | AA9: 0 | AB9: 0 | AC9: 0 | AD9: 0 | AE9: 50 | AF9: 2 | AG9: 10.1 | AH9: 2 | AI9: 1.6 | AJ9: 1 | AK9: 1 | AL9: 0.1 | AM9: 15 | AN9: 30 | AO9: 1.5 | AP9: 0.5 | AQ9: 1 | AR9: 1 | AS9: 0 | AT9: 0.5 | AU9: 0.5 | AV9: 3 | AW9: 0 | AX9: 1.2 | AY9: 0 | AZ9: 0.5 | BA9: 0 | BB9: 0 | BC9: 0 | BD9: 2 | BE9: 2 | BF9: 24 | BG9: 0.5 | BH9: 5 | BI9: 1 | BJ9: 1 | BK9: 3 | BL9: 1 | BM9: 200
A10: September(Quantity) | B10: September | C10: Quantity | D10: 12 | E10: 8 | F10: 6 | G10: 9 | H10: 1 | I10: 2 | J10: 0 | K10: 4 | L10: 3 | M10: 3 | N10: 2 | O10: 2.5 | P10: 0 | Q10: 0 | R10: 0 | S10: 1 | T10: 20 | U10: 5 | V10: 7 | W10: 7 | X10: 360 | Y10: 112 | Z10: 0 | AA10: 0 | AB10: 10 | AC10: 14 | AD10: 0 | AE10: 50 | AF10: 2 | AG10: 10 | AH10: 2 | AI10: 1 | AJ10: 1 | AK10: 1 | AL10: 0.1 | AM10: 15 | AN10: 30 | AO10: 0 | AP10: 0 | AQ10: 0.5 | AR10: 0.5 | AS10: 0 | AT10: 1 | AU10: 0 | AV10: 0 | AW10: 0 | AX10: 1 | AY10: 0 | AZ10: 0 | BA10: 0 | BB10: 0 | BC10: 0 | BD10: 0 | BE10: 0 | BF10: 0 | BG10: 0 | BH10: 3 | BI10: 1 | BJ10: 0 | BK10: 3 | BL10: 1 | BM10: 0
A11: October(Quantity) | B11: October | C11: Quantity | D11: 8 | E11: 6 | F11: 7 | G11: 6 | H11: 3 | I11: 2 | J11: 0 | K11: 5 | L11: 10 | M11: 10 | N11: 0 | O11: 2 | P11: 2 | Q11: 2 | R11: 0 | S11: 1 | T11: 15 | U11: 5 | V11: 5 | W11: 6 | X11: 300 | Y11: 180 | Z11: 25 | AA11: 5 | AB11: 17 | AC11: 10 | AD11: 0 | AE11: 50 | AF11: 2 | AG11: 10 | AH11: 0 | AI11: 0 | AJ11: 1 | AK11: 1 | AL11: 0.1 | AM11: 0 | AN11: 15 | AO11: 0.5 | AP11: 0 | AQ11: 0 | AR11: 0.4 | AS11: 0 | AT11: 1 | AU11: 0 | AV11: 0 | AW11: 0 | AX11: 0 | AY11: 0 | AZ11: 0 | BA11: 0 | BB11: 0 | BC11: 0 | BD11: 0 | BE11: 0 | BF11: 0 | BG11: 0 | BH11: 0 | BI11: 0 | BJ11: 0 | BK11: 3 | BL11: 0 | BM11: 600
A12: November(Quantity) | B12: November | C12: Quantity | D12: 12 | E12: 6 | F12: 0 | G12: 12 | H12: 5 | I12: 0 | J12: 0 | K12: 5 | L12: 6 | M12: 6 | N12: 0 | O12: 3 | P12: 3 | Q12: 3 | R12: 0 | S12: 1 | T12: 15 | U12: 3 | V12: 2 | W12: 6 | X12: 60 | Y12: 32 | Z12: 15 | AA12: 5 | AB12: 0 | AC12: 0 | AD12: 0 | AE12: 0 | AF12: 0 | AG12: 2 | AH12: 0 | AI12: 0 | AJ12: 1 | AK12: 1 | AL12: 0.1 | AM12: 10 | AN12: 15 | AO12: 0.5 | AP12: 0 | AQ12: 0.5 | AR12: 0 | AS12: 0 | AT12: 0.5 | AU12: 0 | AV12: 0 | AW12: 0 | AX12: 0 | AY12: 0 | AZ12: 0 | BA12: 0 | BB12: 0 | BC12: 0 | BD12: 0 | BE12: 0 | BF12: 0 | BG12: 0 | BH12: 2 | BI12: 1 | BJ12: 0 | BK12: 2 | BL12: 0 | BM12: 600
A13: December(Quantity) | B13: December | C13: Quantity | D13: 11 | E13: 2 | F13: 4 | G13: 8 | H13: 2 | I13: 2 | J13: 0 | K13: 0 | L13: 5 | M13: 5 | N13: 0 | O13: 2 | P13: 2 | Q13: 2 | R13: 0 | S13: 0 | T13: 15 | U13: 3 | V13: 0 | W13: 0 | X13: 180 | Y13: 128 | Z13: 10 | AA13: 3 | AB13: 0 | AC13: 0 | AD13: 0 | AE13: 50 | AF13: 2 | AG13: 10 | AH13: 0 | AI13: 0 | AJ13: 1 | AK13: 1 | AL13: 0.1 | AM13: 8 | AN13: 15 | AO13: 0.5 | AP13: 0.25 | AQ13: 0.5 | AR13: 0.2 | AS13: 0 | AT13: 1 | AU13: 0.2 | AV13: 0 | AW13: 0 | AX13: 0.3 | AY13: 0 | AZ13: 0 | BA13: 0 | BB13: 0 | BC13: 0 | BD13: 0 | BE13: 0 | BF13: 0 | BG13: 0 | BH13: 3 | BI13: 1 | BJ13: 0 | BK13: 2 | BL13: 0 | BM13: 0
... A49: December(Unit Price) | B49: December | C49: Unit Price | D49: 37 | E49: 40 | F49: 40 | G49: 80 | H49: 55 | I49: 38 | J49: 0 | K49: 0 | L49: 70 | M49: 70 | N49: 0 | O49: 70 | P49: 650 | Q49: 650 | R49: 0 | S49: 0 | T49: 43 | U49: 170 | V49: 0 | W49: 0 | X49: 92 | Y49: 112.5 | Z49: 40 | AA49: 40 | AB49: 0 | AC49: 0 | AD49: 0 | AE49: 132 | AF49: 0 | AG49: 710 | AH49: 0 | AI49: 0 | AJ49: 200 | AK49: 750 | AL49: 1650 | AM49: 14 | AN49: 14 | AO49: 3400 | AP49: 1000 | AQ49: 400 | AR49: 750 | AS49: 0 | AT49: 330 | AU49: 2000 | AV49: 0 | AW49: 0 | AX49: 2600 | AY49: 0 | AZ49: 0 | BA49: 0 | BB49: 0 | BC49: 0 | BD49: 0 | BE49: 0 | BF49: 0 | BG49: 0 | BH49: 45 | BI49: 330 | BJ49: 0 | BK49: 70 | BL49: 0 | BM49: 0

Sheet Inventory
B1: Biryani | F1: Mandi | J1: Chicken Bodies (KG) | N1: Chicken Lollipop | R1: Chicken Boneless | V1: Pet Bottles | Z1: Glass Bottles | AE1: Water Bottles
A2: Column1 | B2: Cooked KG | C2: Plates Sold | D2: Plates Left | E2: Column2 | F2: Cooked KG3 | G2: Plates Sold4 | H2: Plates Left5 | I2: Column6 | J2: Ordered | K2: Used | L2: Left | M2: Column7 | N2: Ordered KG | O2: Plates Sold8 | P2: Left KG | Q2: Column9 | R2: Ordered KG10 | S2: Plates Sold11 | T2: Left KG12 | U2: Column13 | V2: Thumbsup | W2: Sprite | X2: Coco cola | Y2: Column14 | Z2: Thumbsup15 | AA2: Sprite16 | AB2: Fanta | AC2: Coco cola17 | AD2: Column18 | AE2: Column19
A3: 45901 | B3: 6 | C3: =16+23 -> 39 | D3: 0 | F3: 0 | G3: 0 | H3: 0 | J3: 9 | K3: =J3-L3 -> 7.5 | L3: 1.5 | N3: 1.8 | O3: 0 | P3: 1.8 | R3: 2.7 | S3: 5 | T3: 1.4 | V3: =(28*0)+0 -> 0 | W3: =(28*1)+32 -> 60 | X3: =(28*1)+32 -> 60 | Z3: =(24*0)+0 -> 0 | AA3: =(24*0)+0 -> 0 | AB3: 0 | AC3: 0 | AE3: =(12*18)+36 -> 252
A4: 45902 | B4: 8.5 | C4: =15+34 -> 49 | D4: 0 | F4: 0 | G4: 0 | H4: 0 | J4: 9.8 | K4: =J4+L3-L4 -> 8.3 | L4: 3 | N4: 0 | O4: 2 | P4: 2 | R4: 1 | S4: 6 | T4: 2 | V4: =(28*0)+0 -> 0 | W4: =(28*1)+33 -> 61 | X4: =(28*1)+29 -> 57 | Z4: =(24*0)+0 -> 0 | AA4: =(24*0)+0 -> 0 | AB4: =(24*0)+0 -> 0 | AC4: =(24*0)+0 -> 0 | AE4: =(12*18)+25 -> 241
A5: 45903 | B5: 7.5 | C5: =14+34 -> 48 | D5: 0 | F5: 0 | G5: 0 | H5: 0 | J5: 13.3 | K5: =J5+L4-L5 -> 10.4 | L5: 5.9 | N5: 0 | O5: 2 | P5: 1.2 | R5: 0 | S5: 14 | T5: 0.5 | V5: 0 | W5: 0 | X5: 0 | Z5: 0 | AA5: 0 | AB5: 0 | AC5: 0 | AE5: 0
A6: 45904 | B6: 7 | C6: =13+31 -> 44 | D6: 6 | F6: 0 | G6: 0 | H6: 0 | J6: 17.4 | K6: =J6+L5-L6 -> 11.9 | L6: 11.4 | N6: 0 | O6: 6 | P6: 0 | R6: 1.8 | S6: 11 | T6: 2 | V6: =(28*3)+25 -> 109 | W6: =(28*5)+31 -> 171 | X6: =(28*3)+28 -> 112 | Z6: =(24*5)+24 -> 144 | AA6: =(24*5)+24 -> 144 | AB6: =(24*0)+0 -> 0 | AC6: =(24*1)+24 -> 48 | AE6: =(12*16)+24 -> 216
A7: 45905 | B7: 7 | C7: 36 | D7: 6 | F7: 0 | G7: 0 | H7: 0 | J7: 5 | K7: =J7+L6-L7 -> 8.2 | L7: 8.2 | N7: 0 | O7: 0 | P7: 0 | R7: 0 | S7: 24 | T7: 0 | V7: =(28*3)+25 -> 109 | W7: =(28*5)+27 -> 167 | X7: =(28*3)+28 -> 112 | Z7: =(24*5)+14 -> 134 | AA7: =(24*5)+19 -> 139 | AB7: =(24*0)+0 -> 0 | AC7: =(24*1)+21 -> 45 | AE7: =(12*16)+6 -> 198
A8: 45906 | B8: 7 | C8: 35 | D8: 7 | F8: 0 | G8: 0 | H8: 0 | J8: 6.6 | K8: =J8+L7-L8 -> 3.8 | L8: 11 | N8: 1.2 | O8: 3.4 | P8: 0 | R8: 3 | S8: 10 | T8: 1 | V8: =(28*3)+21 -> 105 | W8: =(28*5)+16 -> 156 | X8: =(28*3)+26 -> 110 | Z8: =(24*5)+14 -> 134 | AA8: =(24*5)+18 -> 138 | AB8: =(24*0)+0 -> 0 | AC8: =(24*1)+20 -> 44 | AE8: =(12*12)+32 -> 176
A9: 45907 | B9: 9 | C9: 51 | D9: 0 | F9: 0 | G9: 0 | H9: 0 | J9: 5.9 | K9: =J9+L8-L9 -> 6.9 | L9: 10 | N9: 2.1 | O9: 6.1 | P9: 0 | R9: 2.6 | S9: 29 | T9: 0 | V9: =(28*3)+16 -> 100 | W9: =(28*5)+14 -> 154 | X9: =(28*3)+21 -> 105 | Z9: =(24*5)+13 -> 133 | AA9: =(24*5)+17 -> 137 | AB9: =(24*0)+0 -> 0 | AC9: =(24*1)+16 -> 40 | AE9: =(12*10)+20 -> 140
A10: 45908 | B10: 6 | C10: 29 | D10: 0 | F10: 0 | G10: 0 | H10: 0 | J10: 0 | K10: =J10+L9-L10 -> 4.6 | L10: 5.4 | N10: 0 | O10: 0 | P10: 0 | R10: 3 | S10: 20 | T10: 0 | V10: =(28*3)+9 -> 93 | W10: =(28*5)+11 -> 151 | X10: =(28*3)+19 -> 103 | Z10: =(24*5)+13 -> 133 | AA10: =(24*5)+15 -> 135 | AB10: =(24*0)+0 -> 0 | AC10: =(24*1)+14 -> 38 | AE10: =(12*10)+26 -> 146
A11: 45909 | B11: 5 | C11: 21 | D11: 9 | F11: 0 | G11: 0 | H11: 0 | J11: 9.8 | K11: =J11+L10-L11 -> 3.2 | L11: 12 | N11: 1 | O11: 4 | P11: 0 | R11: 2 | S11: 7 | T11: 0.4 | V11: =(28*2)+37 -> 93 | W11: =(28*4)+38 -> 150 | X11: =(28*3)+19 -> 103 | Z11: =(24*4)+32 -> 128 | AA11: =(24*4)+32 -> 128 | AB11: =(24*0)+0 -> 0 | AC11: =(24*1)+13 -> 37 | AE11: =(12*4)+21 -> 69
A12: 45910 | B12: 6 | C12: 29 | D12: 6 | F12: 0 | G12: 0 | H12: 0 | J12: 6.5 | K12: =J12+L11-L12 -> 4.8 | L12: 13.7 | N12: 1 | O12: 4.4 | P12: 0 | R12: 2 | S12: 9 | T12: 1.3 | V12: 0 | W12: 0 | X12: 0 | Z12: 0 | AA12: 0 | AB12: 0 | AC12: 0 | AE12: 0
A13: 45911 | B13: 5 | C13: 26 | D13: 4 | F13: 1.2 | G13: 3 | H13: 5 | J13: 5.2 | K13: =J13+L12-L13 -> 6.7 | L13: 12.2 | N13: 1.5 | O13: 4 | P13: 0 | R13: 3 | S13: 5 | T13: 4 | V13: 0 | W13: 0 | X13: 0 | Z13: 0 | AA13: 0 | AB13: 0 | AC13: 0 | AE13: 0
A14: 45912 | B14: 5 | C14: 20 | D14: 10 | F14: 1 | G14: 1 | H14: 5 | J14: 0 | K14: =J14+L13-L14 -> 4.2 | L14: 8 | N14: 2.2 | O14: 2.3 | P14: 0.8 | R14: 0 | S14: 4 | T14: 3.3 | V14: 0 | W14: 0 | X14: 0 | Z14: 0 | AA14: 0 | AB14: 0 | AC14: 0 | AE14: 0
A15: 45913 | B15: 6 | C15: 24 | D15: 12 | F15: 2 | G15: 11 | H15: 1 | J15: 7.2 | K15: =J15+L14-L15 -> 5.7 | L15: 9.5 | N15: 0 | O15: 0 | P15: 1.2 | R15: 0 | S15: 9 | T15: 2.4 | V15: 0 | W15: 0 | X15: 0 | Z15: 0 | AA15: 0 | AB15: 0 | AC15: 0 | AE15: 0
A16: 45914 | B16: 7 | C16: 31 | D16: 0 | F16: 2 | G16: 12 | H16: 0 | J16: 0 | K16: =J16+L15-L16 -> 5.6 | L16: 3.9 | N16: 0 | O16: 8.3 | P16: 0.8 | R16: 0 | S16: 12 | T16: 2.3 | V16: 0 | W16: 0 | X16: 0 | Z16: 0 | AA16: 0 | AB16: 0 | AC16: 0 | AE16: 0
A17: 45915 | B17: 5 | C17: 19 | D17: 11 | F17: 0 | G17: 0 | H17: 0 | J17: 6.8 | K17: =J17+L16-L17 -> 4.7 | L17: 6 | N17: 2.1 | O17: 1 | P17: 2.5 | R17: 0 | S17: 7 | T17: 1.7 | V17: =(28*2)+37 -> 93 | W17: =(28*4)+38 -> 150 | X17: =(28*3)+19 -> 103 | Z17: =(24*4)+32 -> 128 | AA17: =(24*4)+32 -> 128 | AB17: =(24*0)+0 -> 0 | AC17: =(24*1)+13 -> 37 | AE17: =(12*4)+21 -> 69
A18: 45916 | B18: 5 | C18: 35 | D18: 0 | F18: 1 | G18: 6 | H18: 0 | J18: 6.3 | K18: =J18+L17-L18 -> 4.8 | L18: 7.5 | N18: 0 | O18: 2.2 | P18: 2 | R18: 1 | S18: 18 | T18: 1 | V18: =(28*2)+17 -> 73 | W18: =(28*4)+27 -> 139 | X18: =(28*3)+12 -> 96 | Z18: =(24*4)+23 -> 119 | AA18: =(24*4)+24 -> 120 | AB18: =(24*0)+0 -> 0 | AC18: =(24*1)+13 -> 37 | AE18: =(12*48)+11 -> 587
A19: 45917 | B19: 5 | C19: 26 | D19: 4 | F19: 1.5 | G19: 0 | H19: 9 | J19: 11.5 | K19: =J19+L18-L19 -> 4.4 | L19: 14.6 | N19: 2.4 | O19: 6.2 | P19: 2.9 | R19: 3 | S19: 10 | T19: 2.5 | V19: 0 | W19: 0 | X19: 0 | Z19: 0 | AA19: 0 | AB19: 0 | AC19: 0 | AE19: 0
A20: 45918 | B20: 5 | C20: 18 | D20: 12 | F20: 0 | G20: 0 | H20: 0 | J20: 0 | K20: =J20+L19-L20 -> 4.3 | L20: 10.3 | N20: 0 | O20: 6.4 | P20: 0.4 | R20: 0 | S20: 14 | T20: 0.8 | V20: 0 | W20: 0 | X20: 0 | Z20: 0 | AA20: 0 | AB20: 0 | AC20: 0 | AE20: 0
A21: 45919 | B21: 4 | C21: 22 | D21: 2 | F21: 0 | G21: 0 | H21: 0 | J21: 0 | K21: =J21+L20-L21 -> 2.5 | L21: 7.8 | N21: 2.2 | O21: 3 | P21: 1.5 | R21: 2.6 | S21: 5 | T21: 2.4 | V21: 0 | W21: 0 | X21: 0 | Z21: 0 | AA21: 0 | AB21: 0 | AC21: 0 | AE21: 0
A22: 45920 | B22: 5 | C22: 23 | D22: 7 | F22: 0 | G22: 0 | H22: 0 | J22: 8 | K22: =J22+L21-L22 -> 3.8 | L22: 12 | N22: 0 | O22: 2.3 | P22: 1.2 | R22: 1.5 | S22: 10 | T22: 2.8 | V22: 0 | W22: 0 | X22: 0 | Z22: 0 | AA22: 0 | AB22: 0 | AC22: 0 | AE22: 0
A23: 45921 | B23: 7 | C23: 49 | D23: 0 | F23: 0 | G23: 0 | H23: 0 | J23: 4.9 | K23: =J23+L22-L23 -> 6.5 | L23: 10.4 | N23: 1.6 | O23: 0 | P23: 2.4 | R23: 0 | S23: 18 | T23: 0.4 | V23: 0 | W23: 0 | X23: 0 | Z23: 0 | AA23: 0 | AB23: 0 | AC23: 0 | AE23: 0
A24: 45922 | B24: 0 | C24: 0 | D24: 0 | F24: 0 | G24: 0 | H24: 0 | J24: 0 | K24: =J24+L23-L24 -> 0 | L24: 10.4 | N24: 0 | O24: 0 | P24: 2.4 | R24: 0 | S24: 0 | T24: 0 | V24: 0 | W24: 0 | X24: 0 | Z24: 0 | AA24: 0 | AB24: 0 | AC24: 0 | AE24: 0
A25: 45923 | B25: 9 | C25: 52 | D25: 2 | F25: 0 | G25: 0 | H25: 0 | J25: 5.2 | K25: =J25+L24-L25 -> 10.3 | L25: 5.3 | N25: 1 | O25: 7 | P25: 2.2 | R25: 2 | S25: 22 | T25: 0 | V25: 0 | W25: 0 | X25: 0 | Z25: 0 | AA25: 0 | AB25: 0 | AC25: 0 | AE25: 0
A26: 45924 | B26: 10 | C26: 46 | D26: 14 | F26: 0 | G26: 0 | H26: 0 | J26: 7.8 | K26: =J26+L25-L26 -> 6.7 | L26: 6.4 | N26: 0 | O26: 6.1 | P26: 0 | R26: 2 | S26: 10 | T26: 1.6 | V26: 0 | W26: 0 | X26: 0 | Z26: 0 | AA26: 0 | AB26: 0 | AC26: 0 | AE26: 0
A27: 45925 | B27: 5 | C27: 21 | D27: 9 | F27: 0 | G27: 0 | H27: 0 | J27: 6.3 | K27: =J27+L26-L27 -> 6.3 | L27: 6.4 | N27: 0 | O27: 1 | P27: 0.6 | R27: 1 | S27: 6 | T27: 2.8 | V27: 0 | W27: 0 | X27: 0 | Z27: 0 | AA27: 0 | AB27: 0 | AC27: 0 | AE27: 0
A28: 45926 | B28: 7 | C28: 43 | D28: 0 | F28: 0 | G28: 0 | H28: 0 | J28: 7.1 | K28: =J28+L27-L28 -> 4.5 | L28: 9 | N28: 1 | O28: 2.2 | P28: 1 | R28: 0 | S28: 13 | T28: 0.8 | V28: 0 | W28: 0 | X28: 0 | Z28: 0 | AA28: 0 | AB28: 0 | AC28: 0 | AE28: 0
A29: 45927 | B29: 8 | C29: 48 | D29: 0 | F29: 0 | G29: 0 | H29: 0 | J29: 6.9 | K29: =J29+L28-L29 -> 8.9 | L29: 7 | N29: 0 | O29: 1 | P29: 1.2 | R29: 2 | S29: 12 | T29: 2.5 | V29: 0 | W29: 0 | X29: 0 | Z29: 0 | AA29: 0 | AB29: 0 | AC29: 0 | AE29: 0
A30: 45928 | B30: 9 | C30: 53 | D30: 1 | F30: 0 | G30: 0 | H30: 0 | J30: 8.4 | K30: =J30+L29-L30 -> 10.1 | L30: 5.3 | N30: 2.5 | O30: 3.2 | P30: 3 | R30: 0 | S30: 15 | T30: 0 | V30: 0 | W30: 0 | X30: 0 | Z30: 0 | AA30: 0 | AB30: 0 | AC30: 0 | AE30: 0
A31: 45929 | B31: 6 | C31: 35 | D31: 1 | F31: 0 | G31: 0 | H31: 0 | J31: 6.3 | K31: =J31+L30-L31 -> 5.3 | L31: 6.3 | N31: 0 | O31: 10 | P31: 0 | R31: 1.6 | S31: 14 | T31: 1.3 | V31: =(28*1)+32 -> 60 | W31: =(28*3)+36 -> 120 | X31: =(28*3)+25 -> 109 | Z31: =(24*3)+30 -> 102 | AA31: =(24*4)+16 -> 112 | AB31: =(24*0)+0 -> 0 | AC31: =(24*1)+7 -> 31 | AE31: =(12*32)+21 -> 405
A32: 45930 | B32: 11 | C32: 47 | D32: 0 | F32: 0 | G32: 0 | H32: 0 | J32: 11.1 | K32: =J32+L31-L32 -> 9.1 | L32: 8.3 | N32: 0 | O32: 0.3 | P32: 0 | R32: 1 | S32: 26 | T32: 0 | V32: 0 | W32: 0 | X32: 0 | Z32: 0 | AA32: 0 | AB32: 0 | AC32: 0 | AE32: 0
A33: Total | B33: =SUM(B3:B32) -> 193 | C33: =SUM(C3:C32) -> 1019 | D33: =SUM(D3:D32) -> 123 | F33: =SUM(F3:F32) -> 8.7 | G33: =SUM(G3:G32) -> 33 | H33: =SUM(H3:H32) -> 20 | J33: =SUM(J3:J32) -> 192.3 | K33: =SUM(K3:K32) -> 184 | N33: =SUM(N3:N32) -> 23.6 | O33: =SUM(O3:O32) -> 94.4 | R33: =SUM(R3:R32) -> 38.8 | S33: =SUM(S3:S32) -> 365
A36: 45870 | B36: 3 | C36: 13 | D36: 0 | F36: 27 | G36: =11+178 -> 189 | H36: 0 | J36: 33.5 | K36: =J36-L36 -> 29.5 | L36: 4 | N36: 0 | O36: 0 | P36: 2 | R36: 0 | S36: 0 | T36: 0 | V36: =(28*3)+26 -> 110 | W36: =(28*5)+21 -> 161 | X36: =(28*4)+17 -> 129 | Z36: =(24*1)+8 -> 32 | AA36: =(24*0)+21 -> 21 | AB36: =(24*0)+20 -> 20 | AC36: =(24*1)+15 -> 39 | AE36: =(12*17)+36 -> 240
A37: 45871 | B37: 8 | C37: 39 | D37: 9 | F37: 43 | G37: =17+308 -> 325 | H37: 0 | J37: 72.6 | K37: =J37+L36-L37 -> 72.4 | L37: 4.2 | N37: 0 | O37: 0 | P37: 0 | R37: 0 | S37: 0 | T37: 0 | V37: 0 | W37: 0 | X37: 0 | Z37: 0 | AA37: 0 | AB37: 0 | AC37: 0 | AE37: 0
A38: 45872 | B38: 12 | C38: 61 | D38: 13 | F38: 44 | G38: 340 | H38: 0 | J38: 62.2 | K38: =J38+L37-L38 -> 66.4 | L38: 0 | N38: 1.3 | O38: 9 | P38: 0 | R38: 3 | S38: 21 | T38: 0 | V38: 0 | W38: 0 | X38: 0 | Z38: 0 | AA38: 0 | AB38: 0 | AC38: 0 | AE38: 0
A39: 45873 | B39: 0 | C39: 0 | D39: 0 | F39: 22 | G39: =18+157 -> 175 | H39: 0 | J39: 40.3 | K39: =J39+L38-L39 -> 26.8 | L39: 13.5 | N39: 0 | O39: 0 | P39: 0 | R39: 0 | S39: 0 | T39: 0 | V39: 0 | W39: 0 | X39: 0 | Z39: 0 | AA39: 0 | AB39: 0 | AC39: 0 | AE39: 0
A40: 45874 | B40: 4 | C40: 26 | D40: 0 | F40: 27 | G40: =8+200 -> 208 | H40: 8 | J40: 39.2 | K40: =J40+L39-L40 -> 46.7 | L40: 6 | N40: 2.4 | O40: 5.3 | P40: 1.5 | R40: 2 | S40: 16 | T40: 1.3 | V40: =(28*3)+10 -> 94 | W40: =(28*5)+2 -> 142 | X40: =(28*4)+13 -> 125 | Z40: =(24*1)+1 -> 25 | AA40: =(24*0)+6 -> 6 | AB40: =(24*0)+6 -> 6 | AC40: =(24*1)+12 -> 36 | AE40: =(12*8)+27 -> 123
A41: 45875 | B41: 5 | C41: 21 | D41: 0 | F41: 19 | G41: 178 | H41: 0 | J41: 38.7 | K41: =J41+L40-L41 -> 40.2 | L41: 4.5 | N41: 0 | O41: 4 | P41: 0 | R41: 2 | S41: 9 | T41: 0 | V41: 0 | W41: 0 | X41: 0 | Z41: 0 | AA41: 0 | AB41: 0 | AC41: 0 | AE41: 0
A42: 45876 | B42: 5 | C42: 31 | D42: 5 | F42: 17 | G42: =11+122 -> 133 | H42: 0 | J42: 35.5 | K42: =J42+L41-L42 -> 34.5 | L42: 5.5 | N42: 1.2 | O42: 4.3 | P42: 0 | R42: 0 | S42: 13 | T42: 1.1 | V42: 0 | W42: 0 | X42: 0 | Z42: 0 | AA42: 0 | AB42: 0 | AC42: 0 | AE42: 0
A43: 45877 | B43: 5 | C43: 17 | D43: 12 | F43: 2 | G43: 12 | H43: 0 | J43: 10.1 | K43: =J43+L42-L43 -> 5.6 | L43: 10 | N43: 0 | O43: 1.2 | P43: 0.6 | R43: 1 | S43: 3 | T43: 2.5 | V43: 0 | W43: 0 | X43: 0 | Z43: 0 | AA43: 0 | AB43: 0 | AC43: 0 | AE43: 0
A44: 45878 | B44: 6 | C44: 42 | D44: 0 | F44: 2.5 | G44: 10 | H44: 0 | J44: 9.2 | K44: =J44+L43-L44 -> 8.8 | L44: 10.4 | N44: 0 | O44: 4.2 | P44: 0 | R44: 0 | S44: 20 | T44: 0 | V44: =(28*2)+11 -> 67 | W44: =(28*4)+19 -> 131 | X44: =(28*4)+10 -> 122 | Z44: =(24*0)+14 -> 14 | AA44: =(24*0)+0 -> 0 | AB44: =(24*0)+4 -> 4 | AC44: =(24*0)+31 -> 31 | AE44: =(54*8)+4 -> 436
A45: 45879 | B45: 9.5 | C45: 59 | D45: 0 | F45: 5 | G45: 33 | H45: 0 | J45: 13.7 | K45: =J45+L44-L45 -> 18 | L45: 6.1 | N45: 3 | O45: 9.3 | P45: 0.2 | R45: 4 | S45: 30 | T45: 0.3 | V45: 0 | W45: 0 | X45: 0 | Z45: 0 | AA45: 0 | AB45: 0 | AC45: 0 | AE45: 0
A46: 45880 | B46: 4.5 | C46: 22 | D46: 5 | F46: 4 | G46: 21 | H46: 3 | J46: 12.4 | K46: =J46+L45-L46 -> 2.2 | L46: 16.3 | N46: 2 | O46: 1 | P46: 1.8 | R46: 2 | S46: 13 | T46: 0 | V46: =(28*1)+27 -> 55 | W46: =(28*4)+4 -> 116 | X46: =(28*4)+8 -> 120 | Z46: =(24*0)+10 -> 10 | AA46: =(24*0)+0 -> 0 | AB46: =(24*0)+3 -> 3 | AC46: =(24*0)+28 -> 28 | AE46: =(48*12)+33 -> 609
A47: 45881 | B47: 3.5 | C47: 23 | D47: 0 | F47: 2.5 | G47: 5 | H47: 10 | J47: 13.1 | K47: =J47+L46-L47 -> 12.7 | L47: =9.5+7.2 -> 16.7 | N47: 2 | O47: 5.2 | P47: 1.8 | R47: 1 | S47: 9 | T47: 0.2 | V47: =(28*1)+23 -> 51 | W47: =(28*3)+29 -> 113 | X47: =(28*4)+8 -> 120 | Z47: =(24*0)+5 -> 5 | AA47: =(24*0)+0 -> 0 | AB47: =(24*0)+3 -> 3 | AC47: =(24*0)+28 -> 28 | AE47: =(42*12)+41 -> 545
A48: 45882 | B48: 5 | C48: 20 | D48: 10 | F48: 2 | G48: 10 | H48: 2 | J48: 8.7 | K48: =J48+L47-L48 -> 5 | L48: =7.6+7.5+5.3 -> 20.4 | N48: 1 | O48: 4.4 | P48: 1.7 | R48: 2 | S48: 20 | T48: 0 | V48: =(28*1)+21 -> 49 | W48: =(28*3)+23 -> 107 | X48: =(28*4)+8 -> 120 | Z48: =(24*0)+2 -> 2 | AA48: =(24*0)+0 -> 0 | AB48: =(24*0)+2 -> 2 | AC48: =(24*0)+28 -> 28 | AE48: =(42*12)+27 -> 531
A49: 45883 | B49: 4.5 | C49: 16 | D49: 11 | F49: 2 | G49: 6 | H49: 6 | J49: 0 | K49: =J49+L48-L49 -> 5.8 | L49: =12+2.6 -> 14.6 | N49: 0 | O49: 6.2 | P49: 0 | R49: 2.5 | S49: 12 | T49: 0 | V49: =(28*1)+15 -> 43 | W49: =(28*3)+22 -> 106 | X49: =(28*4)+8 -> 120 | Z49: =(24*0)+1 -> 1 | AA49: 0 | AB49: =(24*0)+0 -> 0 | AC49: =(24*0)+28 -> 28 | AE49: =(41*12)+27 -> 519
A50: 45884 | B50: 9 | C50: 51 | D50: 0 | F50: 7 | G50: 34 | H50: 8 | J50: 13.5 | K50: =J50+L49-L50 -> 20.3 | L50: 7.8 | N50: 2.5 | O50: 6.3 | P50: 0 | R50: 2 | S50: 29 | T50: 0 | V50: =(28*1)+21 -> 49 | W50: =(28*3)+23 -> 107 | X50: =(28*4)+8 -> 120 | Z50: =(24*0)+2 -> 2 | AA50: 0 | AB50: =(24*0)+2 -> 2 | AC50: =(24*0)+28 -> 28 | AE50: =(42*12)+27 -> 531
A51: 45885 | B51: 0 | C51: 0 | D51: 0 | F51: 0 | G51: 0 | H51: 0 | J51: 0 | K51: =J51+L50-L51 -> 0 | L51: 7.8 | N51: 0 | O51: 0 | P51: 2.5 | R51: 0 | S51: 0 | T51: 0 | V51: 0 | W51: 0 | X51: 0 | Z51: 0 | AA51: 0 | AB51: 0 | AC51: 0 | AE51: 0
A52: 45886 | B52: 8.3 | C52: 50 | D52: 1 | F52: 3 | G52: 9 | H52: 9 | J52: 15.8 | K52: =J52+L51-L52 -> 12.8 | L52: =7.4+3.4 -> 10.8 | N52: 3 | O52: 1.1 | P52: 2.5 | R52: 2 | S52: 21 | T52: 0 | V52: 0 | W52: 0 | X52: 0 | Z52: 0 | AA52: 0 | AB52: 0 | AC52: 0 | AE52: 0
A53: 45887 | B53: 5 | C53: 26 | D53: 4 | F53: 2 | G53: 3 | H53: 9 | J53: 8 | K53: =J53+L52-L53 -> 4.2 | L53: =11.4+3.2 -> 14.6 | N53: 0 | O53: 1.2 | P53: 2.1 | R53: 2.1 | S53: 15 | T53: 0 | V53: 0 | W53: 0 | X53: 0 | Z53: 0 | AA53: 0 | AB53: 0 | AC53: 0 | AE53: 0
A54: 45888 | B54: 4 | C54: 15 | D54: 9 | F54: 2 | G54: 10 | H54: 2 | J54: 6 | K54: =J54+L53-L54 -> 4.1 | L54: =7.8+8.7 -> 16.5 | N54: 0 | O54: 2 | P54: 2 | R54: 2 | S54: 9 | T54: 1.7 | V54: =(28*0)+18 -> 18 | W54: =(28*3)+8 -> 92 | X54: =(28*3)+23 -> 107 | Z54: =(24*0)+0 -> 0 | AA54: =(24*0)+0 -> 0 | AB54: =(24*0)+0 -> 0 | AC54: =(24*0)+18 -> 18 | AE54: =(34*12)+23 -> 431
A55: 45889 | B55: 4 | C55: 22 | D55: 0 | F55: 2 | G55: 3 | H55: 9 | J55: 8.9 | K55: =J55+L54-L55 -> 5.6 | L55: =13+6.8 -> 19.8 | N55: 0 | O55: 6 | P55: 0.7 | R55: 1 | S55: 15 | T55: 0.7 | V55: =(28*0)+18 -> 18 | W55: =(28*3)+8 -> 92 | X55: =(28*3)+23 -> 107 | Z55: =(24*0)+0 -> 0 | AA55: =(24*0)+0 -> 0 | AB55: =(24*0)+0 -> 0 | AC55: =(24*0)+18 -> 18 | AE55: =(34*12)+23 -> 431
A56: 45890 | B56: 4 | C56: 13 | D56: 0 | F56: 2 | G56: 6 | H56: 6 | J56: 0 | K56: =J56+L55-L56 -> 5.3 | L56: =9.4+5.1 -> 14.5 | N56: 2.3 | O56: 4.2 | P56: 1.4 | R56: 2 | S56: 7 | T56: 1 | V56: 0 | W56: 0 | X56: 0 | Z56: 0 | AA56: 0 | AB56: 0 | AC56: 0 | AE56: 0
A57: 45891 | B57: 15 | C57: 95 | D57: 10 | F57: 2 | G57: 4 | H57: 8 | J57: 24.7 | K57: =J57+L56-L57 -> 23.1 | L57: =5+11.1 -> 16.1 | N57: 0 | O57: 1.3 | P57: 2.4 | R57: 0 | S57: 7 | T57: 2 | V57: 0 | W57: 0 | X57: 0 | Z57: 0 | AA57: 0 | AB57: 0 | AC57: 0 | AE57: 0
A58: 45892 | B58: 21 | C58: =34+101 -> 135 | D58: 0 | F58: 2 | G58: 4 | H58: 8 | J58: 29.2 | K58: =J58+L57-L58 -> 33.8 | L58: =6.5+5 -> 11.5 | N58: 0 | O58: 1.4 | P58: 3.2 | R58: 0 | S58: 4 | T58: 3 | V58: 0 | W58: 0 | X58: 0 | Z58: 0 | AA58: 0 | AB58: 0 | AC58: 0 | AE58: 0
A59: 45893 | B59: 33 | C59: =22+206 -> 228 | D59: 0 | F59: 2 | G59: 12 | H59: 0 | J59: 48.6 | K59: =J59+L58-L59 -> 51 | L59: =3.1+6 -> 9.1 | N59: 0 | O59: 2 | P59: 3.3 | R59: 0 | S59: 7 | T59: 4 | V59: 0 | W59: 0 | X59: 0 | Z59: 0 | AA59: 0 | AB59: 0 | AC59: 0 | AE59: 0
A60: 45894 | B60: 15 | C60: =29+50 -> 79 | D60: 0 | F60: 2 | G60: 7 | H60: 5 | J60: 29.2 | K60: =J60+L59-L60 -> 26.7 | L60: 11.6 | N60: 0 | O60: 3 | P60: 5 | R60: 0 | S60: 9 | T60: 3 | V60: 0 | W60: 0 | X60: 0 | Z60: 0 | AA60: 0 | AB60: 0 | AC60: 0 | AE60: 0
A61: 45895 | B61: 16 | C61: =26+72 -> 98 | D61: 0 | F61: 0 | G61: 0 | H61: 0 | J61: 8 | K61: =J61+L60-L61 -> 11.6 | L61: 8 | N61: 0 | O61: 4.4 | P61: 3.2 | R61: 0 | S61: 12 | T61: 2 | V61: 0 | W61: 0 | X61: 0 | Z61: 0 | AA61: 0 | AB61: 0 | AC61: 0 | AE61: 0
A62: 45896 | B62: 0 | C62: 0 | D62: 0 | F62: 0 | G62: 0 | H62: 0 | J62: 0 | K62: =J62+L61-L62 -> 8 | L62: 0 | N62: 0 | O62: 0 | P62: 0 | R62: 0 | S62: 0 | T62: 0 | V62: 0 | W62: 0 | X62: 0 | Z62: 0 | AA62: 0 | AB62: 0 | AC62: 0 | AE62: 0
A63: 45897 | B63: 13 | C63: =13+69 -> 82 | D63: 0 | F63: 0 | G63: 0 | H63: 0 | J63: 18.8 | K63: =J63+L62-L63 -> 8.8 | L63: 10 | N63: 0 | O63: 3 | P63: 3 | R63: 0 | S63: 5 | T63: 2.3 | V63: 0 | W63: 0 | X63: 0 | Z63: 0 | AA63: 0 | AB63: 0 | AC63: 0 | AE63: 0
A64: 45898 | B64: 5 | C64: =10+21 -> 31 | D64: 3 | F64: 0 | G64: 0 | H64: 0 | J64: 0 | K64: =J64+L63-L64 -> 4.6 | L64: 5.4 | N64: 0 | O64: 2.3 | P64: 2.2 | R64: 0 | S64: 7 | T64: 0.9 | V64: 0 | W64: 0 | X64: 0 | Z64: 0 | AA64: 0 | AB64: 0 | AC64: 0 | AE64: 0
A65: 45899 | B65: 12 | C65: 32 | D65: 0 | F65: 0 | G65: 0 | H65: 0 | J65: 13.4 | K65: =J65+L64-L65 -> 11.8 | L65: 7 | N65: 0 | O65: 3.4 | P65: 1.4 | R65: 0 | S65: 14 | T65: 0 | V65: 0 | W65: 0 | X65: 0 | Z65: 0 | AA65: 0 | AB65: 0 | AC65: 0 | AE65: 0
A66: 45900 | B66: 12 | C66: 24 | D66: 0 | F66: 0 | G66: 0 | H66: 0 | J66: 17 | K66: =J66+L65-L66 -> 15 | L66: 9 | N66: 0 | O66: 3.3 | P66: 0 | R66: 2 | S66: 7 | T66: 0 | V66: 0 | W66: 0 | X66: 0 | Z66: 0 | AA66: 0 | AB66: 0 | AC66: 0 | AE66: 0
A67: Total | B67: =SUM(B36:B66) -> 251.3 | C67: =SUM(C36:C66) -> 1371 | D67: =SUM(D36:D66) -> 92 | F67: =SUM(F36:F66) -> 245 | G67: =SUM(G36:G66) -> 1737 | H67: =SUM(H36:H66) -> 93 | J67: =SUM(J36:J66) -> 630.3 | K67: =SUM(K36:K66) -> 621.3 | N67: =SUM(N36:N66) -> 20.7 | O67: =SUM(O36:O66) -> 99 | R67: =SUM(R36:R66) -> 32.6 | S67: =SUM(S36:S66) -> 334
A70: 45839 | B70: 6 | C70: 27 | D70: 9 | F70: 0 | G70: 0 | H70: 0 | J70: 6.3 | K70: =J70-L70 -> -3.1 | L70: 9.4 | N70: 0.7 | O70: 4 | P70: 1.5 | R70: 2 | S70: 11 | T70: 0.7 | V70: =(28*0)+0 -> 0 | W70: =(28*0)+0 -> 0 | X70: =(28*0)+0 -> 0 | Z70: =(24*0)+0 -> 0 | AA70: =(24*0)+0 -> 0 | AB70: =(24*0)+0 -> 0 | AC70: =(24*0)+0 -> 0 | AE70: =(12*0)+0 -> 0
A71: 45840 | B71: 5 | C71: 31 | D71: 0 | F71: 0 | G71: 0 | H71: 0 | J71: 6.2 | K71: =J71+L70-L71 -> 4.6 | L71: 11 | N71: 0 | O71: 5 | P71: 0.5 | R71: 3.1 | S71: 15 | T71: 2.5 | V71: 0 | W71: 0 | X71: 0 | Z71: 0 | AA71: 0 | AB71: 0 | AC71: 0 | AE71: 0
A72: 45841 | B72: 6 | C72: 24 | D72: 12 | F72: 0 | G72: 0 | H72: 0 | J72: 6.3 | K72: =J72+L71-L72 -> 4.9 | L72: 12.4 | N72: 2 | O72: 6.2 | P72: 0.3 | R72: 1 | S72: 7 | T72: 1.5 | V72: 0 | W72: 0 | X72: 0 | Z72: 0 | AA72: 0 | AB72: 0 | AC72: 0 | AE72: 0
A73: 45842 | B73: 18 | C73: =22+93+3 -> 118 | D73: 0 | F73: 0 | G73: 0 | H73: 0 | J73: 16.7 | K73: =J73+L72-L73 -> 21 | L73: 8.1 | N73: 0.9 | O73: 4 | P73: 0.5 | R73: 1 | S73: 12 | T73: 1.4 | V73: 0 | W73: 0 | X73: 0 | Z73: 0 | AA73: 0 | AB73: 0 | AC73: 0 | AE73: 0
A74: 45843 | B74: 22 | C74: =121+25 -> 146 | D74: 0 | F74: 0 | G74: 0 | H74: 0 | J74: 27.9 | K74: =J74+L73-L74 -> 26 | L74: 10 | N74: 0.6 | O74: 3.5 | P74: 0.5 | R74: 1.5 | S74: 16 | T74: 3 | V74: 0 | W74: 0 | X74: 0 | Z74: 0 | AA74: 0 | AB74: 0 | AC74: 0 | AE74: 0
A75: 45844 | B75: 17 | C75: =35+84 -> 119 | D75: 0 | F75: 0 | G75: 0 | H75: 0 | J75: 32.1 | K75: =J75+L74-L75 -> 25.1 | L75: 17 | N75: 2 | O75: 2 | P75: 1.8 | R75: 0 | S75: 15 | T75: 3 | V75: 0 | W75: 0 | X75: 0 | Z75: 0 | AA75: 0 | AB75: 0 | AC75: 0 | AE75: 0
A76: 45845 | B76: 12 | C76: =16+60 -> 76 | D76: 0 | F76: 0 | G76: 0 | H76: 0 | J76: 15.2 | K76: =J76+L75-L76 -> 13.6 | L76: 18.6 | N76: 0 | O76: 4 | P76: 2.8 | R76: 0 | S76: 6 | T76: 3 | V76: 0 | W76: 0 | X76: 0 | Z76: 0 | AA76: 0 | AB76: 0 | AC76: 0 | AE76: 0
A77: 45846 | B77: 21 | C77: =31+123 -> 154 | D77: 0 | F77: 0 | G77: 0 | H77: 0 | J77: 8.6 | K77: =J77+L76-L77 -> 24.2 | L77: 3 | N77: 0 | O77: 4 | P77: 0 | R77: 0 | S77: 18 | T77: 1.5 | V77: =(28*0)+0 -> 0 | W77: =(28*1)+45 -> 73 | X77: =(28*0)+40 -> 40 | Z77: =(24*0)+0 -> 0 | AA77: =(24*0)+6 -> 6 | AB77: =(24*0)+0 -> 0 | AC77: =(24*0)+16 -> 16 | AE77: =(12*54)+21 -> 669
A78: 45847 | B78: 14 | C78: =35+57 -> 92 | D78: 12 | F78: 0 | G78: 0 | H78: 0 | J78: 20.9 | K78: =J78+L77-L78 -> 18.4 | L78: 5.5 | N78: 0 | O78: 0 | P78: 1.2 | R78: 0 | S78: 0 | T78: 1.4 | V78: =(28*0)+0 -> 0 | W78: =(28*1)+40 -> 68 | X78: =(28*0)+37 -> 37 | Z78: =(24*0)+0 -> 0 | AA78: =(24*0)+0 -> 0 | AB78: =(24*0)+0 -> 0 | AC78: =(24*0)+16 -> 16 | AE78: =(12*52)+24 -> 648
A79: 45848 | B79: 12 | C79: =19+38 -> 57 | D79: 15 | F79: 0 | G79: 0 | H79: 0 | J79: 18.9 | K79: =J79+L78-L79 -> 14.1 | L79: 10.3 | N79: 0 | O79: 1.3 | P79: 1.5 | R79: 0 | S79: 5 | T79: 2.1 | V79: =(28*0)+0 -> 0 | W79: =(28*1)+40 -> 68 | X79: =(28*0)+37 -> 37 | Z79: =(24*0)+0 -> 0 | AA79: =(24*0)+0 -> 0 | AB79: =(24*0)+0 -> 0 | AC79: =(24*0)+16 -> 16 | AE79: =(12*49)+42 -> 630
A80: 45849 | B80: 4 | C80: 24 | D80: 0 | F80: 0 | G80: 0 | H80: 0 | J80: 0 | K80: =J80+L79-L80 -> 5.5 | L80: 4.8 | N80: 0 | O80: 3 | P80: 0 | R80: 0 | S80: 17 | T80: 0 | V80: =(28*0)+0 -> 0 | W80: =(28*1)+38 -> 66 | X80: =(28*0)+35 -> 35 | Z80: =(24*0)+0 -> 0 | AA80: =(24*0)+0 -> 0 | AB80: =(24*0)+0 -> 0 | AC80: =(24*0)+13 -> 13 | AE80: =(12*49)+32 -> 620
A81: 45850 | B81: 7 | C81: 34 | D81: 8 | F81: 0 | G81: 0 | H81: 0 | J81: 8.6 | K81: =J81+L80-L81 -> 7.9 | L81: 5.5 | N81: 0 | O81: 0.3 | P81: 0 | R81: 1.7 | S81: 17 | T81: 0 | V81: 0 | W81: 0 | X81: 0 | Z81: 0 | AA81: 0 | AB81: 0 | AC81: 0 | AE81: 0
A82: 45851 | B82: 9 | C82: 43 | D82: 9 | F82: 0 | G82: 0 | H82: 0 | J82: 11.8 | K82: =J82+L81-L82 -> 9.8 | L82: 7.5 | N82: 2 | O82: 9.2 | P82: 0.6 | R82: 3.3 | S82: 15 | T82: 0.8 | V82: =(28*5)+26 -> 166 | W82: =(28*6)+19 -> 187 | X82: =(28*4)+29 -> 141 | Z82: =(24*4)+11 -> 107 | AA82: =(24*2)+17 -> 65 | AB82: =(24*2)+0 -> 48 | AC82: =(24*2)+3 -> 51 | AE82: =(12*49)+32 -> 620
A83: 45852 | B83: 5.5 | C83: 23 | D83: 10 | F83: 0 | G83: 0 | H83: 0 | J83: 5.6 | K83: =J83+L82-L83 -> 2.1 | L83: 11 | N83: 0.5 | O83: 4.4 | P83: 0 | R83: 2 | S83: 8 | T83: 1.7 | V83: =(28*5)+25 -> 165 | W83: =(28*6)+18 -> 186 | X83: =(28*4)+27 -> 139 | Z83: =(24*4)+9 -> 105 | AA83: =(24*2)+17 -> 65 | AB83: =(24*2)+0 -> 48 | AC83: =(24*2)+3 -> 51 | AE83: =(12*48)+21 -> 597
A84: 45853 | B84: 4.5 | C84: 15 | D84: 7 | F84: 0 | G84: 0 | H84: 0 | J84: 2.8 | K84: =J84+L83-L84 -> 5.4 | L84: 8.4 | N84: 1.1 | O84: 2 | P84: 1.5 | R84: 0 | S84: 9 | T84: 0.5 | V84: =(28*5)+21 -> 161 | W84: =(28*6)+18 -> 186 | X84: =(28*4)+27 -> 139 | Z84: =(24*4)+5 -> 101 | AA84: =(24*2)+17 -> 65 | AB84: =(24*2)+0 -> 48 | AC84: =(24*2)+3 -> 51 | AE84: =(12*41)+29 -> 521
A85: 45854 | B85: 0 | C85: 0 | D85: 0 | F85: 0 | G85: 0 | H85: 0 | J85: 2.8 | K85: =J85+L84-L85 -> 2.8 | L85: 8.4 | N85: 0 | O85: 0 | P85: 0 | R85: 2 | S85: 0 | T85: 0.6 | V85: 0 | W85: 0 | X85: 0 | Z85: 0 | AA85: 0 | AB85: 0 | AC85: 0 | AE85: 0
A86: 45855 | B86: 4.5 | C86: 16 | D86: 11 | F86: 0 | G86: 0 | H86: 0 | J86: 3.8 | K86: =J86+L85-L86 -> 3.4 | L86: 8.8 | N86: 0.7 | O86: 3.3 | P86: 0 | R86: 2 | S86: 14 | T86: 0.3 | V86: 0 | W86: 0 | X86: 0 | Z86: 0 | AA86: 0 | AB86: 0 | AC86: 0 | AE86: 0
A87: 45856 | B87: 5.5 | C87: 29 | D87: 4 | F87: 0 | G87: 0 | H87: 0 | J87: 0 | K87: =J87+L86-L87 -> 1.9 | L87: 6.9 | N87: 0 | O87: 6.2 | P87: 0 | R87: 0 | S87: 17 | T87: 0.8 | V87: =(28*5)+14 -> 154 | W87: =(28*6)+15 -> 183 | X87: =(28*4)+26 -> 138 | Z87: =(24*3)+17 -> 89 | AA87: =(24*1)+33 -> 57 | AB87: =(24*1)+19 -> 43 | AC87: =(24*1)+25 -> 49 | AE87: =(12*39)+17 -> 485
A88: 45857 | B88: 5 | C88: 26 | D88: 4 | F88: 0 | G88: 0 | H88: 0 | J88: 5 | K88: =J88+L87-L88 -> 6.9 | L88: 5 | N88: 2 | O88: 6.1 | P88: 0 | R88: 2 | S88: 16 | T88: 0.8 | V88: =(28*5)+12 -> 152 | W88: =(28*6)+14 -> 182 | X88: =(28*4)+26 -> 138 | Z88: =(24*3)+13 -> 85 | AA88: =(24*1)+32 -> 56 | AB88: =(24*1)+17 -> 41 | AC88: =(24*1)+25 -> 49 | AE88: =(12*34)+22 -> 430
A89: 45858 | B89: 5 | C89: 30 | D89: 0 | F89: 0 | G89: 0 | H89: 0 | J89: 6.7 | K89: =J89+L88-L89 -> 4.3 | L89: 7.4 | N89: 4 | O89: 11.1 | P89: 0.7 | R89: 3 | S89: 17 | T89: 0.9 | V89: =(28*5)+5 -> 145 | W89: =(28*6)+13 -> 181 | X89: =(28*4)+26 -> 138 | Z89: =(24*3)+11 -> 83 | AA89: =(24*1)+32 -> 56 | AB89: =(24*1)+15 -> 39 | AC89: =(24*1)+22 -> 46 | AE89: =(12*33)+29 -> 425
A90: 45859 | B90: 4 | C90: 14 | D90: 10 | F90: 0 | G90: 0 | H90: 0 | J90: 4.7 | K90: =J90+L89-L90 -> 1.8 | L90: 10.3 | N90: 0 | O90: 2 | P90: 0 | R90: 2 | S90: 13 | T90: 1 | V90: =(28*5)+2 -> 142 | W90: =(28*6)+11 -> 179 | X90: =(28*4)+24 -> 136 | Z90: =(24*3)+5 -> 77 | AA90: =(24*1)+29 -> 53 | AB90: =(24*0)+37 -> 37 | AC90: =(24*1)+19 -> 43 | AE90: =(12*32)+31 -> 415
A91: 45860 | B91: 4 | C91: 17 | D91: 7 | F91: 0 | G91: 0 | H91: 0 | J91: 2.8 | K91: =J91+L90-L91 -> 2.8 | L91: 10.3 | N91: 1.3 | O91: 4.1 | P91: 0 | R91: 2 | S91: 7 | T91: 2.3 | V91: =(28*5)+2 -> 142 | W91: =(28*6)+11 -> 179 | X91: =(28*4)+24 -> 136 | Z91: =(24*3)+5 -> 77 | AA91: =(24*1)+29 -> 53 | AB91: =(24*0)+29 -> 29 | AC91: =(24*1)+19 -> 43 | AE91: =(12*31)+31 -> 403
A92: 45861 | B92: 5 | C92: 35 | D92: 0 | F92: 0 | G92: 0 | H92: 0 | J92: 3.1 | K92: =J92+L91-L92 -> 4.2 | L92: 9.2 | N92: 1 | O92: 4.4 | P92: 0.2 | R92: 1.5 | S92: 15 | T92: 0.8 | V92: =(28*4)+24 -> 136 | W92: =(28*5)+32 -> 172 | X92: =(28*4)+24 -> 136 | Z92: =(24*2)+24 -> 72 | AA92: =(24*1)+28 -> 52 | AB92: =(24*0)+29 -> 29 | AC92: =(24*1)+19 -> 43 | AE92: =(12*30)+23 -> 383
A93: 45862 | B93: 5 | C93: 21 | D93: 9 | F93: 0 | G93: 0 | H93: 0 | J93: 4.8 | K93: =J93+L92-L93 -> 4 | L93: 10 | N93: 1.5 | O93: 2 | P93: 0.7 | R93: 1.5 | S93: 8 | T93: 1.5 | V93: =(28*4)+21 -> 133 | W93: =(28*5)+32 -> 172 | X93: =(28*4)+24 -> 136 | Z93: =(24*2)+24 -> 72 | AA93: =(24*1)+27 -> 51 | AB93: =(24*0)+28 -> 28 | AC93: =(24*1)+19 -> 43 | AE93: =(12*28)+38 -> 374
A94: 45863 | B94: 25 | C94: =33+126 -> 159 | D94: 0 | F94: 0 | G94: 0 | H94: 0 | J94: 14.3 | K94: =J94+L93-L94 -> 24.3 | L94: 0 | N94: 0 | O94: 4.2 | P94: 1 | R94: 0 | S94: 9 | T94: 2 | V94: =(28*4)+15 -> 127 | W94: =(28*5)+25 -> 165 | X94: =(28*4)+19 -> 131 | Z94: =(24*2)+22 -> 70 | AA94: =(24*1)+24 -> 48 | AB94: =(24*0)+28 -> 28 | AC94: =(24*1)+19 -> 43 | AE94: =(12*27)+28 -> 352
A95: 45864 | B95: 23 | C95: =128+35 -> 163 | D95: 0 | F95: 0 | G95: 0 | H95: 0 | J95: 36.9 | K95: =J95+L94-L95 -> 31.7 | L95: 5.2 | N95: 0 | O95: 5.4 | P95: 1.9 | R95: 0 | S95: 5 | T95: 4.7 | V95: =(28*4)+14 -> 126 | W95: =(28*5)+22 -> 162 | X95: =(28*4)+19 -> 131 | Z95: =(24*2)+17 -> 65 | AA95: =(24*1)+20 -> 44 | AB95: =(24*0)+28 -> 28 | AC95: =(24*1)+19 -> 43 | AE95: =(12*25)+16 -> 316
A96: 45865 | B96: 28 | C96: =39+171 -> 210 | D96: 0 | F96: 0 | G96: 0 | H96: 0 | J96: 55.7 | K96: =J96+L95-L96 -> 36.4 | L96: 24.5 | N96: 0 | O96: 4.4 | P96: 3 | R96: 0 | S96: 18 | T96: 3 | V96: =(28*4)+7 -> 119 | W96: =(28*5)+22 -> 162 | X96: =(28*4)+18 -> 130 | Z96: =(24*2)+6 -> 54 | AA96: =(24*1)+11 -> 35 | AB96: =(24*0)+28 -> 28 | AC96: =(24*1)+19 -> 43 | AE96: =(12*22)+25 -> 289
A97: 45866 | B97: 13 | C97: =9+81 -> 90 | D97: 0 | F97: 0 | G97: 0 | H97: 0 | J97: 0 | K97: =J97+L96-L97 -> 15.1 | L97: 9.4 | N97: 0 | O97: 2.2 | P97: 2.5 | R97: 0 | S97: 7 | T97: 3.4 | V97: =(28*3)+35 -> 119 | W97: =(28*5)+22 -> 162 | X97: =(28*4)+18 -> 130 | Z97: =(24*1)+25 -> 49 | AA97: =(24*0)+31 -> 31 | AB97: =(24*0)+26 -> 26 | AC97: =(24*1)+19 -> 43 | AE97: =(12*21)+45 -> 297
A98: 45867 | B98: 17 | C98: =33+76 -> 109 | D98: 15 | F98: 0 | G98: 0 | H98: 0 | J98: 15.5 | K98: =J98+L97-L98 -> 18.4 | L98: 6.5 | N98: 0 | O98: 1.2 | P98: 3.3 | R98: 0 | S98: 8 | T98: 2.5 | V98: =(28*3)+35 -> 119 | W98: =(28*5)+21 -> 161 | X98: =(28*4)+18 -> 130 | Z98: =(24*1)+19 -> 43 | AA98: =(24*0)+29 -> 29 | AB98: =(24*0)+22 -> 22 | AC98: =(24*1)+15 -> 39 | AE98: =(12*21)+25 -> 277
A99: 45868 | B99: 24 | C99: =25+151 -> 176 | D99: 0 | F99: 0 | G99: 0 | H99: 0 | J99: 28.8 | K99: =J99+L98-L99 -> 29.6 | L99: 5.7 | N99: 0 | O99: 3 | P99: 3.5 | R99: 0 | S99: 12 | T99: 1.7 | V99: =(28*3)+28 -> 112 | W99: =(28*5)+21 -> 161 | X99: =(28*4)+18 -> 130 | Z99: =(24*1)+15 -> 39 | AA99: =(24*0)+22 -> 22 | AB99: =(24*0)+21 -> 21 | AC99: =(24*1)+15 -> 39 | AE99: =(12*19)+29 -> 257
A100: 45869 | B100: 19 | C100: =18+103 -> 121 | F100: 0 | G100: 0 | H100: 0 | J100: 26 | K100: =J100+L99-L100 -> 22.7 | L100: 9 | N100: 0 | O100: 4.3 | P100: 3.5 | R100: 0 | S100: 9 | T100: 0.5 | V100: =(28*3)+26 -> 110 | W100: =(28*5)+21 -> 161 | X100: =(28*4)+17 -> 129 | Z100: =(24*1)+8 -> 32 | AA100: =(24*0)+21 -> 21 | AB100: =(24*0)+20 -> 20 | AC100: =(24*1)+15 -> 39 | AE100: =(12*17)+36 -> 240
B101: =SUM(B70:B100) -> 350 | C101: =SUM(C70:C100) -> 2199 | D101: =SUM(D70:D100) -> 142 | F101: =SUM(F71:F100) -> 0 | G101: =SUM(G71:G100) -> 0 | H101: =SUM(H71:H100) -> 0 | J101: =SUM(J71:J100) -> 392.5 | K101: =SUM(K71:K100) -> 392.9 | N101: =SUM(N71:N100) -> 19.6 | O101: =SUM(O71:O100) -> 112.8 | R101: =SUM(R71:R100) -> 29.6 | S101: =SUM(S71:S100) -> 335
A104: 45809 | B104: 8 | C104: 42 | D104: 6 | F104: 0 | G104: 0 | H104: 0 | J104: =1.6+10.7 -> 12.3 | K104: =J104-L104 -> 9.3 | L104: 3 | N104: 1 | O104: 5 | P104: 1.2 | R104: 1.8 | S104: 12 | T104: 0.3 | V104: =(4*28)+25 -> 137 | W104: =(4*28)+34 -> 146 | X104: =(3*28)+33 -> 117 | Z104: =(3*24)+26 -> 98 | AA104: =(3*24)+25 -> 97 | AB104: =(0*24)+23 -> 23 | AC104: =(2*24)+19 -> 67 | AE104: =(2*12)+20 -> 44
A105: 45810 | B105: 6 | C105: 45 | D105: 0 | F105: 0 | G105: 0 | H105: 0 | J105: 4.6 | K105: =J105+L104-L105 -> 6.6 | L105: 1 | N105: 0 | O105: 0 | P105: 0 | R105: 2 | S105: 18 | T105: 0 | V105: =(4*28)+19 -> 131 | W105: =(4*28)+32 -> 144 | X105: =(3*28)+33 -> 117 | Z105: =(3*24)+17 -> 89 | AA105: =(3*24)+22 -> 94 | AB105: =(0*24)+21 -> 21 | AC105: =(2*24)+18 -> 66 | AE105: =(0*12)+11 -> 11
A106: 45811 | B106: 7 | C106: 41 | D106: 1 | F106: 0 | G106: 0 | H106: 0 | J106: 13.8 | K106: =J106+L105-L106 -> 10.2 | L106: 4.6 | N106: 0.8 | O106: 5 | P106: 0.3 | R106: 2 | S106: 17 | T106: 1 | V106: =(4*28)+9 -> 121 | W106: =(4*28)+28 -> 140 | X106: =(3*28)+31 -> 115 | Z106: =(3*24)+17 -> 89 | AA106: =(3*24)+22 -> 94 | AB106: =(0*24)+18 -> 18 | AC106: =(2*24)+18 -> 66 | AE106: =(5*12)+26 -> 86
...

Sheet Analytics
C2: January
C3: Week 1 | D3: Week 2 | E3: Week 3 | F3: Week 4 | G3: Week 5 | H3: Average
B4: Monday | D4: 0 | E4: 15935 | F4: 10005 | G4: 7835 | H4: =AVERAGEIF(C4:G4,"<>0") -> 11258.333
B5: Tuesday | D5: 6040 | E5: 5745 | F5: 0 | G5: 5490 | H5: =AVERAGEIF(C5:G5,"<>0") -> 5758.3333
B6: Wednesday | C6: 61365 | D6: 8355 | E6: 23905 | F6: 3955 | G6: 8230 | H6: =AVERAGEIF(C6:G6,"<>0") -> 21162
B7: Thursday | C7: 8220 | D7: 7730 | E7: 18595 | F7: 10095 | G7: 8435 | H7: =AVERAGEIF(C7:G7,"<>0") -> 10615
B8: Friday | C8: 8845 | D8: 10740 | E8: 14687 | F8: 9455 | H8: =AVERAGEIF(C8:G8,"<>0") -> 10931.75
B9: Saturday | C9: 11950 | D9: 7190 | E9: 14549 | F9: 8035 | H9: =AVERAGEIF(C9:G9,"<>0") -> 10431
B10: Sunday | C10: 19770 | D10: 24865 | E10: 13435 | F10: 16780 | H10: =AVERAGEIF(C10:G10,"<>0") -> 18712.5
B11: Average | C11: =AVERAGE(C4:C10) -> 22030 | D11: =AVERAGE(D5:D10) -> 10820 | E11: =AVERAGE(E4:E10) -> 15264.429 | F11: =AVERAGE(F4:F10) -> 8332.1429 | G11: =AVERAGE(G4:G10) -> 7497.5 | H11: =AVERAGEIF(C11:G11,"<>0") -> 12788.814
C13: Febraury
C14: Week 1 | D14: Week 2 | E14: Week 3 | F14: Week 4 | G14: Week 5 | H14: Average
B15: Monday | D15: 8155 | E15: 4785 | F15: 2815 | G15: 8340 | H15: =AVERAGE(C15:G15) -> 6023.75
B16: Tuesday | D16: 7270 | E16: 4800 | F16: 5565 | G16: 0 | H16: =AVERAGE(C16:G16) -> 4408.75
B17: Wednesday | D17: 5095 | E17: 0 | F17: 8775 | G17: 0 | H17: =AVERAGE(C17:G17) -> 3467.5
B18: Thursday | D18: 5750 | E18: 7850 | F18: 6485 | G18: 7075 | H18: =AVERAGE(C18:G18) -> 6790
B19: Friday | D19: 9505 | E19: 8595 | F19: 3890 | G19: 10275 | H19: =AVERAGE(C19:G19) -> 8066.25
B20: Saturday | C20: 9440 | D20: 9455 | E20: 7925 | F20: 7145 | H20: =AVERAGE(C20:G20) -> 8491.25
B21: Sunday | C21: 15705 | D21: 19395 | E21: 15155 | F21: 11125 | H21: =AVERAGE(C21:G21) -> 15345
B22: Average | C22: =AVERAGE(C15:C21) -> 12572.5 | D22: =AVERAGE(D16:D21) -> 9411.6667 | E22: =AVERAGE(E15:E21) -> 7015.7143 | F22: =AVERAGE(F15:F21) -> 6542.8571 | G22: =AVERAGE(G15:G21) -> 5138 | H22: =AVERAGE(H15:H21) -> 7513.2143
C24: March
C25: Week 1 | D25: Week 2 | E25: Week 3 | F25: Week 4 | G25: Week 5 | H25: Average
B26: Monday | C26: 16455 | D26: 6700 | E26: 4665 | F26: 0 | G26: 9100 | H26: =AVERAGE(C26:G26) -> 7384
B27: Tuesday | D27: 7520 | E27: 7245 | F27: 6850 | G27: 7830 | H27: =AVERAGE(C27:G27) -> 7361.25
B28: Wednesday | D28: 7445 | E28: 11270 | F28: 5445 | G28: 8385 | H28: =AVERAGE(C28:G28) -> 8136.25
B29: Thursday | D29: 0 | E29: 7780 | F29: 11460 | G29: 13380 | H29: =AVERAGE(C29:G29) -> 8155
B30: Friday | D30: 5725 | E30: 17470 | F30: 9305 | G30: 11105 | H30: =AVERAGE(C30:G30) -> 10901.25
B31: Saturday | C31: 8727 | D31: 9815 | E31: 12475 | F31: 13715 | G31: 12735 | H31: =AVERAGE(C31:G31) -> 11493.4
B32: Sunday | C32: 10190 | D32: 11325 | E32: 15785 | F32: 10055 | G32: 16455 | H32: =AVERAGE(C32:G32) -> 12762
B33: Average | C33: =AVERAGE(C26:C32) -> 11790.667 | D33: =AVERAGE(D27:D32) -> 6971.6667 | E33: =AVERAGE(E26:E32) -> 10955.714 | F33: =AVERAGE(F26:F32) -> 8118.5714 | G33: =AVERAGE(G26:G32) -> 11284.286 | H33: =AVERAGE(H26:H32) -> 9456.1643
C35: April
B36: Monday | C36: Week 1 | D36: Week 2 | E36: Week 3 | F36: Week 4 | G36: Week 5 | H36: Average
B37: Tuesday | D37: 11140 | E37: 6135 | F37: 0 | G37: 19400 | H37: =AVERAGE(C37:G37) -> 9168.75
B38: Wednesday | C38: 18920 | D38: 13857 | E38: 12050 | F38: 15580 | G38: 9118 | H38: =AVERAGE(C38:G38) -> 13905
B39: Thursday | C39: 15950 | D39: 9775 | E39: 11100 | F39: 9200 | G39: 7055 | H39: =AVERAGE(C39:G39) -> 10616
B40: Friday | C40: 15345 | D40: 8452 | E40: 6645 | F40: 7705 | H40: =AVERAGE(C40:G40) -> 9536.75
B41: Saturday | C41: 16087 | D41: 13210 | E41: 15540 | F41: 17280 | H41: =AVERAGE(C41:G41) -> 15529.25
B42: Sunday | C42: 10485 | D42: 12055 | E42: 16905 | F42: 14560 | H42: =AVERAGE(C42:G42) -> 13501.25
B43: Average | C43: 0 | D43: 16660 | E43: 8783 | F43: 14920 | H43: =AVERAGE(C43:G43) -> 10090.75
C44: =AVERAGE(C37:C43) -> 12797.833 | D44: =AVERAGE(D37:D43) -> 12164.143 | E44: =AVERAGE(E37:E43) -> 11022.571 | F44: =AVERAGE(F37:F43) -> 11320.714 | G44: =AVERAGE(G37:G43) -> 11857.667 | H44: =AVERAGE(H37:H43) -> 11763.964
C46: May
C47: Week 1 | D47: Week 2 | E47: Week 3 | F47: Week 4 | G47: Week 5 | H47: Average
B48: Monday | D48: 8990 | E48: 12325 | F48: 0 | G48: 10985 | H48: =AVERAGE(C48:G48) -> 8075
B49: Tuesday | D49: 15050 | E49: 9670 | F49: 15725 | G49: 12170 | H49: =AVERAGE(C49:G49) -> 13153.75
B50: Wednesday | D50: 18205 | E50: 17220 | F50: 5715 | G50: 12115 | H50: =AVERAGE(C50:G50) -> 13313.75
B51: Thursday | C51: 15360 | D51: 16730 | E51: 6245 | F51: 10575 | G51: 9245 | H51: =AVERAGE(C51:G51) -> 11631
B52: Friday | C52: 8306 | D52: 18965 | E52: 16490 | F52: 16060 | G52: 16241 | H52: =AVERAGE(C52:G52) -> 15212.4
B53: Saturday | C53: 9295 | D53: 11876 | E53: 13615 | F53: 12481 | G53: 15790 | H53: =AVERAGE(C53:G53) -> 12611.4
B54: Sunday | C54: 13465 | D54: 14060 | E54: 14345 | F54: 13960 | H54: =AVERAGE(C54:G54) -> 13957.5
B55: Average | C55: =AVERAGE(C48:C54) -> 11606.5 | D55: =AVERAGE(D48:D54) -> 14839.429 | E55: =AVERAGE(E48:E54) -> 12844.286 | F55: =AVERAGE(F48:F54) -> 10645.143 | G55: =AVERAGE(G48:G54) -> 12757.667 | H55: =AVERAGE(H48:H54) -> 12564.971
C57: June
C58: Week 1 | D58: Week 2 | E58: Week 3 | F58: Week 4 | G58: Week 5 | H58: Average
B59: Monday | C59: 0 | D59: 15090 | E59: 0 | F59: 9940 | G59: 6680 | H59: =AVERAGE(C59:G59) -> 6342
B60: Tuesday | D60: 11711 | E60: 10875 | F60: 6085 | G60: 11824 | H60: =AVERAGE(C60:G60) -> 10123.75
B61: Wednesday | D61: 11100 | E61: 11695 | F61: 16245 | G61: 5530 | H61: =AVERAGE(C61:G61) -> 11142.5
B62: Thursday | D62: 6830 | E62: 8790 | F62: 11190 | G62: 9780 | H62: =AVERAGE(C62:G62) -> 9147.5
B63: Friday | D63: 17690 | E63: 9350 | F63: 9980 | G63: 9625 | H63: =AVERAGE(C63:G63) -> 11661.25
B64: Saturday | D64: 8915 | E64: 9410 | F64: 8510 | G64: 9530 | H64: =AVERAGE(C64:G64) -> 9091.25
B65: Sunday | C65: 13080 | D65: 11675 | E65: 9495 | F65: 13720 | G65: 12025 | H65: =AVERAGE(C65:G65) -> 11999
B66: Average | C66: =AVERAGE(C59:C65) -> 6540 | D66: =AVERAGE(D59:D65) -> 11858.714 | E66: =AVERAGE(E59:E65) -> 8516.4286 | F66: =AVERAGE(F59:F65) -> 10810 | G66: =AVERAGE(G59:G65) -> 9284.8571 | H66: =AVERAGE(H59:H65) -> 9929.6071
C68: July
C69: Week 1 | D69: Week 2 | E69: Week 3 | F69: Week 4 | G69: Week 5 | H69: Average
B70: Monday | D70: 6500 | E70: 6425 | F70: 7200 | G70: 3455 | H70: =AVERAGE(C70:G70) -> 5895
B71: Tuesday | C71: 9295 | D71: 10445 | E71: 5345 | F71: 4055 | G71: 8015 | H71: =AVERAGE(C71:G71) -> 7431
B72: Wednesday | C72: 7280 | D72: 10580 | E72: 7770 | F72: 11010 | G72: 8750 | H72: =AVERAGE(C72:G72) -> 9078
B73: Thursday | C73: 9175 | D73: 6256 | E73: 6480 | F73: 5035 | G73: 6915 | H73: =AVERAGE(C73:G73) -> 6772.2
B74: Friday | C74: 8470 | D74: 9535 | E74: 10515 | F74: 11605 | H74: =AVERAGE(C74:G74) -> 10031.25
B75: Saturday | C75: 11050 | D75: 16305 | E75: 9080 | F75: 11070 | H75: =AVERAGE(C75:G75) -> 11876.25
B76: Sunday | C76: 12095 | D76: 13085 | E76: 9810 | F76: 14635 | H76: =AVERAGE(C76:G76) -> 12406.25
B77: Average | C77: =AVERAGE(C70:C76) -> 9560.8333 | D77: =AVERAGE(D70:D76) -> 10386.571 | E77: =AVERAGE(E70:E76) -> 7917.8571 | F77: =AVERAGE(F70:F76) -> 9230 | G77: =AVERAGE(G70:G76) -> 6783.75 | H77: =AVERAGE(H70:H76) -> 9069.9929
C79: August
C80: Week 1 | D80: Week 2 | E80: Week 3 | F80: Week 4 | G80: Week 5 | H80: Average
B81: Monday | D81: 4345 | E81: 10015 | F81: 6390 | G81: 10510 | H81: =AVERAGE(C81:G81) -> 7815
B82: Tuesday | D82: 8260 | E82: 6820 | F82: 5525 | G82: 9250 | H82: =AVERAGE(C82:G82) -> 7463.75
B83: Wednesday | D83: 7275 | E83: 8605 | F83: 5750 | G83: 0 | H83: =AVERAGE(C83:G83) -> 5407.5
B84: Thursday | D84: 11205 | E84: 5030 | F84: 4620 | G84: 3540 | H84: =AVERAGE(C84:G84) -> 6098.75
B85: Friday | C85: 8059 | D85: 8030 | E85: 22745 | F85: 3400 | G85: 3225 | H85: =AVERAGE(C85:G85) -> 9091.8
B86: Saturday | C86: 12150 | D86: 13230 | E86: 0 | F86: 10845 | G86: 10720 | H86: =AVERAGE(C86:G86) -> 9389
B87: Sunday | C87: 23360 | D87: 24005 | E87: 10945 | F87: 9335 | G87: 8240 | H87: =AVERAGE(C87:G87) -> 15177
B88: Average | C88: =AVERAGE(C84:C87) -> 14523 | D88: =AVERAGE(D81:D87) -> 10907.143 | E88: =AVERAGE(E81:E87) -> 9165.7143 | F88: =AVERAGE(F81:F87) -> 6552.1429 | G88: =AVERAGE(G81:G87) -> 6497.8571 | H88: =AVERAGE(H81:H87) -> 8634.6857
C90: September
C91: Week 1 | D91: Week 2 | E91: Week 3 | F91: Week 4 | G91: Week 5 | H91: Average
B92: Monday | C92: 4470 | D92: 8735 | E92: 4590 | F92: 0 | G92: 9020 | H92: =AVERAGE(C92:G92) -> 5363
B93: Tuesday | C93: 5875 | D93: 4120 | E93: 10920 | F93: 13040 | G93: 16630 | H93: =AVERAGE(C93:G93) -> 10117
B94: Wednesday | C94: 5110 | D94: 7955 | E94: 5975 | F94: 10780 | H94: =AVERAGE(C94:G94) -> 7455
B95: Thursday | C95: 4475 | D95: 5975 | E95: 4875 | F95: 1980 | H95: =AVERAGE(C95:G95) -> 4326.25
B96: Friday | C96: 11210 | D96: 4410 | E96: 4280 | F96: 9710 | H96: =AVERAGE(C96:G96) -> 7402.5
B97: Saturday | C97: 10745 | D97: 6440 | E97: 5585 | F97: 8860 | H97: =AVERAGE(C97:G97) -> 7907.5
B98: Sunday | C98: 14460 | D98: 9705 | E98: 8200 | F98: 9510 | H98: =AVERAGE(C98:G98) -> 10468.75
B99: Average | C99: =AVERAGE(C92:C98) -> 8049.2857 | D99: =AVERAGE(D92:D98) -> 6762.8571 | E99: =AVERAGE(E92:E98) -> 6346.4286 | F99: =AVERAGE(F92:F98) -> 7697.1429 | G99: =AVERAGE(G92:G98) -> 12825 | H99: =AVERAGE(H92:H98) -> 7577.1429
C101: October
C102: Week 1 | D102: Week 2 | E102: Week 3 | F102: Week 4 | G102: Week 5 | H102: Average
B103: Monday | D103: 0 | E103: 5545 | F103: 4870 | G103: 4075 | H103: =AVERAGE(C103:G103) -> 3622.5
B104: Tuesday | D104: 10345 | E104: 4460 | F104: 6970 | G104: 4560 | H104: =AVERAGE(C104:G104) -> 6583.75
B105: Wednesday | C105: 15795 | D105: 8270 | E105: 7355 | F105: 5290 | G105: 5630 | H105: =AVERAGE(C105:G105) -> 8468
B106: Thursday | C106: 66280 | D106: 6615 | E106: 4605 | F106: 6125 | G106: 5405 | H106: =AVERAGE(C106:G106) -> 17806
B107: Friday | C107: 48305 | D107: 8620 | E107: 5340 | F107: 4410 | G107: 0 | H107: =AVERAGE(C107:G107) -> 13335
B108: Saturday | C108: 16760 | D108: 8895 | E108: 8565 | F108: 6040 | H108: =AVERAGE(C108:G108) -> 10065
B109: Sunday | C109: 19550 | D109: 11030 | E109: 11770 | F109: 15370 | H109: =AVERAGE(C109:G109) -> 14430
B110: Average | C110: =AVERAGE(C103:C109) -> 33338 | D110: =AVERAGE(D103:D109) -> 7682.1429 | E110: =AVERAGE(E103:E109) -> 6805.7143 | F110: =AVERAGE(F103:F109) -> 7010.7143 | G110: =AVERAGE(G103:G109) -> 3934 | H110: =AVERAGE(H103:H109) -> 10615.75
...

Sheet January
B1: 45658 | C1: 45659 | D1: 45660 | E1: 45661 | F1: 45662 | G1: 45663 | H1: 45664 | I1: 45665 | J1: 45666 | K1: 45667 | L1: 45668 | M1: 45669 | N1: 45670 | O1: 45671 | P1: 45672 | Q1: 45673 | R1: 45674 | S1: 45675 | T1: 45676 | U1: 45677 | V1: 45678 | W1: 45679 | X1: 45680 | Y1: 45681 | Z1: 45682 | AA1: 45683 | AB1: 45684 | AC1: 45685 | AD1: 45686 | AE1: 45687 | AF1: 45688 | AG1: Total | AH1: Average | AI1: % Share
A2: Chef | B2: =3900+1700 -> 5600 | C2: 3900 | D2: 3900 | E2: 3900 | F2: 3200 | G2: 0 | H2: 3200 | I2: 3200 | J2: 3200 | K2: 3200 | L2: 3200 | M2: 3200 | N2: 3200 | O2: 3200 | P2: 3200 | Q2: 3200 | R2: 3200 | S2: 3200 | T2: 3200 | U2: 3200 | V2: 0 | W2: 3200 | X2: 3200 | Y2: 3200 | Z2: 3200 | AA2: 3200 | AB2: 3200 | AC2: 3200 | AD2: 3200 | AE2: 3200 | AF2: 3200 | AG2: =SUM(B2:AF2) -> 97300 | AH2: =IFERROR(AVERAGE(B2:AF2),0) -> 3138.7097 | AI2: =(AH2/$AH$29)*100 -> 21.81228
A3: Salaries, Rent and others | B3: =$B$39/$B$59 -> 3068 | C3: =$B$39/$B$59 -> 3068 | D3: =$B$39/$B$59 -> 3068 | E3: =$B$39/$B$59 -> 3068 | F3: =$B$39/$B$59 -> 3068 | G3: 0 | H3: =$B$39/$B$59 -> 3068 | I3: =$B$39/$B$59 -> 3068 | J3: =$B$39/$B$59 -> 3068 | K3: =$B$39/$B$59 -> 3068 | L3: =$B$39/$B$59 -> 3068 | M3: =$B$39/$B$59 -> 3068 | N3: =$B$39/$B$59 -> 3068 | O3: =$B$39/$B$59 -> 3068 | ... U3: =$B$39/$B$59 -> 3068 | V3: 0 | W3: =$B$39/$B$59 -> 3068 | X3: =$B$39/$B$59 -> 3068 | Y3: =$B$39/$B$59 -> 3068 | Z3: =$B$39/$B$59 -> 3068 | AA3: =$B$39/$B$59 -> 3068 | AB3: =$B$39/$B$59 -> 3068 | AC3: =$B$39/$B$59 -> 3068 | AD3: =$B$39/$B$59 -> 3068 | ... AF3: =$B$39/$B$59 -> 3068 | AG3: =SUM(B3:AF3) -> 88972 | AH3: =IFERROR(AVERAGE(B3:AF3),0) -> 2870.0645 | AI3: =(AH3/$AH$29)*100 -> 19.945346
A4: Stock | B4: =$B$42/$B$59 -> 3285.1034 | C4: =$B$42/$B$59 -> 3285.1034 | D4: =$B$42/$B$59 -> 3285.1034 | E4: =$B$42/$B$59 -> 3285.1034 | F4: =$B$42/$B$59 -> 3285.1034 | G4: 0 | H4: =$B$42/$B$59 -> 3285.1034 | I4: =$B$42/$B$59 -> 3285.1034 | J4: =$B$42/$B$59 -> 3285.1034 | K4: =$B$42/$B$59 -> 3285.1034 | L4: =$B$42/$B$59 -> 3285.1034 | M4: =$B$42/$B$59 -> 3285.1034 | N4: =$B$42/$B$59 -> 3285.1034 | O4: =$B$42/$B$59 -> 3285.1034 | ... U4: =$B$42/$B$59 -> 3285.1034 | V4: 0 | W4: =$B$42/$B$59 -> 3285.1034 | X4: =$B$42/$B$59 -> 3285.1034 | Y4: =$B$42/$B$59 -> 3285.1034 | Z4: =$B$42/$B$59 -> 3285.1034 | AA4: =$B$42/$B$59 -> 3285.1034 | AB4: =$B$42/$B$59 -> 3285.1034 | AC4: =$B$42/$B$59 -> 3285.1034 | AD4: =$B$42/$B$59 -> 3285.1034 | ... AF4: =$B$42/$B$59 -> 3285.1034 | AG4: =SUM(B4:AF4) -> 95268 | AH4: =IFERROR(AVERAGE(B4:AF4),0) -> 3073.1613 | AI4: =(AH4/$AH$29)*100 -> 21.356755
A5: Meat
A6: Chicken | B6: 7000 | C6: 3000 | D6: 0 | E6: 3000 | F6: 3000 | G6: 0 | H6: 1900 | I6: 2500 | J6: 2000 | K6: 2000 | L6: 1500 | M6: 3000 | N6: 2000 | O6: 2000 | P6: 1500 | Q6: 3620 | R6: 2500 | S6: 1800 | T6: 2000 | U6: 2000 | V6: 0 | W6: 2000 | X6: 2000 | Y6: 2000 | Z6: 2000 | AA6: 1520 | AB6: 2000 | AC6: 2000 | AD6: 1500 | AE6: 1500 | AF6: 1200 | AG6: =SUM(B6:AF6) -> 64040 | AH6: =IFERROR(AVERAGE(B6:AF6),0) -> 2065.8065 | AI6: =(AH6/$AH$29)*100 -> 14.356201
A7: Mutton | B7: =$B$51/$B$59 -> 168.96552 | C7: =$B$51/$B$59 -> 168.96552 | D7: =$B$51/$B$59 -> 168.96552 | E7: =$B$51/$B$59 -> 168.96552 | F7: =$B$51/$B$59 -> 168.96552 | G7: 0 | H7: =$B$51/$B$59 -> 168.96552 | I7: =$B$51/$B$59 -> 168.96552 | J7: =$B$51/$B$59 -> 168.96552 | K7: =$B$51/$B$59 -> 168.96552 | L7: =$B$51/$B$59 -> 168.96552 | M7: =$B$51/$B$59 -> 168.96552 | N7: =$B$51/$B$59 -> 168.96552 | O7: =$B$51/$B$59 -> 168.96552 | ... U7: =$B$51/$B$59 -> 168.96552 | V7: 0 | W7: =$B$51/$B$59 -> 168.96552 | X7: =$B$51/$B$59 -> 168.96552 | Y7: =$B$51/$B$59 -> 168.96552 | Z7: =$B$51/$B$59 -> 168.96552 | AA7: =$B$51/$B$59 -> 168.96552 | AB7: =$B$51/$B$59 -> 168.96552 | AC7: =$B$51/$B$59 -> 168.96552 | AD7: =$B$51/$B$59 -> 168.96552 | ... AF7: =$B$51/$B$59 -> 168.96552 | AG7: =SUM(B7:AF7) -> 4900 | AH7: =IFERROR(AVERAGE(B7:AF7),0) -> 158.06452 | AI7: =(AH7/$AH$29)*100 -> 1.0984601
A8: Sea food | B8: =$B$52/$B$59 -> 213.7931 | C8: =$B$52/$B$59 -> 213.7931 | D8: =$B$52/$B$59 -> 213.7931 | E8: =$B$52/$B$59 -> 213.7931 | F8: =$B$52/$B$59 -> 213.7931 | G8: 0 | H8: =$B$52/$B$59 -> 213.7931 | I8: =$B$52/$B$59 -> 213.7931 | J8: =$B$52/$B$59 -> 213.7931 | K8: =$B$52/$B$59 -> 213.7931 | L8: =$B$52/$B$59 -> 213.7931 | M8: =$B$52/$B$59 -> 213.7931 | N8: =$B$52/$B$59 -> 213.7931 | O8: =$B$52/$B$59 -> 213.7931 | ... U8: =$B$52/$B$59 -> 213.7931 | V8: 0 | W8: =$B$52/$B$59 -> 213.7931 | X8: =$B$52/$B$59 -> 213.7931 | Y8: =$B$52/$B$59 -> 213.7931 | Z8: =$B$52/$B$59 -> 213.7931 | AA8: =$B$52/$B$59 -> 213.7931 | AB8: =$B$52/$B$59 -> 213.7931 | AC8: =$B$52/$B$59 -> 213.7931 | AD8: =$B$52/$B$59 -> 213.7931 | ... AF8: =$B$52/$B$59 -> 213.7931 | AG8: =SUM(B8:AF8) -> 6200 | AH8: =IFERROR(AVERAGE(B8:AF8),0) -> 200 | AI8: =(AH8/$AH$29)*100 -> 1.3898883
A9: Market
A10: All Vegetables | B10: =40+10+40+30+40+220+80+50+50 -> 560 | C10: =90+30+50+550+40+40+60+50+20+50+30 -> 1010 | D10: =40+20+30+40+150+30+50+50 -> 410 | E10: =20+10+150+20+30+50 -> 280 | F10: =40+20+40+50+40+30+40+180+50+30 -> 520 | G10: 0 | H10: =40+10+20+40+40+40+500+60+125 -> 875 | I10: =40+20+20+150+60+20+40+50 -> 400 | J10: =20+20+30+110+40+40+50+50 -> 360 | K10: =40+150+20+40+50+20+50+50+30 -> 450 | L10: =50+10+40+30+50+40+220+20 -> 460 | M10: =40+40+50+50+50+40+50+40+10+50+40+100 -> 560 | N10: =20+20+270+40+20+110+40+20+120+60+40 -> 760 | O10: =130+40+50+25+25+50+40+50 -> 410 | P10: =60+30+40+50+60+50+230+40+10 -> 570 | Q10: =200+30+40+20+50+40+20+60 -> 460 | R10: =2280+50+70+20+100+40+40+50+20+40+40+40 -> 2790 | S10: =120+30+30+20+50+20+10+30 -> 310 | T10: =220+30+60+40+30+50+30+40+20+50+40 -> 610 | U10: =30+20+270+40+30+40+40+50 -> 520 | V10: 0 | W10: =200+30+20+40+50+20+40+80+40+40 -> 560 | X10: =30+20+50+130+40+40+50+40 -> 400 | Y10: =10+10+130+30+20+30+50+50+30 -> 360 | Z10: =40+10+30+20+30+40+45+20+130+10 -> 375 | AA10: =40+20+20+40+20+30+160+30+50+40 -> 450 | AB10: =10+10+440+50+50+30+30+40+50 -> 710 | AC10: =30+20+50+40+20+100+50+120 -> 430 | AD10: =10+10+50+40+30+120+40 -> 300 | AE10: =20+350+40+20+30+30+20+50+50 -> 610 | AF10: =30+10+200+50+30+40+30+40+40 -> 470 | AG10: =SUM(B10:AD10) -> 15900 | AH10: =IFERROR(AVERAGE(B10:AD10),0) -> 548.27586 | AI10: =(AH10/$AH$29)*100 -> 3.8102111
A11: Curd | B11: 350 | C11: 200 | D11: 150 | E11: 100 | F11: 150 | G11: 0 | H11: 150 | I11: 150 | J11: 150 | K11: 150 | L11: 150 | M11: 100 | N11: 200 | O11: 150 | P11: 250 | Q11: 200 | R11: 200 | S11: 150 | T11: 150 | U11: 150 | V11: 0 | W11: 150 | X11: 100 | Y11: 150 | Z11: 150 | AA11: 200 | AB11: 150 | AC11: 100 | AD11: 150 | AE11: 150 | AF11: 100 | AG11: =SUM(B11:AD11) -> 4400 | AH11: =IFERROR(AVERAGE(B11:AD11),0) -> 151.72414 | AI11: =(AH11/$AH$29)*100 -> 1.054398
A12: Milk | B12: 130 | C12: 130 | D12: 130 | E12: 65 | F12: 130 | G12: 0 | H12: 130 | I12: 65 | J12: 65 | K12: 130 | L12: 130 | M12: 65 | N12: 130 | O12: 130 | P12: 130 | Q12: 65 | R12: 130 | S12: 130 | T12: 130 | U12: 165 | V12: 0 | W12: 130 | X12: 65 | Y12: 130 | Z12: 130 | AA12: 100 | AB12: 130 | AC12: 100 | AD12: 100 | AE12: 130 | AF12: 100 | AG12: =SUM(B12:AD12) -> 3065 | AH12: =IFERROR(AVERAGE(B12:AD12),0) -> 105.68966 | AI12: =(AH12/$AH$29)*100 -> 0.7344841
A13: Paneer | B13: 0 | C13: 350 | D13: 0 | E13: 0 | F13: 350 | G13: 0 | H13: 350 | I13: 0 | J13: 0 | K13: 370 | L13: 0 | M13: 370 | N13: 370 | O13: 370 | P13: 370 | Q13: 370 | R13: 370 | S13: 370 | T13: 0 | U13: 0 | V13: 0 | W13: 370 | X13: 0 | Y13: 0 | Z13: 370 | AA13: 370 | AB13: 0 | AC13: 0 | AD13: 0 | AE13: 0 | AF13: 370 | AG13: =SUM(B13:AD13) -> 5120 | AH13: =IFERROR(AVERAGE(B13:AD13),0) -> 176.55172 | AI13: =(AH13/$AH$29)*100 -> 1.2269359
A14: Mushroom | B14: 0 | C14: 0 | D14: 0 | E14: 0 | F14: 160 | G14: 0 | H14: 80 | I14: 0 | J14: 0 | K14: 80 | L14: 170 | M14: 0 | N14: 200 | O14: 200 | P14: 120 | Q14: 0 | R14: 80 | S14: 190 | T14: 199 | U14: 40 | V14: 0 | W14: 160 | X14: 0 | Y14: 0 | Z14: 0 | AA14: 135 | AB14: 80 | AC14: 0 | AD14: 0 | AE14: 0 | AF14: 0 | AG14: =SUM(B14:AD14) -> 1894 | AH14: =IFERROR(AVERAGE(B14:AD14),0) -> 65.310345 | AI14: =(AH14/$AH$29)*100 -> 0.45387043
A15: Babycorn | B15: 0 | C15: 175 | D15: 0 | E15: 0 | F15: 0 | G15: 0 | H15: 0 | I15: 0 | J15: 0 | K15: 0 | L15: 70 | M15: 0 | N15: 0 | O15: 70 | P15: 0 | Q15: 0 | R15: 70 | S15: 105 | T15: 0 | U15: 0 | V15: 0 | W15: 105 | X15: 0 | Y15: 0 | Z15: 0 | AA15: 35 | AB15: 0 | AC15: 0 | AD15: 70 | AE15: 0 | AF15: 35 | AG15: =SUM(B15:AD15) -> 700 | AH15: =IFERROR(AVERAGE(B15:AD15),0) -> 24.137931 | AI15: =(AH15/$AH$29)*100 -> 0.16774514
A16: Eggs | B16: 400 | C16: 200 | D16: 0 | E16: 0 | F16: 200 | G16: 0 | H16: 200 | I16: 200 | J16: 0 | K16: 200 | L16: 200 | M16: 200 | N16: 0 | O16: 180 | P16: 180 | Q16: 180 | R16: 0 | S16: 0 | T16: 180 | U16: 180 | V16: 0 | W16: 0 | X16: 180 | Y16: 180 | Z16: 0 | AA16: 180 | AB16: 170 | AC16: 0 | AD16: 170 | AE16: 0 | AF16: 170 | AG16: =SUM(B16:AD16) -> 3580 | AH16: =IFERROR(AVERAGE(B16:AD16),0) -> 123.44828 | AI16: =(AH16/$AH$29)*100 -> 0.85789659
A17: Dry Grocery | B17: =45+80 -> 125 | C17: =200+98 -> 298 | D17: 0 | E17: 0 | F17: =1000+150 -> 1150 | G17: 0 | H17: 0 | I17: =100+65 -> 165 | J17: 89 | K17: 200 | L17: 0 | M17: =500+89 -> 589 | N17: 0 | O17: 89 | P17: =200+35 -> 235 | Q17: =100+75+700 -> 875 | R17: 294 | S17: 200 | T17: 0 | U17: =89+340 -> 429 | V17: 0 | W17: =130+130 -> 260 | X17: 0 | Y17: 200 | Z17: 78 | AA17: 0 | AB17: 0 | AC17: =89+75 -> 164 | AD17: 200 | AE17: 100 | AF17: 35 | AG17: =SUM(B17:AD17) -> 5640 | AH17: =IFERROR(AVERAGE(B17:AD17),0) -> 194.48276 | AI17: =(AH17/$AH$29)*100 -> 1.3515466
A18: Garlic | B18: 0 | C18: 190 | D18: 0 | E18: 0 | F18: 360 | G18: 0 | H18: 0 | I18: 0 | J18: 180 | K18: 180 | L18: 0 | M18: 0 | N18: =190+600 -> 790 | O18: 180 | P18: 0 | Q18: 190 | R18: 0 | S18: 240 | T18: 0 | U18: 160 | V18: 0 | W18: 0 | X18: 160 | Y18: 160 | Z18: 0 | AA18: 150 | AB18: 0 | AC18: =150+440 -> 590 | AD18: 0 | AE18: 200 | AF18: 0 | AG18: =SUM(B18:AD18) -> 3530 | AH18: =IFERROR(AVERAGE(B18:AD18),0) -> 121.72414 | AI18: =(AH18/$AH$29)*100 -> 0.8459148
A19: Running
A20: Gas | B20: =$B$53/$B$59 -> 965.51724 | C20: =$B$53/$B$59 -> 965.51724 | D20: =$B$53/$B$59 -> 965.51724 | E20: =$B$53/$B$59 -> 965.51724 | F20: =$B$53/$B$59 -> 965.51724 | G20: 0 | H20: =$B$53/$B$59 -> 965.51724 | I20: =$B$53/$B$59 -> 965.51724 | J20: =$B$53/$B$59 -> 965.51724 | K20: =$B$53/$B$59 -> 965.51724 | L20: =$B$53/$B$59 -> 965.51724 | M20: =$B$53/$B$59 -> 965.51724 | N20: =$B$53/$B$59 -> 965.51724 | O20: =$B$53/$B$59 -> 965.51724 | ... U20: =$B$53/$B$59 -> 965.51724 | V20: 0 | W20: =$B$53/$B$59 -> 965.51724 | X20: =$B$53/$B$59 -> 965.51724 | Y20: =$B$53/$B$59 -> 965.51724 | Z20: =$B$53/$B$59 -> 965.51724 | AA20: =$B$53/$B$59 -> 965.51724 | AB20: =$B$53/$B$59 -> 965.51724 | AC20: =$B$53/$B$59 -> 965.51724 | AD20: =$B$53/$B$59 -> 965.51724 | ... AF20: =$B$53/$B$59 -> 965.51724 | AG20: =SUM(B20:AF20) -> 28000 | AH20: =IFERROR(AVERAGE(B20:AF20),0) -> 903.22581 | AI20: =(AH20/$AH$29)*100 -> 6.2769151
A21: Coal | B21: =$B$54/$B$59 -> 172.41379 | C21: =$B$54/$B$59 -> 172.41379 | D21: =$B$54/$B$59 -> 172.41379 | E21: =$B$54/$B$59 -> 172.41379 | F21: =$B$54/$B$59 -> 172.41379 | G21: 0 | H21: =$B$54/$B$59 -> 172.41379 | I21: =$B$54/$B$59 -> 172.41379 | J21: =$B$54/$B$59 -> 172.41379 | K21: =$B$54/$B$59 -> 172.41379 | L21: =$B$54/$B$59 -> 172.41379 | M21: =$B$54/$B$59 -> 172.41379 | N21: =$B$54/$B$59 -> 172.41379 | O21: =$B$54/$B$59 -> 172.41379 | ... U21: =$B$54/$B$59 -> 172.41379 | V21: 0 | W21: =$B$54/$B$59 -> 172.41379 | X21: =$B$54/$B$59 -> 172.41379 | Y21: =$B$54/$B$59 -> 172.41379 | Z21: =$B$54/$B$59 -> 172.41379 | AA21: =$B$54/$B$59 -> 172.41379 | AB21: =$B$54/$B$59 -> 172.41379 | AC21: =$B$54/$B$59 -> 172.41379 | AD21: =$B$54/$B$59 -> 172.41379 | ... AF21: =$B$54/$B$59 -> 172.41379 | AG21: =SUM(B21:AF21) -> 5000 | AH21: =IFERROR(AVERAGE(B21:AF21),0) -> 161.29032 | AI21: =(AH21/$AH$29)*100 -> 1.1208777
A22: Water | B22: =$B$55/$B$59 -> 137.93103 | C22: =$B$55/$B$59 -> 137.93103 | D22: =$B$55/$B$59 -> 137.93103 | E22: =$B$55/$B$59 -> 137.93103 | F22: =$B$55/$B$59 -> 137.93103 | G22: 0 | H22: =$B$55/$B$59 -> 137.93103 | I22: =$B$55/$B$59 -> 137.93103 | J22: =$B$55/$B$59 -> 137.93103 | K22: =$B$55/$B$59 -> 137.93103 | L22: =$B$55/$B$59 -> 137.93103 | M22: =$B$55/$B$59 -> 137.93103 | N22: =$B$55/$B$59 -> 137.93103 | O22: =$B$55/$B$59 -> 137.93103 | ... U22: =$B$55/$B$59 -> 137.93103 | V22: 0 | W22: =$B$55/$B$59 -> 137.93103 | X22: =$B$55/$B$59 -> 137.93103 | Y22: =$B$55/$B$59 -> 137.93103 | Z22: =$B$55/$B$59 -> 137.93103 | AA22: =$B$55/$B$59 -> 137.93103 | AB22: =$B$55/$B$59 -> 137.93103 | AC22: =$B$55/$B$59 -> 137.93103 | AD22: =$B$55/$B$59 -> 137.93103 | ... AF22: =$B$55/$B$59 -> 137.93103 | AG22: =SUM(B22:AF22) -> 4000 | AH22: =IFERROR(AVERAGE(B22:AF22),0) -> 129.03226 | AI22: =(AH22/$AH$29)*100 -> 0.89670215
A23: Others
A24: Covers | B24: 0 | C24: 0 | D24: 0 | E24: 0 | F24: 0 | G24: 0 | H24: 400 | I24: 0 | J24: 0 | K24: 0 | L24: 0 | M24: 0 | N24: 0 | O24: 0 | P24: 100 | Q24: 0 | R24: 0 | S24: 0 | T24: 0 | U24: 0 | V24: 0 | W24: 0 | X24: 1100 | Y24: 0 | Z24: 0 | AA24: 0 | AB24: 0 | AC24: 0 | AD24: 0 | AE24: 0 | AF24: 0 | AG24: =SUM(B24:AF24) -> 1600 | AH24: =IFERROR(AVERAGE(B24:AF24),0) -> 51.612903 | AI24: =(AH24/$AH$29)*100 -> 0.35868086
A25: Tissue Paper | B25: 0 | C25: 0 | D25: 0 | E25: 0 | F25: 800 | G25: 0 | H25: 0 | I25: 0 | J25: 0 | K25: 0 | L25: 0 | M25: 0 | N25: 0 | O25: 0 | P25: 0 | Q25: 0 | R25: 0 | S25: 0 | T25: 0 | U25: 0 | V25: 0 | W25: 0 | X25: 0 | Y25: 0 | Z25: 0 | AA25: 0 | AB25: 0 | AC25: 0 | AD25: 0 | AE25: 0 | AF25: 0 | AG25: =SUM(B25:AF25) -> 800 | AH25: =IFERROR(AVERAGE(B25:AF25),0) -> 25.806452 | AI25: =(AH25/$AH$29)*100 -> 0.17934043
A26: Utilities | B26: 50 | C26: =220+70 -> 290 | D26: 50 | E26: 0 | F26: 0 | G26: 0 | H26: 0 | I26: 100 | J26: 40 | K26: 0 | L26: 0 | M26: 220 | N26: 0 | O26: 0 | P26: =280+30 -> 310 | Q26: 0 | R26: 0 | S26: 0 | T26: 1200 | U26: 0 | V26: 0 | W26: 40 | X26: 0 | Y26: 280 | Z26: 0 | AA26: 0 | AB26: 0 | AC26: 0 | AD26: 0 | AE26: 0 | AF26: 220 | AG26: =SUM(B26:AF26) -> 2800 | AH26: =IFERROR(AVERAGE(B26:AF26),0) -> 90.322581 | AI26: =(AH26/$AH$29)*100 -> 0.62769151
A27: Worker | B27: 0 | C27: 0 | D27: 0 | E27: 0 | F27: 0 | G27: 0 | H27: 0 | I27: 0 | J27: 0 | K27: 0 | L27: 0 | M27: 400 | N27: 0 | O27: 0 | P27: 0 | Q27: 0 | R27: 0 | S27: 500 | T27: 0 | U27: 0 | V27: 0 | W27: 0 | X27: 0 | Y27: 0 | Z27: 0 | AA27: 0 | AB27: 0 | AC27: 0 | AD27: 0 | AE27: 0 | AF27: 0 | AG27: =SUM(B27:AF27) -> 900 | AH27: =IFERROR(AVERAGE(B27:AF27),0) -> 29.032258 | AI27: =(AH27/$AH$29)*100 -> 0.20175798
A28: Stationery | B28: 0 | C28: 0 | D28: 0 | E28: 0 | F28: 0 | G28: 0 | H28: 0 | I28: 0 | J28: 0 | K28: 0 | L28: 0 | M28: 0 | N28: 0 | O28: 0 | P28: 0 | Q28: 0 | R28: 0 | S28: 0 | T28: 0 | U28: 0 | V28: 0 | W28: 0 | X28: 0 | Y28: 0 | Z28: 0 | AA28: 0 | AB28: 0 | AC28: 0 | AD28: 0 | AE28: 0 | AF28: 0 | AG28: =SUM(B28:AF28) -> 0 | AH28: =IFERROR(AVERAGE(B28:AF28),0) -> 0 | AI28: =(AH28/$AH$29)*100 -> 0
A29: Total | B29: =SUM(B2:B28) -> 22226.724 | C29: =SUM(C2:C28) -> 17754.724 | D29: =SUM(D2:D28) -> 12651.724 | E29: =SUM(E2:E28) -> 15356.724 | F29: =SUM(F2:F28) -> 18031.724 | G29: =SUM(G2:G28) -> 0 | H29: =SUM(H2:H28) -> 15296.724 | I29: =SUM(I2:I28) -> 14791.724 | ... AF29: =SUM(AF2:AF28) -> 13911.724 | AG29: =SUM(B29:AF29) -> 446079 | AH29: =AVERAGE(B29:AF29) -> 14389.645 | AI29: =(AH29/$AH$29)*100 -> 100
A30: UPI | B30: 26095 | C30: 4255 | D30: 6345 | E30: 9365 | F30: 10925 | G30: 0 | H30: 3460 | I30: 5200 | J30: 4930 | K30: 7665 | L30: 6155 | M30: 18450 | N30: 7095 | O30: 2925 | P30: =10670+7000 -> 17670 | Q30: 8920 | R30: 5305 | S30: 7184 | T30: 2795 | U30: 4780 | V30: 0 | W30: 890 | X30: 5527 | Y30: 6165 | Z30: 3880 | AA30: 6570 | AB30: 4825 | AC30: 2455 | AD30: 4175 | AE30: 2425 | AF30: 6280 | AG30: =SUM(B30:AF30) -> 202711 | AH30: =IFERROR(AVERAGE(B30:AF30),0) -> 6539.0645 | AI30: =IFERROR((AH30/$AH$32)*100,0) -> 54.051078
A31: Cash | B31: =B32-B30 -> 35270 | C31: =C32-C30 -> 3965 | D31: =D32-D30 -> 2500 | E31: =E32-E30 -> 2585 | F31: =F32-F30 -> 8845 | G31: =G32-G30 -> 0 | H31: =H32-H30 -> 2580 | I31: =I32-I30 -> 3155 | ... AF31: =AF32-AF30 -> 2155 | AG31: =SUM(B31:AF31) -> 172325 | AH31: =IFERROR(AVERAGE(B31:AF31),0) -> 5558.871 | AI31: =IFERROR((AH31/$AH$32)*100,0) -> 45.948922
A32: Total Sale | B32: 61365 | C32: 8220 | D32: 8845 | E32: 11950 | F32: 19770 | G32: 0 | H32: 6040 | I32: 8355 | J32: 7730 | K32: 10740 | L32: 7190 | M32: 24865 | N32: 15935 | O32: 5745 | P32: =16905+7000 -> 23905 | Q32: 18595 | R32: 14687 | S32: 14549 | T32: 13435 | U32: 10005 | V32: 0 | W32: 3955 | X32: 10095 | Y32: 9455 | Z32: 8035 | AA32: 16780 | AB32: 7835 | AC32: 5490 | AD32: 8230 | AE32: 4800 | AF32: 8435 | AG32: =SUM(B32:AF32) -> 375036 | AH32: =IFERROR(AVERAGE(B32:AF32),0) -> 12097.935 | AI32: =IFERROR((AH32/$AH$32)*100,0) -> 100
A33: Profit or Loss | B33: =B32-B29 -> 39138.276 | C33: =C32-C29 -> -9534.7241 | D33: =D32-D29 -> -3806.7241 | E33: =E32-E29 -> -3406.7241 | F33: =F32-F29 -> 1738.2759 | G33: =G32-G29 -> 0 | H33: =H32-H29 -> -9256.7241 | I33: =I32-I29 -> -6436.7241 | ... AF33: =AF32-AF29 -> -5476.7241 | AG33: =SUM(B33:AF33)+B40+B41 -> -33706 | AH33: =AVERAGE(B33:AF33,B40,B41) -> -1021.3939
A35: Monthy Expenses | B35: =SUM(B29:AF29) -> 446079
A36: Monthly UPI | B36: =SUM(B30:AF30) -> 202711 | P36: auto 30 | Q36: chicken 620 | S36: susheela | T36: fry pan/pulka
A37: Monthly Cash | B37: =SUM(B31:AF31) -> 172325 | C37: auto 70 | D37: auto 50 | F37: mirchi p | P37: catering 7k | Q37: masala 75
A38: Monthly Sales | B38: =SUM(B32:AF32) -> 375036
A39: Rent, Salaries & others | B39: =Expenses!E20 -> 88972
A40: Swiggy | B40: =1912+6934+6665+3336+4823 -> 23670
A41: Zomato | B41: =4155+2622+2895+3995 -> 13667
A42: Stock | B42: =Stock!C72 -> 95268
A43: Actual P/L | B43: =B38-B35+B40+B41 -> -33706
A45: Chefs amount from Javeed | B45: 0 | C45: 0 | D45: 0 | E45: 0 | F45: 0 | G45: 0 | H45: 3200 | I45: 900 | J45: 3200 | K45: 3200 | L45: 3200 | M45: 1800 | N45: 1800 | O45: 1800 | P45: 1800 | Q45: 1800 | R45: 1800 | S45: 1800 | T45: 800 | U45: 800 | V45: 0 | W45: 400 | X45: 0 | Y45: 0 | Z45: 0 | AA45: 0 | AB45: 0 | AC45: 0 | AD45: 0 | AE45: 3200 | AF45: 3200 | AG45: =SUM(B45:AF45) -> 34700
A46: Market from Javeed | B46: 0 | C46: 0 | D46: 1000 | E46: 0 | F46: 1900 | G46: 0 | H46: 0 | I46: 1000 | J46: 900 | K46: 1800 | L46: 0 | M46: 1500 | N46: 2500 | O46: 0 | P46: 0 | Q46: 700 | R46: 0 | S46: 0 | T46: 0 | U46: 0 | V46: 0 | W46: 1900 | X46: 0 | Y46: 0 | Z46: 0 | AA46: 0 | AB46: 0 | AC46: 0 | AD46: 1100 | AE46: 1200 | AF46: 1300 | AG46: =SUM(B46:AF46) -> 16800
A47: Javeed's Expenses | B47: =B4+B3+B7+B8+(SUM(B20:B22))+B45+B46 -> 8011.7241 | C47: =C4+C3+C7+C8+(SUM(C20:C22))+C45+C46 -> 8011.7241 | D47: =D4+D3+D7+D8+(SUM(D20:D22))+D45+D46 -> 9011.7241 | E47: =E4+E3+E7+E8+(SUM(E20:E22))+E45+E46 -> 8011.7241 | F47: =F4+F3+F7+F8+(SUM(F20:F22))+F45+F46 -> 9911.7241 | G47: =G4+G3+G7+G8+(SUM(G20:G22))+G45+G46 -> 0 | H47: =H4+H3+H7+H8+(SUM(H20:H22))+H45+H46 -> 11211.724 | I47: =I4+I3+I7+I8+(SUM(I20:I22))+I45+I46 -> 9911.7241 | J47: =J4+J3+J7+J8+(SUM(J20:J22))+J45+J46 -> 12111.724 | K47: =K4+K3+K7+K8+(SUM(K20:K22))+K45+K46-10000 -> 3011.7241 | L47: =L4+L3+L7+L8+(SUM(L20:L22))+L45+L46 -> 11211.724 | M47: =M4+M3+M7+M8+(SUM(M20:M22))+M45+M46 -> 11311.724 | N47: =N4+N3+N7+N8+(SUM(N20:N22))+N45+N46 -> 12311.724 | O47: =O4+O3+O7+O8+(SUM(O20:O22))+O45+O46 -> 9811.7241 | P47: =P4+P3+P7+P8+(SUM(P20:P22))+P45+P46 -> 9811.7241 | Q47: =Q4+Q3+Q7+Q8+(SUM(Q20:Q22))+Q45+Q46 -> 10511.724 | R47: =R4+R3+R7+R8+(SUM(R20:R22))+R45+R46 -> 9811.7241 | S47: =S4+S3+S7+S8+(SUM(S20:S22))+S45+S46 -> 9811.7241 | ... AF47: =AF4+AF3+AF7+AF8+(SUM(AF20:AF22))+AF45+AF46 -> 12511.724 | AG47: =SUM(B47:AF47) -> 273840
A48: Counter Cash | B48: =B31-B29+B47+6107 -> 27162 | C48: =B48+C31-C29+C47 -> 21384 | D48: =C48+D31-D29+D47 -> 20244 | E48: =D48+E31-E29+E47 -> 15484 | F48: =E48+F31-F29+F47 -> 16209 | G48: =F48+G31-G29+G47 -> 16209 | H48: =G48+H31-H29+H47 -> 14704 | I48: =H48+I31-I29+I47 -> 12979 | J48: =I48+J31-J29+J47 -> 13795 | ... AF48: =AE48+AF31-AF29+AF47 -> 6193
A51: Mutton | B51: =3500+1400 -> 4900
A52: Sea Food | B52: =2500+1300+2400 -> 6200
A53: Gas | B53: =8000+8000+8000+4000 -> 28000
A54: Coal | B54: =2500+2500 -> 5000
A55: Water | B55: 4000
B56: =SUM(B51:B55) -> 48100 | J56: Mon | L56: =G32 -> 0 | M56: =N32 -> 15935 | N56: =U32 -> 10005 | O56: =AB32 -> 7835 | P56: =AVERAGEIF(K56:O56,"<>0") -> 11258.333
J57: Tue | L57: =H32 -> 6040 | M57: =O32 -> 5745 | N57: =V32 -> 0 | O57: =AC32 -> 5490 | P57: =AVERAGEIF(K57:O57,"<>0") -> 5758.3333
J58: Wed | K58: =B32 -> 61365 | L58: =I32 -> 8355 | M58: =P32 -> 23905 | N58: =W32 -> 3955 | O58: =AD32 -> 8230 | P58: =AVERAGEIF(K58:O58,"<>0") -> 21162
A59: Number of Days | B59: 29 | J59: Thu | K59: =C32 -> 8220 | L59: =J32 -> 7730 | M59: =Q32 -> 18595 | N59: =X32 -> 10095 | O59: =AF32 -> 8435 | P59: =AVERAGEIF(K59:O59,"<>0") -> 10615
J60: Fri | K60: =D32 -> 8845 | L60: =K32 -> 10740 | M60: =R32 -> 14687 | N60: =Y32 -> 9455 | P60: =AVERAGEIF(K60:O60,"<>0") -> 10931.75
J61: Sat | K61: =E32 -> 11950 | L61: =L32 -> 7190 | M61: =S32 -> 14549 | N61: =Z32 -> 8035 | P61: =AVERAGEIF(K61:O61,"<>0") -> 10431
J62: Sun | K62: =F32 -> 19770 | L62: =M32 -> 24865 | M62: =T32 -> 13435 | N62: =AA32 -> 16780 | P62: =AVERAGEIF(K62:O62,"<>0") -> 18712.5

Sheet Febraury
B1: 45689 | C1: 45690 | D1: 45691 | E1: 45692 | F1: 45693 | G1: 45694 | H1: 45695 | I1: 45696 | J1: 45697 | K1: 45698 | L1: 45699 | M1: 45700 | N1: 45701 | O1: 45702 | P1: 45703 | Q1: 45704 | R1: 45705 | S1: 45706 | T1: 45707 | U1: 45708 | V1: 45709 | W1: 45710 | X1: 45711 | Y1: 45712 | Z1: 45713 | AA1: 45714 | AB1: 45715 | AC1: 45716 | AD1: Total | AE1: Average | AF1: % Share
A2: Chef | B2: 3200 | C2: 3200 | D2: 3200 | E2: 3200 | F2: 3200 | G2: 3200 | H2: 3200 | I2: 3200 | J2: 3200 | K2: 3200 | L2: 3200 | M2: 0 | N2: 3200 | O2: 3200 | P2: 3200 | Q2: 3200 | R2: 3200 | S2: 3200 | T2: 3200 | U2: 3200 | V2: 3200 | W2: 3200 | X2: 3200 | Y2: 3200 | Z2: 0 | AA2: 0 | AB2: 3200 | AC2: 3200 | AD2: =SUM(B2:AC2) -> 80000 | AE2: =IFERROR(AVERAGE(B2:AC2),0) -> 2857.1429 | AF2: =(AE2/$AE$29)*100 -> 24.059571
A3: Salaries, Rent and others | B3: =$B$39/$B$59 -> 3635.64 | C3: =$B$39/$B$59 -> 3635.64 | D3: =$B$39/$B$59 -> 3635.64 | E3: =$B$39/$B$59 -> 3635.64 | F3: =$B$39/$B$59 -> 3635.64 | G3: =$B$39/$B$59 -> 3635.64 | H3: =$B$39/$B$59 -> 3635.64 | I3: =$B$39/$B$59 -> 3635.64 | ... L3: =$B$39/$B$59 -> 3635.64 | M3: 0 | N3: =$B$39/$B$59 -> 3635.64 | O3: =$B$39/$B$59 -> 3635.64 | P3: =$B$39/$B$59 -> 3635.64 | Q3: =$B$39/$B$59 -> 3635.64 | R3: =$B$39/$B$59 -> 3635.64 | S3: =$B$39/$B$59 -> 3635.64 | T3: =$B$39/$B$59 -> 3635.64 | U3: =$B$39/$B$59 -> 3635.64 | ... Y3: =$B$39/$B$59 -> 3635.64 | Z3: 0 | AA3: 0 | AB3: =$B$39/$B$59 -> 3635.64 | AC3: =$B$39/$B$59 -> 3635.64 | AD3: =SUM(B3:AC3) -> 90891 | AE3: =IFERROR(AVERAGE(B3:AC3),0) -> 3246.1071 | AF3: =(AE3/$AE$29)*100 -> 27.334981
A4: Stock | B4: =$B$42/$B$59 -> 2702.12 | C4: =$B$42/$B$59 -> 2702.12 | D4: =$B$42/$B$59 -> 2702.12 | E4: =$B$42/$B$59 -> 2702.12 | F4: =$B$42/$B$59 -> 2702.12 | G4: =$B$42/$B$59 -> 2702.12 | H4: =$B$42/$B$59 -> 2702.12 | I4: =$B$42/$B$59 -> 2702.12 | ... L4: =$B$42/$B$59 -> 2702.12 | M4: 0 | N4: =$B$42/$B$59 -> 2702.12 | O4: =$B$42/$B$59 -> 2702.12 | P4: =$B$42/$B$59 -> 2702.12 | Q4: =$B$42/$B$59 -> 2702.12 | R4: =$B$42/$B$59 -> 2702.12 | S4: =$B$42/$B$59 -> 2702.12 | T4: =$B$42/$B$59 -> 2702.12 | U4: =$B$42/$B$59 -> 2702.12 | ... Y4: =$B$42/$B$59 -> 2702.12 | Z4: 0 | AA4: 0 | AB4: =$B$42/$B$59 -> 2702.12 | AC4: =$B$42/$B$59 -> 2702.12 | AD4: =SUM(B4:AC4) -> 67553 | AE4: =IFERROR(AVERAGE(B4:AC4),0) -> 2412.6071 | AF4: =(AE4/$AE$29)*100 -> 20.316203
A5: Meat
A6: Chicken | B6: 2000 | C6: 2000 | D6: 1500 | E6: 1500 | F6: 1000 | G6: 1500 | H6: 0 | I6: 1500 | J6: 2500 | K6: 1500 | L6: 1000 | M6: 0 | N6: 1000 | O6: 1000 | P6: 1500 | Q6: 2000 | R6: 1000 | S6: 0 | T6: 0 | U6: 1500 | V6: 1000 | W6: 1000 | X6: 1000 | Y6: 1000 | Z6: 0 | AA6: 0 | AB6: 0 | AC6: 1000 | AD6: =SUM(B6:AC6) -> 29000 | AE6: =IFERROR(AVERAGE(B6:AC6),0) -> 1035.7143 | AF6: =(AE6/$AE$29)*100 -> 8.7215947
A7: Mutton | B7: =$B$51/$B$59 -> 112 | C7: =$B$51/$B$59 -> 112 | D7: =$B$51/$B$59 -> 112 | E7: =$B$51/$B$59 -> 112 | F7: =$B$51/$B$59 -> 112 | G7: =$B$51/$B$59 -> 112 | H7: =$B$51/$B$59 -> 112 | I7: =$B$51/$B$59 -> 112 | ... L7: =$B$51/$B$59 -> 112 | M7: 0 | N7: =$B$51/$B$59 -> 112 | O7: =$B$51/$B$59 -> 112 | P7: =$B$51/$B$59 -> 112 | Q7: =$B$51/$B$59 -> 112 | R7: =$B$51/$B$59 -> 112 | S7: =$B$51/$B$59 -> 112 | T7: =$B$51/$B$59 -> 112 | U7: =$B$51/$B$59 -> 112 | ... Y7: =$B$51/$B$59 -> 112 | Z7: 0 | AA7: 0 | AB7: =$B$51/$B$59 -> 112 | AC7: =$B$51/$B$59 -> 112 | AD7: =SUM(B7:AC7) -> 2800 | AE7: =IFERROR(AVERAGE(B7:AC7),0) -> 100 | AF7: =(AE7/$AE$29)*100 -> 0.842085
A8: Sea food | B8: =$B$52/$B$59 -> 0 | C8: =$B$52/$B$59 -> 0 | D8: =$B$52/$B$59 -> 0 | E8: =$B$52/$B$59 -> 0 | F8: =$B$52/$B$59 -> 0 | G8: =$B$52/$B$59 -> 0 | H8: =$B$52/$B$59 -> 0 | I8: =$B$52/$B$59 -> 0 | ... AC8: =$B$52/$B$59 -> 0 | AD8: =SUM(B8:AC8) -> 0 | AE8: =IFERROR(AVERAGE(B8:AC8),0) -> 0 | AF8: =(AE8/$AE$29)*100 -> 0
A9: Market
A10: All Vegetables | B10: =30+20+120+30+40+50+20+40 -> 350 | C10: =30+20+200+50+40+50+20 -> 410 | D10: =20+10+30+120+50+20+50+20+50 -> 370 | E10: =30+10+20+40+120+30+60 -> 310 | F10: =20+10+30+30+20+30+50+50+120 -> 360 | G10: =30+10+30+120+10+30+50+30 -> 310 | H10: =10+30+100+30+10+30+50+50 -> 310 | I10: =20+10+30+30+50+120+30+20 -> 310 | J10: =20+20+10+30+160+20+50+50+30+50 -> 440 | K10: =20+20+400+50+20+30+30+30+40 -> 640 | L10: =10+10+20+30+10+30+100 -> 210 | M10: 0 | N10: =10+10+30+20+30+30+20+80+50 -> 280 | O10: =20+10+20+30+240+40+40+40 -> 440 | P10: =20+20+30+30+120+20+30+30+40+30+50 -> 420 | Q10: =40+20+200+30+20+30+30+50+130+50 -> 600 | R10: =30+10+30+30+80+30+80+30+30+50 -> 400 | S10: =10+10+20+80+30+20+50 -> 220 | T10: =20+20+30+80+30+30+30+30+20 -> 290 | U10: =20+10+80+1950+30+30+20+30+60+20 -> 2250 | V10: =10+30+50+25+40+30 -> 185 | W10: =20+20+30+20+20+30+50 -> 190 | X10: =20+20+50+30+30+20+30+50+200 -> 450 | Y10: =10+10+30+80+30+30+30 -> 220 | Z10: 0 | AA10: 0 | AB10: =20+10+40+30+100+10+30+30 -> 270 | AC10: =10+10+10+10+30+30+30+320+60 -> 510 | AD10: =SUM(B10:AC10) -> 10745 | AE10: =IFERROR(AVERAGE(B10:AC10),0) -> 383.75 | AF10: =(AE10/$AE$29)*100 -> 3.2315012
A11: Curd | B11: 100 | C11: 200 | D11: 150 | E11: 150 | F11: 150 | G11: 150 | H11: 150 | I11: 150 | J11: 150 | K11: 150 | L11: 150 | M11: 0 | N11: 150 | O11: 150 | P11: 150 | Q11: 200 | R11: 150 | S11: 150 | T11: 150 | U11: 150 | V11: 50 | W11: 100 | X11: 200 | Y11: 150 | Z11: 0 | AA11: 0 | AB11: 150 | AC11: 150 | AD11: =SUM(B11:AC11) -> 3700 | AE11: =IFERROR(AVERAGE(B11:AC11),0) -> 132.14286 | AF11: =(AE11/$AE$29)*100 -> 1.1127552
A12: Milk | B12: 100 | C12: 130 | D12: 100 | E12: 65 | F12: 100 | G12: 100 | H12: 100 | I12: 100 | J12: 130 | K12: 100 | L12: 100 | M12: 0 | N12: 100 | O12: 100 | P12: 65 | Q12: 130 | R12: 130 | S12: 130 | T12: 100 | U12: 65 | V12: 65 | W12: 100 | X12: 130 | Y12: 100 | Z12: 0 | AA12: 0 | AB12: 100 | AC12: 100 | AD12: =SUM(B12:AC12) -> 2540 | AE12: =IFERROR(AVERAGE(B12:AC12),0) -> 90.714286 | AF12: =(AE12/$AE$29)*100 -> 0.7638914
A13: Paneer | B13: 0 | C13: 0 | D13: 0 | E13: 370 | F13: 0 | G13: 0 | H13: 0 | I13: 370 | J13: 0 | K13: 370 | L13: 0 | M13: 0 | N13: 0 | O13: 370 | P13: 0 | Q13: 370 | R13: 0 | S13: 0 | T13: 370 | U13: 0 | V13: 370 | W13: 0 | X13: 370 | Y13: 0 | Z13: 0 | AA13: 0 | AB13: 370 | AC13: 0 | AD13: =SUM(B13:AC13) -> 3330 | AE13: =IFERROR(AVERAGE(B13:AC13),0) -> 118.92857 | AF13: =(AE13/$AE$29)*100 -> 1.0014797
A14: Mushroom | B14: 120 | C14: 0 | D14: 0 | E14: 80 | F14: 80 | G14: 0 | H14: 0 | I14: 120 | J14: 0 | K14: 80 | L14: 0 | M14: 0 | N14: 0 | O14: 120 | P14: 0 | Q14: 0 | R14: 80 | S14: 0 | T14: 0 | U14: 0 | V14: 80 | W14: 0 | X14: 0 | Y14: 120 | Z14: 0 | AA14: 0 | AB14: 120 | AC14: 80 | AD14: =SUM(B14:AC14) -> 1080 | AE14: =IFERROR(AVERAGE(B14:AC14),0) -> 38.571429 | AF14: =(AE14/$AE$29)*100 -> 0.32480422
A15: Babycorn | B15: 0 | C15: 0 | D15: 0 | E15: 70 | F15: 70 | G15: 35 | H15: 0 | I15: 70 | J15: 0 | K15: 70 | L15: 0 | M15: 0 | N15: 0 | O15: 0 | P15: 105 | Q15: 0 | R15: 0 | S15: 0 | T15: 0 | U15: 0 | V15: 0 | W15: 70 | X15: 0 | Y15: 105 | Z15: 0 | AA15: 0 | AB15: 0 | AC15: 0 | AD15: =SUM(B15:AC15) -> 595 | AE15: =IFERROR(AVERAGE(B15:AC15),0) -> 21.25 | AF15: =(AE15/$AE$29)*100 -> 0.17894306
A16: Eggs | B16: 170 | C16: 0 | D16: 170 | E16: 0 | F16: 170 | G16: 0 | H16: 170 | I16: 0 | J16: 170 | K16: 170 | L16: 0 | M16: 0 | N16: 170 | O16: 170 | P16: 0 | Q16: 170 | R16: 170 | S16: 0 | T16: 0 | U16: 170 | V16: 170 | W16: 0 | X16: 170 | Y16: 0 | Z16: 0 | AA16: 0 | AB16: 0 | AC16: 170 | AD16: =SUM(B16:AC16) -> 2380 | AE16: =IFERROR(AVERAGE(B16:AC16),0) -> 85 | AF16: =(AE16/$AE$29)*100 -> 0.71577225
A17: Dry Grocery | B17: 89 | C17: 80 | D17: 0 | E17: 110 | F17: 0 | G17: 89 | H17: 0 | I17: 590 | J17: =200+90+1000 -> 1290 | K17: 65 | L17: 55 | M17: 0 | N17: 89 | O17: 0 | P17: 0 | Q17: =200+89 -> 289 | R17: 500 | S17: 0 | T17: 0 | U17: 0 | V17: 0 | W17: =65+89 -> 154 | X17: 0 | Y17: 0 | Z17: 0 | AA17: 0 | AB17: 0 | AC17: =200+89 -> 289 | AD17: =SUM(B17:AC17) -> 3689 | AE17: =IFERROR(AVERAGE(B17:AC17),0) -> 131.75 | AF17: =(AE17/$AE$29)*100 -> 1.109447
A18: Garlic | B18: 0 | C18: 110 | D18: 0 | E18: 110 | F18: 0 | G18: 0 | H18: 110 | I18: 100 | J18: 0 | K18: 0 | L18: 0 | M18: 0 | N18: 190 | O18: 0 | P18: 0 | Q18: 360 | R18: 100 | S18: 120 | T18: 0 | U18: 0 | V18: 0 | W18: 80 | X18: 120 | Y18: 0 | Z18: 0 | AA18: 0 | AB18: 0 | AC18: 0 | AD18: =SUM(B18:AC18) -> 1400 | AE18: =IFERROR(AVERAGE(B18:AC18),0) -> 50 | AF18: =(AE18/$AE$29)*100 -> 0.4210425
A19: Running
A20: Gas | B20: =$B$53/$B$59 -> 800 | C20: =$B$53/$B$59 -> 800 | D20: =$B$53/$B$59 -> 800 | E20: =$B$53/$B$59 -> 800 | F20: =$B$53/$B$59 -> 800 | G20: =$B$53/$B$59 -> 800 | H20: =$B$53/$B$59 -> 800 | I20: =$B$53/$B$59 -> 800 | ... L20: =$B$53/$B$59 -> 800 | M20: 0 | N20: =$B$53/$B$59 -> 800 | O20: =$B$53/$B$59 -> 800 | P20: =$B$53/$B$59 -> 800 | Q20: =$B$53/$B$59 -> 800 | R20: =$B$53/$B$59 -> 800 | S20: =$B$53/$B$59 -> 800 | T20: =$B$53/$B$59 -> 800 | U20: =$B$53/$B$59 -> 800 | ... Y20: =$B$53/$B$59 -> 800 | Z20: 0 | AA20: 0 | AB20: =$B$53/$B$59 -> 800 | AC20: =$B$53/$B$59 -> 800 | AD20: =SUM(B20:AC20) -> 20000 | AE20: =IFERROR(AVERAGE(B20:AC20),0) -> 714.28571 | AF20: =(AE20/$AE$29)*100 -> 6.0148929
A21: Coal | B21: =$B$54/$B$59 -> 200 | C21: =$B$54/$B$59 -> 200 | D21: =$B$54/$B$59 -> 200 | E21: =$B$54/$B$59 -> 200 | F21: =$B$54/$B$59 -> 200 | G21: =$B$54/$B$59 -> 200 | H21: =$B$54/$B$59 -> 200 | I21: =$B$54/$B$59 -> 200 | ... L21: =$B$54/$B$59 -> 200 | M21: 0 | N21: =$B$54/$B$59 -> 200 | O21: =$B$54/$B$59 -> 200 | P21: =$B$54/$B$59 -> 200 | Q21: =$B$54/$B$59 -> 200 | R21: =$B$54/$B$59 -> 200 | S21: =$B$54/$B$59 -> 200 | T21: =$B$54/$B$59 -> 200 | U21: =$B$54/$B$59 -> 200 | ... Y21: =$B$54/$B$59 -> 200 | Z21: 0 | AA21: 0 | AB21: =$B$54/$B$59 -> 200 | AC21: =$B$54/$B$59 -> 200 | AD21: =SUM(B21:AC21) -> 5000 | AE21: =IFERROR(AVERAGE(B21:AC21),0) -> 178.57143 | AF21: =(AE21/$AE$29)*100 -> 1.5037232
A22: Water | B22: =$B$55/$B$59 -> 127 | C22: =$B$55/$B$59 -> 127 | D22: =$B$55/$B$59 -> 127 | E22: =$B$55/$B$59 -> 127 | F22: =$B$55/$B$59 -> 127 | G22: =$B$55/$B$59 -> 127 | H22: =$B$55/$B$59 -> 127 | I22: =$B$55/$B$59 -> 127 | ... L22: =$B$55/$B$59 -> 127 | M22: 0 | N22: =$B$55/$B$59 -> 127 | O22: =$B$55/$B$59 -> 127 | P22: =$B$55/$B$59 -> 127 | Q22: =$B$55/$B$59 -> 127 | R22: =$B$55/$B$59 -> 127 | S22: =$B$55/$B$59 -> 127 | T22: =$B$55/$B$59 -> 127 | U22: =$B$55/$B$59 -> 127 | ... Y22: =$B$55/$B$59 -> 127 | Z22: 0 | AA22: 0 | AB22: =$B$55/$B$59 -> 127 | AC22: =$B$55/$B$59 -> 127 | AD22: =SUM(B22:AC22) -> 3175 | AE22: =IFERROR(AVERAGE(B22:AC22),0) -> 113.39286 | AF22: =(AE22/$AE$29)*100 -> 0.95486424
A23: Others
A24: Covers | B24: 0 | C24: 0 | D24: 0 | E24: 0 | F24: 0 | G24: 0 | H24: 0 | I24: 0 | J24: 0 | K24: 0 | L24: 0 | M24: 0 | N24: 0 | O24: 0 | P24: 0 | Q24: 0 | R24: 0 | S24: 780 | T24: 0 | U24: 0 | V24: 100 | W24: 0 | X24: 0 | Y24: 0 | Z24: 0 | AA24: 0 | AB24: 0 | AC24: 0 | AD24: =SUM(B24:AC24) -> 880 | AE24: =IFERROR(AVERAGE(B24:AC24),0) -> 31.428571 | AF24: =(AE24/$AE$29)*100 -> 0.26465529
A25: Tissue Paper | B25: 0 | C25: 0 | D25: 0 | E25: 0 | F25: 0 | G25: 0 | H25: 0 | I25: 0 | J25: 0 | K25: 0 | L25: 500 | M25: 0 | N25: 0 | O25: 0 | P25: 0 | Q25: 0 | R25: 0 | S25: 0 | T25: 0 | U25: 0 | V25: 0 | W25: 0 | X25: 500 | Y25: 0 | Z25: 0 | AA25: 0 | AB25: 0 | AC25: 0 | AD25: =SUM(B25:AC25) -> 1000 | AE25: =IFERROR(AVERAGE(B25:AC25),0) -> 35.714286 | AF25: =(AE25/$AE$29)*100 -> 0.30074464
A26: Utilities | B26: 0 | C26: 80 | D26: 280 | E26: 0 | F26: 0 | G26: 280 | H26: 0 | I26: 100 | J26: 0 | K26: 0 | L26: 0 | M26: 0 | N26: 270 | O26: 160 | P26: 0 | Q26: 0 | R26: 0 | S26: 0 | T26: 0 | U26: 280 | V26: 100 | W26: 0 | X26: 0 | Y26: 0 | Z26: 0 | AA26: 0 | AB26: 0 | AC26: 0 | AD26: =SUM(B26:AC26) -> 1550 | AE26: =IFERROR(AVERAGE(B26:AC26),0) -> 55.357143 | AF26: =(AE26/$AE$29)*100 -> 0.4661542
A27: Worker | B27: 0 | C27: 0 | D27: 0 | E27: 0 | F27: 0 | G27: 0 | H27: 0 | I27: 0 | J27: 0 | K27: 400 | L27: 400 | M27: 0 | N27: 0 | O27: 0 | P27: 0 | Q27: 0 | R27: 0 | S27: 0 | T27: 0 | U27: 0 | V27: 0 | W27: 0 | X27: 0 | Y27: 0 | Z27: 0 | AA27: 0 | AB27: 400 | AC27: 0 | AD27: =SUM(B27:AC27) -> 1200 | AE27: =IFERROR(AVERAGE(B27:AC27),0) -> 42.857143 | AF27: =(AE27/$AE$29)*100 -> 0.36089357
A28: Stationery | B28: 0 | C28: 0 | D28: 0 | E28: 0 | F28: 0 | G28: 0 | H28: 0 | I28: 0 | J28: 0 | K28: 0 | L28: 0 | M28: 0 | N28: 0 | O28: 0 | P28: 0 | Q28: 0 | R28: 0 | S28: 0 | T28: 0 | U28: 0 | V28: 0 | W28: 0 | X28: 0 | Y28: 0 | Z28: 0 | AA28: 0 | AB28: 0 | AC28: 0 | AD28: =SUM(B28:AC28) -> 0 | AE28: =IFERROR(AVERAGE(B28:AC28),0) -> 0 | AF28: =(AE28/$AE$29)*100 -> 0
A29: Total | B29: =SUM(B2:B28) -> 13705.76 | C29: =SUM(C2:C28) -> 13786.76 | D29: =SUM(D2:D28) -> 13346.76 | E29: =SUM(E2:E28) -> 13541.76 | F29: =SUM(F2:F28) -> 12706.76 | G29: =SUM(G2:G28) -> 13240.76 | H29: =SUM(H2:H28) -> 11616.76 | I29: =SUM(I2:I28) -> 14186.76 | ... AC29: =SUM(AC2:AC28) -> 13075.76 | AD29: =SUM(B29:AC29) -> 332508 | AE29: =AVERAGE(B29:AC29) -> 11875.286 | AF29: =(AE29/$AE$29)*100 -> 100
A30: UPI | B30: 4450 | C30: 10610 | D30: 4135 | E30: 2875 | F30: 3545 | G30: 2245 | H30: 6285 | I30: 3715 | J30: 9705 | K30: 2285 | L30: 1305 | M30: 0 | N30: 3495 | O30: 5235 | P30: 3685 | Q30: 6360 | R30: 610 | S30: 1395 | T30: 2795 | U30: 3825 | V30: 1220 | W30: 2120 | X30: 6035 | Y30: 4800 | Z30: 0 | AA30: 0 | AB30: 5425 | AC30: 4862 | AD30: =SUM(B30:AC30) -> 103017 | AE30: =IFERROR(AVERAGE(B30:AC30),0) -> 3679.1786 | AF30: =IFERROR((AE30/$AE$32)*100,0) -> 48.969435
A31: Cash | B31: =B32-B30 -> 4990 | C31: =C32-C30 -> 5095 | D31: =D32-D30 -> 4020 | E31: =E32-E30 -> 4395 | F31: =F32-F30 -> 1550 | G31: =G32-G30 -> 3505 | H31: =H32-H30 -> 3220 | I31: =I32-I30 -> 5740 | ... AC31: =AC32-AC30 -> 5413 | AD31: =SUM(B31:AC31) -> 107353 | AE31: =IFERROR(AVERAGE(B31:AC31),0) -> 3834.0357 | AF31: =IFERROR((AE31/$AE$32)*100,0) -> 51.030565
A32: Total Sale | B32: 9440 | C32: 15705 | D32: 8155 | E32: 7270 | F32: 5095 | G32: 5750 | H32: 9505 | I32: 9455 | J32: 19395 | K32: 4785 | L32: 4800 | M32: 0 | N32: 7850 | O32: 8595 | P32: 7925 | Q32: 15155 | R32: 2815 | S32: 5565 | T32: 8775 | U32: 6485 | V32: 3890 | W32: 7145 | X32: 11125 | Y32: 8340 | Z32: 0 | AA32: 0 | AB32: 7075 | AC32: 10275 | AD32: =SUM(B32:AC32) -> 210370 | AE32: =IFERROR(AVERAGE(B32:AC32),0) -> 7513.2143 | AF32: =IFERROR((AE32/$AE$32)*100,0) -> 100
A33: Profit or Loss | B33: =B32-B29 -> -4265.76 | C33: =C32-C29 -> 1918.24 | D33: =D32-D29 -> -5191.76 | E33: =E32-E29 -> -6271.76 | F33: =F32-F29 -> -7611.76 | G33: =G32-G29 -> -7490.76 | H33: =H32-H29 -> -2111.76 | I33: =I32-I29 -> -4731.76 | ... AC33: =AC32-AC29 -> -2800.76 | AD33: =SUM(B33:AC33)+B40+B41 -> -96129 | AE33: =AVERAGE(B33:AC33,B40,B41) -> -3204.3
A35: Monthy Expenses | B35: =SUM(B29:AC29) -> 332508
A36: Monthly UPI | B36: =SUM(B30:AC30) -> 103017 | C36: auto | D36: auto/rice | F36: B/M.....P | G36: M.......P | I36: exhaust fan
A37: Monthly Cash | B37: =SUM(B31:AC31) -> 107353 | I37: mirchi p | J37: mirchi p | K37: jameel | L37: jameel | R37: mirchi p
A38: Monthly Sales | B38: =SUM(B32:AC32) -> 210370
A39: Rent, Salaries & others | B39: =Expenses!F20 -> 90891
A40: Swiggy | B40: =3615+2908+4680+2252 -> 13455
A41: Zomato | B41: =4243+2394+1959+2074+1884 -> 12554
A42: Stock | B42: =Stock!H72 -> 67553
A43: Actual P/L | B43: =B38-B35+B40+B41 -> -96129
A45: Chefs amount from Javeed | B45: 0 | C45: 0 | D45: 0 | E45: 0 | F45: 3200 | G45: 900 | H45: 0 | I45: 0 | J45: 1000 | K45: 1000 | L45: 1000 | M45: 0 | N45: 1000 | O45: 1000 | P45: 1000 | Q45: 1000 | R45: 1000 | S45: 1000 | T45: 1000 | U45: 1000 | V45: 1000 | W45: 1000 | X45: 1000 | Y45: 1000 | Z45: 0 | AA45: 0 | AB45: 1000 | AC45: 1000 | AD45: =SUM(B45:AC45) -> 21100
A46: Market from Javeed | B46: 1000 | C46: 1100 | D46: 800 | E46: 1300 | F46: 800 | G46: 800 | H46: 900 | I46: 1500 | J46: 1100 | K46: 0 | L46: 500 | M46: 0 | N46: 0 | O46: 1500 | P46: 800 | Q46: 2100 | R46: 0 | S46: 0 | T46: 0 | U46: 1900 | V46: 320 | W46: 0 | X46: 0 | Y46: 0 | Z46: 0 | AA46: 0 | AB46: 1100 | AC46: 1200 | AD46: =SUM(B46:AC46) -> 18720
A47: Javeed's Expenses | B47: =B4+B3+B7+B8+(SUM(B20:B22))+B45+B46 -> 8576.76 | C47: =C4+C3+C7+C8+(SUM(C20:C22))+C45+C46 -> 8676.76 | D47: =D4+D3+D7+D8+(SUM(D20:D22))+D45+D46 -> 8376.76 | E47: =E4+E3+E7+E8+(SUM(E20:E22))+E45+E46 -> 8876.76 | F47: =F4+F3+F7+F8+(SUM(F20:F22))+F45+F46 -> 11576.76 | G47: =G4+G3+G7+G8+(SUM(G20:G22))+G45+G46 -> 9276.76 | H47: =H4+H3+H7+H8+(SUM(H20:H22))+H45+H46 -> 8476.76 | I47: =I4+I3+I7+I8+(SUM(I20:I22))+I45+I46 -> 9076.76 | ... AC47: =AC4+AC3+AC7+AC8+(SUM(AC20:AC22))+AC45+AC46 -> 9776.76 | AD47: =SUM(B47:AC47) -> 229239
A48: Counter Cash | B48: =B31-B29+B47+6193 -> 6054 | C48: =B48+C31-C29+C47 -> 6039 | D48: =C48+D31-D29+D47 -> 5089 | E48: =D48+E31-E29+E47 -> 4819 | F48: =E48+F31-F29+F47 -> 5239 | G48: =F48+G31-G29+G47 -> 4780 | H48: =G48+H31-H29+H47 -> 4860 | I48: =H48+I31-I29+I47 -> 5490 | J48: =I48+J31-J29+J47 -> 9400 | ... AC48: =AB48+AC31-AC29+AC47 -> 10277
A51: Mutton | B51: =1400+1400 -> 2800
A52: Sea Food | B52: 0
A53: Gas | B53: =4000+6000+4000+6000 -> 20000
A54: Coal | B54: =2500+2500 -> 5000
A55: Water | B55: 3175
B56: =SUM(B51:B55) -> 30975 | J56: Mon | L56: =D32 -> 8155 | M56: =K32 -> 4785 | N56: =R32 -> 2815 | O56: =Y32 -> 8340 | P56: =AVERAGEIF(K56:O56,"<>0") -> 6023.75
J57: Tue | L57: =E32 -> 7270 | M57: =L32 -> 4800 | N57: =S32 -> 5565 | O57: =Z32 -> 0 | P57: =AVERAGEIF(K57:O57,"<>0") -> 5878.3333
J58: Wed | L58: =F32 -> 5095 | M58: =M32 -> 0 | N58: =T32 -> 8775 | O58: =AA32 -> 0 | P58: =AVERAGEIF(K58:O58,"<>0") -> 6935
A59: Number of Days | B59: 25 | J59: Thu | L59: =G32 -> 5750 | M59: =N32 -> 7850 | N59: =U32 -> 6485 | O59: =AB32 -> 7075 | P59: =AVERAGEIF(K59:O59,"<>0") -> 6790
J60: Fri | L60: =H32 -> 9505 | M60: =O32 -> 8595 | N60: =V32 -> 3890 | O60: =AC32 -> 10275 | P60: =AVERAGEIF(K60:O60,"<>0") -> 8066.25
J61: Sat | K61: =B32 -> 9440 | L61: =I32 -> 9455 | M61: =P32 -> 7925 | N61: =W32 -> 7145 | P61: =AVERAGEIF(K61:O61,"<>0") -> 8491.25
J62: Sun | K62: =C32 -> 15705 | L62: =J32 -> 19395 | M62: =Q32 -> 15155 | N62: =X32 -> 11125 | P62: =AVERAGEIF(K62:O62,"<>0") -> 15345

Sheet March
B1: 45717 | C1: 45718 | D1: 45719 | E1: 45720 | F1: 45721 | G1: 45722 | H1: 45723 | I1: 45724 | J1: 45725 | K1: 45726 | L1: 45727 | M1: 45728 | N1: 45729 | O1: 45730 | P1: 45731 | Q1: 45732 | R1: 45733 | S1: 45734 | T1: 45735 | U1: 45736 | V1: 45737 | W1: 45738 | X1: 45739 | Y1: 45740 | Z1: 45741 | AA1: 45742 | AB1: 45743 | AC1: 45744 | AD1: 45745 | AE1: 45746 | AF1: 45747 | AG1: Total | AH1: Average | AI1: % Share
A2: Chef | B2: 3200 | C2: 3200 | D2: 3200 | E2: 3200 | F2: 3200 | G2: 0 | H2: 3200 | I2: 3200 | J2: 2900 | K2: 2900 | L2: 2900 | M2: 2900 | N2: 2900 | O2: 2900 | P2: 2900 | Q2: 2900 | R2: 0 | S2: 2900 | T2: 2900 | U2: 2900 | V2: 2900 | W2: 2900 | X2: 2900 | Y2: 2900 | Z2: 2900 | AA2: 2900 | AB2: 2900 | AC2: 2900 | AD2: 2900 | AE2: 2900 | AF2: 2900 | AG2: =SUM(B2:AF2) -> 86200 | AH2: =IFERROR(AVERAGE(B2:AF2),0) -> 2780.6452 | AI2: =(AH2/$AH$29)*100 -> 23.915016
A3: Salaries, Rent and others | B3: =$B$39/$B$59 -> 3242.1379 | C3: =$B$39/$B$59 -> 3242.1379 | D3: =$B$39/$B$59 -> 3242.1379 | E3: =$B$39/$B$59 -> 3242.1379 | F3: =$B$39/$B$59 -> 3242.1379 | G3: 0 | H3: =$B$39/$B$59 -> 3242.1379 | I3: =$B$39/$B$59 -> 3242.1379 | J3: =$B$39/$B$59 -> 3242.1379 | K3: =$B$39/$B$59 -> 3242.1379 | L3: =$B$39/$B$59 -> 3242.1379 | M3: =$B$39/$B$59 -> 3242.1379 | N3: =$B$39/$B$59 -> 3242.1379 | O3: =$B$39/$B$59 -> 3242.1379 | ... Q3: =$B$39/$B$59 -> 3242.1379 | R3: 0 | S3: =$B$39/$B$59 -> 3242.1379 | T3: =$B$39/$B$59 -> 3242.1379 | U3: =$B$39/$B$59 -> 3242.1379 | V3: =$B$39/$B$59 -> 3242.1379 | W3: =$B$39/$B$59 -> 3242.1379 | X3: =$B$39/$B$59 -> 3242.1379 | Y3: =$B$39/$B$59 -> 3242.1379 | Z3: =$B$39/$B$59 -> 3242.1379 | ... AF3: =$B$39/$B$59 -> 3242.1379 | AG3: =SUM(B3:AF3) -> 94022 | AH3: =IFERROR(AVERAGE(B3:AF3),0) -> 3032.9677 | AI3: =(AH3/$AH$29)*100 -> 26.085123
A4: Stock | B4: =$B$42/$B$59 -> 1864.931 | C4: =$B$42/$B$59 -> 1864.931 | D4: =$B$42/$B$59 -> 1864.931 | E4: =$B$42/$B$59 -> 1864.931 | F4: =$B$42/$B$59 -> 1864.931 | G4: 0 | H4: =$B$42/$B$59 -> 1864.931 | I4: =$B$42/$B$59 -> 1864.931 | J4: =$B$42/$B$59 -> 1864.931 | K4: =$B$42/$B$59 -> 1864.931 | L4: =$B$42/$B$59 -> 1864.931 | M4: =$B$42/$B$59 -> 1864.931 | N4: =$B$42/$B$59 -> 1864.931 | O4: =$B$42/$B$59 -> 1864.931 | ... Q4: =$B$42/$B$59 -> 1864.931 | R4: 0 | S4: =$B$42/$B$59 -> 1864.931 | T4: =$B$42/$B$59 -> 1864.931 | U4: =$B$42/$B$59 -> 1864.931 | V4: =$B$42/$B$59 -> 1864.931 | W4: =$B$42/$B$59 -> 1864.931 | X4: =$B$42/$B$59 -> 1864.931 | Y4: =$B$42/$B$59 -> 1864.931 | Z4: =$B$42/$B$59 -> 1864.931 | ... AF4: =$B$42/$B$59 -> 1864.931 | AG4: =SUM(B4:AF4) -> 54083 | AH4: =IFERROR(AVERAGE(B4:AF4),0) -> 1744.6129 | AI4: =(AH4/$AH$29)*100 -> 15.004592
A5: Meat
A6: Chicken | B6: 2000 | C6: 2000 | D6: 1000 | E6: 2000 | F6: 1500 | G6: 0 | H6: 1500 | I6: 1000 | J6: 2000 | K6: 1000 | L6: 1000 | M6: 1000 | N6: 900 | O6: 2000 | P6: 1500 | Q6: 2500 | R6: 0 | S6: 1500 | T6: 1200 | U6: 1000 | V6: 2000 | W6: 2000 | X6: 1500 | Y6: 1000 | Z6: 2000 | AA6: 1500 | AB6: 2000 | AC6: 1500 | AD6: 1500 | AE6: 1500 | AF6: 3000 | AG6: =SUM(B6:AF6) -> 46100 | AH6: =IFERROR(AVERAGE(B6:AF6),0) -> 1487.0968 | AI6: =(AH6/$AH$29)*100 -> 12.789817
A7: Mutton | B7: =$B$51/$B$59 -> 162.93103 | C7: =$B$51/$B$59 -> 162.93103 | D7: =$B$51/$B$59 -> 162.93103 | E7: =$B$51/$B$59 -> 162.93103 | F7: =$B$51/$B$59 -> 162.93103 | G7: 0 | H7: =$B$51/$B$59 -> 162.93103 | I7: =$B$51/$B$59 -> 162.93103 | J7: =$B$51/$B$59 -> 162.93103 | K7: =$B$51/$B$59 -> 162.93103 | L7: =$B$51/$B$59 -> 162.93103 | M7: =$B$51/$B$59 -> 162.93103 | N7: =$B$51/$B$59 -> 162.93103 | O7: =$B$51/$B$59 -> 162.93103 | ... Q7: =$B$51/$B$59 -> 162.93103 | R7: 0 | S7: =$B$51/$B$59 -> 162.93103 | T7: =$B$51/$B$59 -> 162.93103 | U7: =$B$51/$B$59 -> 162.93103 | V7: =$B$51/$B$59 -> 162.93103 | W7: =$B$51/$B$59 -> 162.93103 | X7: =$B$51/$B$59 -> 162.93103 | Y7: =$B$51/$B$59 -> 162.93103 | Z7: =$B$51/$B$59 -> 162.93103 | ... AF7: =$B$51/$B$59 -> 162.93103 | AG7: =SUM(B7:AF7) -> 4725 | AH7: =IFERROR(AVERAGE(B7:AF7),0) -> 152.41935 | AI7: =(AH7/$AH$29)*100 -> 1.3108869
A8: Sea food | B8: =$B$52/$B$59 -> 232.06897 | C8: =$B$52/$B$59 -> 232.06897 | D8: =$B$52/$B$59 -> 232.06897 | E8: =$B$52/$B$59 -> 232.06897 | F8: =$B$52/$B$59 -> 232.06897 | G8: 0 | H8: =$B$52/$B$59 -> 232.06897 | I8: =$B$52/$B$59 -> 232.06897 | J8: =$B$52/$B$59 -> 232.06897 | K8: =$B$52/$B$59 -> 232.06897 | L8: =$B$52/$B$59 -> 232.06897 | M8: =$B$52/$B$59 -> 232.06897 | N8: =$B$52/$B$59 -> 232.06897 | O8: =$B$52/$B$59 -> 232.06897 | ... Q8: =$B$52/$B$59 -> 232.06897 | R8: 0 | S8: =$B$52/$B$59 -> 232.06897 | T8: =$B$52/$B$59 -> 232.06897 | U8: =$B$52/$B$59 -> 232.06897 | V8: =$B$52/$B$59 -> 232.06897 | W8: =$B$52/$B$59 -> 232.06897 | X8: =$B$52/$B$59 -> 232.06897 | Y8: =$B$52/$B$59 -> 232.06897 | Z8: =$B$52/$B$59 -> 232.06897 | ... AF8: =$B$52/$B$59 -> 232.06897 | AG8: =SUM(B8:AF8) -> 6730 | AH8: =IFERROR(AVERAGE(B8:AF8),0) -> 217.09677 | AI8: =(AH8/$AH$29)*100 -> 1.8671468
A9: Market
A10: All Vegetables | B10: =30+20+160+50+10+45+30+30+30+20 -> 425 | C10: =40+20+30+120+30+30+30+160+50+30 -> 540 | D10: =20+10+10+20+30+30+50+50+120 -> 340 | E10: =10+20+20+20+60+30+30+120 -> 310 | F10: =10+10+20+30+20+30+50+120 -> 290 | G10: 0 | H10: =20+10+20+20+30+40+60+120 -> 320 | I10: =20+20+20+120+20+30+40+30+40+50 -> 390 | J10: =20+20+30+20+30+40+160 -> 320 | K10: =30+10+10+30+30+200+50+30+30 -> 420 | L10: =20+10+10+100+20+50+20+30 -> 260 | M10: =20+20+200+20+30+20+30+30 -> 370 | N10: =30+20+30+10+100+40+30+50+40 -> 350 | O10: =10+10+10+20+200+30+30+40+30+40 -> 420 | P10: =20+20+160+30+30+30+50+20+30 -> 390 | Q10: =20+10+200+30+30+30+120+20+50 -> 510 | R10: 0 | S10: =20+20+120+30+30+30+30+20+20 -> 320 | T10: =20+20+100+20+30+20+20+30+20 -> 280 | U10: =10+120+20+30+30+50 -> 260 | V10: =20+20+120+20+20+30+30+30+20+50+30 -> 390 | W10: =20+20+20+200+30+20+50+30+30 -> 420 | X10: =40+20+250+30+30+30+20+30+40+50+50+30 -> 620 | Y10: =20+10+20+30+30+80+1650+30+40 -> 1910 | Z10: =20+10+30+40+50+100+30+30+30+20 -> 360 | AA10: =20+20+70+20+20+30+30+20+30+30 -> 290 | AB10: =20+20+30+150+30+120+30+30+50+50 -> 530 | AC10: =30+20+30+20+120+30+30+30 -> 310 | AD10: =30+20+30+100+30+20+50+30+30+60+30 -> 430 | AE10: =30+20+50+150+30+20+30+50+30 -> 410 | AF10: =110+40+50+120+80+20+20+30+60+30 -> 560 | AG10: =SUM(B10:AD10) -> 11775 | AH10: =IFERROR(AVERAGE(B10:AF10),0) -> 411.12903 | AI10: =(AH10/$AH$29)*100 -> 3.5359266 | AJ10: 150
A11: Curd | B11: 150 | C11: 200 | D11: 150 | E11: 100 | F11: 150 | G11: 0 | H11: 150 | I11: 150 | J11: 150 | K11: 150 | L11: 150 | M11: 100 | N11: 100 | O11: 150 | P11: 200 | Q11: 200 | R11: 0 | S11: 150 | T11: 150 | U11: 150 | V11: 150 | W11: 150 | X11: 200 | Y11: 150 | Z11: 150 | AA11: 150 | AB11: 150 | AC11: 100 | AD11: 200 | AE11: 250 | AF11: 300 | AG11: =SUM(B11:AD11) -> 4100 | AH11: =IFERROR(AVERAGE(B11:AF11),0) -> 150 | AI11: =(AH11/$AH$29)*100 -> 1.2900792
A12: Milk | B12: 100 | C12: 130 | D12: 100 | E12: 65 | F12: 65 | G12: 0 | H12: 100 | I12: 65 | J12: 100 | K12: 0 | L12: 100 | M12: 100 | N12: 65 | O12: 65 | P12: 100 | Q12: 65 | R12: 0 | S12: 100 | T12: 100 | U12: 100 | V12: 65 | W12: 65 | X12: 100 | Y12: 65 | Z12: 100 | AA12: 100 | AB12: 100 | AC12: 100 | AD12: 100 | AE12: 100 | AF12: 130 | AG12: =SUM(B12:AD12) -> 2315 | AH12: =IFERROR(AVERAGE(B12:AF12),0) -> 82.096774 | AI12: =(AH12/$AH$29)*100 -> 0.70607558
A13: Paneer | B13: 0 | C13: 370 | D13: 0 | E13: 370 | F13: 0 | G13: 0 | H13: 0 | I13: 0 | J13: 0 | K13: 370 | L13: 0 | M13: 370 | N13: 0 | O13: 0 | P13: 370 | Q13: 370 | R13: 0 | S13: 370 | T13: 0 | U13: 0 | V13: 0 | W13: 370 | X13: 370 | Y13: 0 | Z13: 0 | AA13: 0 | AB13: 370 | AC13: 370 | AD13: 370 | AE13: 740 | AF13: 0 | AG13: =SUM(B13:AD13) -> 4440 | AH13: =IFERROR(AVERAGE(B13:AF13),0) -> 167.09677 | AI13: =(AH13/$AH$29)*100 -> 1.4371204
A14: Mushroom | B14: 0 | C14: 0 | D14: 80 | E14: 120 | F14: 0 | G14: 0 | H14: 0 | I14: 0 | J14: 0 | K14: 160 | L14: 0 | M14: 80 | N14: 40 | O14: 0 | P14: 196 | Q14: 120 | R14: 0 | S14: 80 | T14: 0 | U14: 80 | V14: 0 | W14: 0 | X14: 150 | Y14: 80 | Z14: 0 | AA14: 0 | AB14: 178 | AC14: 160 | AD14: 0 | AE14: 160 | AF14: 0 | AG14: =SUM(B14:AD14) -> 1524 | AH14: =IFERROR(AVERAGE(B14:AF14),0) -> 54.322581 | AI14: =(AH14/$AH$29)*100 -> 0.46720286
A15: Babycorn | B15: 70 | C15: 0 | D15: 70 | E15: 0 | F15: 0 | G15: 0 | H15: 0 | I15: 70 | J15: 0 | K15: 0 | L15: 0 | M15: 0 | N15: 0 | O15: 0 | P15: 105 | Q15: 0 | R15: 0 | S15: 0 | T15: 70 | U15: 0 | V15: 0 | W15: 0 | X15: 140 | Y15: 0 | Z15: 0 | AA15: 0 | AB15: 0 | AC15: 0 | AD15: 0 | AE15: 175 | AF15: 0 | AG15: =SUM(B15:AD15) -> 525 | AH15: =IFERROR(AVERAGE(B15:AF15),0) -> 22.580645 | AI15: =(AH15/$AH$29)*100 -> 0.19420546
A16: Eggs | B16: 170 | C16: 0 | D16: 170 | E16: 0 | F16: 0 | G16: 0 | H16: 170 | I16: 0 | J16: 170 | K16: 160 | L16: 0 | M16: 160 | N16: 160 | O16: 0 | P16: 160 | Q16: 160 | R16: 0 | S16: 160 | T16: 0 | U16: 160 | V16: 0 | W16: 160 | X16: 160 | Y16: 0 | Z16: 150 | AA16: 0 | AB16: 150 | AC16: 0 | AD16: 150 | AE16: 150 | AF16: 0 | AG16: =SUM(B16:AD16) -> 2570 | AH16: =IFERROR(AVERAGE(B16:AF16),0) -> 87.741935 | AI16: =(AH16/$AH$29)*100 -> 0.75462695
A17: Dry Grocery | B17: 0 | C17: 0 | D17: 0 | E17: =55+35+35 -> 125 | F17: 89 | G17: 0 | H17: 0 | I17: 0 | J17: 500 | K17: =100+200 -> 300 | L17: 0 | M17: 89 | N17: 0 | O17: 0 | P17: 89 | Q17: 0 | R17: 0 | S17: 0 | T17: =200+65 -> 265 | U17: 0 | V17: 89 | W17: 0 | X17: 0 | Y17: 0 | Z17: 0 | AA17: 89 | AB17: 0 | AC17: 200 | AD17: 0 | AE17: 89 | AF17: =240+110 -> 350 | AG17: =SUM(B17:AD17) -> 1835 | AH17: =IFERROR(AVERAGE(B17:AF17),0) -> 73.354839 | AI17: =(AH17/$AH$29)*100 -> 0.63089032
A18: Garlic | B18: 70 | C18: =240+120 -> 360 | D18: 0 | E18: 0 | F18: 0 | G18: 0 | H18: 150 | I18: 0 | J18: 0 | K18: 0 | L18: 100 | M18: 70 | N18: 0 | O18: 0 | P18: 0 | Q18: =140+240 -> 380 | R18: 0 | S18: 0 | T18: 0 | U18: 140 | V18: 0 | W18: 70 | X18: 0 | Y18: 70 | Z18: 0 | AA18: 60 | AB18: =80+250 -> 330 | AC18: 0 | AD18: 0 | AE18: 70 | AF18: 100 | AG18: =SUM(B18:AD18) -> 1800 | AH18: =IFERROR(AVERAGE(B18:AF18),0) -> 63.548387 | AI18: =(AH18/$AH$29)*100 -> 0.54654966
A19: Running
A20: Gas | B20: =$B$53/$B$59 -> 827.58621 | C20: =$B$53/$B$59 -> 827.58621 | D20: =$B$53/$B$59 -> 827.58621 | E20: =$B$53/$B$59 -> 827.58621 | F20: =$B$53/$B$59 -> 827.58621 | G20: 0 | H20: =$B$53/$B$59 -> 827.58621 | I20: =$B$53/$B$59 -> 827.58621 | J20: =$B$53/$B$59 -> 827.58621 | K20: =$B$53/$B$59 -> 827.58621 | L20: =$B$53/$B$59 -> 827.58621 | M20: =$B$53/$B$59 -> 827.58621 | N20: =$B$53/$B$59 -> 827.58621 | O20: =$B$53/$B$59 -> 827.58621 | ... Q20: =$B$53/$B$59 -> 827.58621 | R20: 0 | S20: =$B$53/$B$59 -> 827.58621 | T20: =$B$53/$B$59 -> 827.58621 | U20: =$B$53/$B$59 -> 827.58621 | V20: =$B$53/$B$59 -> 827.58621 | W20: =$B$53/$B$59 -> 827.58621 | X20: =$B$53/$B$59 -> 827.58621 | Y20: =$B$53/$B$59 -> 827.58621 | Z20: =$B$53/$B$59 -> 827.58621 | ... AF20: =$B$53/$B$59 -> 827.58621 | AG20: =SUM(B20:AF20) -> 24000 | AH20: =IFERROR(AVERAGE(B20:AF20),0) -> 774.19355 | AI20: =(AH20/$AH$29)*100 -> 6.658473
A21: Coal | B21: =$B$54/$B$59 -> 86.206897 | C21: =$B$54/$B$59 -> 86.206897 | D21: =$B$54/$B$59 -> 86.206897 | E21: =$B$54/$B$59 -> 86.206897 | F21: =$B$54/$B$59 -> 86.206897 | G21: 0 | H21: =$B$54/$B$59 -> 86.206897 | I21: =$B$54/$B$59 -> 86.206897 | J21: =$B$54/$B$59 -> 86.206897 | K21: =$B$54/$B$59 -> 86.206897 | L21: =$B$54/$B$59 -> 86.206897 | M21: =$B$54/$B$59 -> 86.206897 | N21: =$B$54/$B$59 -> 86.206897 | O21: =$B$54/$B$59 -> 86.206897 | ... Q21: =$B$54/$B$59 -> 86.206897 | R21: 0 | S21: =$B$54/$B$59 -> 86.206897 | T21: =$B$54/$B$59 -> 86.206897 | U21: =$B$54/$B$59 -> 86.206897 | V21: =$B$54/$B$59 -> 86.206897 | W21: =$B$54/$B$59 -> 86.206897 | X21: =$B$54/$B$59 -> 86.206897 | Y21: =$B$54/$B$59 -> 86.206897 | Z21: =$B$54/$B$59 -> 86.206897 | ... AF21: =$B$54/$B$59 -> 86.206897 | AG21: =SUM(B21:AF21) -> 2500 | AH21: =IFERROR(AVERAGE(B21:AF21),0) -> 80.645161 | AI21: =(AH21/$AH$29)*100 -> 0.69359094
A22: Water | B22: =$B$55/$B$59 -> 0 | C22: =$B$55/$B$59 -> 0 | D22: =$B$55/$B$59 -> 0 | E22: =$B$55/$B$59 -> 0 | F22: =$B$55/$B$59 -> 0 | G22: 0 | H22: =$B$55/$B$59 -> 0 | I22: =$B$55/$B$59 -> 0 | J22: =$B$55/$B$59 -> 0 | K22: =$B$55/$B$59 -> 0 | L22: =$B$55/$B$59 -> 0 | M22: =$B$55/$B$59 -> 0 | N22: =$B$55/$B$59 -> 0 | O22: =$B$55/$B$59 -> 0 | ... Q22: =$B$55/$B$59 -> 0 | R22: 0 | S22: =$B$55/$B$59 -> 0 | T22: =$B$55/$B$59 -> 0 | U22: =$B$55/$B$59 -> 0 | V22: =$B$55/$B$59 -> 0 | W22: =$B$55/$B$59 -> 0 | X22: =$B$55/$B$59 -> 0 | Y22: =$B$55/$B$59 -> 0 | Z22: =$B$55/$B$59 -> 0 | ... AF22: =$B$55/$B$59 -> 0 | AG22: =SUM(B22:AF22) -> 0 | AH22: =IFERROR(AVERAGE(B22:AF22),0) -> 0 | AI22: =(AH22/$AH$29)*100 -> 0
A23: Others
A24: Covers | B24: 0 | C24: 0 | D24: 0 | E24: 0 | F24: 0 | G24: 0 | H24: 0 | I24: 0 | J24: 0 | K24: 0 | L24: 640 | M24: 0 | N24: 0 | O24: 0 | P24: 0 | Q24: 0 | R24: 0 | S24: 0 | T24: 100 | U24: 0 | V24: 0 | W24: 0 | X24: 0 | Y24: 0 | Z24: 0 | AA24: 0 | AB24: 0 | AC24: 0 | AD24: 0 | AE24: 0 | AF24: =760+90 -> 850 | AG24: =SUM(B24:AF24) -> 1590 | AH24: =IFERROR(AVERAGE(B24:AF24),0) -> 51.290323 | AI24: =(AH24/$AH$29)*100 -> 0.44112384
A25: Tissue Paper | B25: 300 | C25: 300 | D25: 0 | E25: 0 | F25: 0 | G25: 0 | H25: 0 | I25: 0 | J25: 0 | K25: 0 | L25: 0 | M25: 0 | N25: 0 | O25: 0 | P25: 0 | Q25: 0 | R25: 0 | S25: 0 | T25: 0 | U25: 0 | V25: 0 | W25: 0 | X25: 0 | Y25: 0 | Z25: 0 | AA25: 0 | AB25: 0 | AC25: 0 | AD25: 0 | AE25: 0 | AF25: 0 | AG25: =SUM(B25:AF25) -> 600 | AH25: =IFERROR(AVERAGE(B25:AF25),0) -> 19.354839 | AI25: =(AH25/$AH$29)*100 -> 0.16646183
A26: Utilities | B26: 70 | C26: 0 | D26: =280+70 -> 350 | E26: 180 | F26: 0 | G26: 0 | H26: 0 | I26: 2100 | J26: 200 | K26: 0 | L26: 220 | M26: 0 | N26: 0 | O26: 0 | P26: 0 | Q26: 0 | R26: 0 | S26: 220 | T26: 0 | U26: 0 | V26: 285 | W26: 0 | X26: 100 | Y26: 0 | Z26: 0 | AA26: =310+150+90 -> 550 | AB26: 0 | AC26: 0 | AD26: 110 | AE26: 0 | AF26: 40 | AG26: =SUM(B26:AF26) -> 4425 | AH26: =IFERROR(AVERAGE(B26:AF26),0) -> 142.74194 | AI26: =(AH26/$AH$29)*100 -> 1.227656
A27: Worker | B27: 0 | C27: 0 | D27: 0 | E27: 0 | F27: 0 | G27: 0 | H27: 0 | I27: 0 | J27: 0 | K27: 0 | L27: 0 | M27: 0 | N27: 0 | O27: 0 | P27: 0 | Q27: 0 | R27: 0 | S27: 400 | T27: 0 | U27: 0 | V27: 0 | W27: 0 | X27: 0 | Y27: 0 | Z27: 0 | AA27: 0 | AB27: 0 | AC27: 0 | AD27: 0 | AE27: 0 | AF27: 0 | AG27: =SUM(B27:AF27) -> 400 | AH27: =IFERROR(AVERAGE(B27:AF27),0) -> 12.903226 | AI27: =(AH27/$AH$29)*100 -> 0.11097455
A28: Stationery | B28: 0 | C28: 0 | D28: 0 | E28: 0 | F28: 0 | G28: 0 | H28: 0 | I28: 0 | J28: 0 | K28: 0 | L28: 0 | M28: 0 | N28: 0 | O28: 0 | P28: 0 | Q28: 0 | R28: 0 | S28: 0 | T28: 0 | U28: 0 | V28: 600 | W28: 0 | X28: 0 | Y28: 0 | Z28: 0 | AA28: 0 | AB28: 0 | AC28: 0 | AD28: 0 | AE28: 0 | AF28: 0 | AG28: =SUM(B28:AF28) -> 600 | AH28: =IFERROR(AVERAGE(B28:AF28),0) -> 19.354839 | AI28: =(AH28/$AH$29)*100 -> 0.16646183
A29: Total | B29: =SUM(B2:B28) -> 12970.862 | C29: =SUM(C2:C28) -> 13515.862 | D29: =SUM(D2:D28) -> 11875.862 | E29: =SUM(E2:E28) -> 12885.862 | F29: =SUM(F2:F28) -> 11709.862 | G29: =SUM(G2:G28) -> 0 | H29: =SUM(H2:H28) -> 12005.862 | I29: =SUM(I2:I28) -> 13390.862 | ... AF29: =SUM(AF2:AF28) -> 14645.862 | AG29: =SUM(B29:AF29) -> 360443 | AH29: =AVERAGE(B29:AF29) -> 11627.194 | AI29: =(AH29/$AH$29)*100 -> 100
A30: UPI | B30: 3675 | C30: 6715 | D30: 3150 | E30: 3085 | F30: 5205 | G30: 0 | H30: 4610 | I30: 8120 | J30: 5865 | K30: 3695 | L30: 4920 | M30: 5660 | N30: 2555 | O30: 9425 | P30: 5135 | Q30: 8025 | R30: 0 | S30: 5300 | T30: 416 | U30: 6085 | V30: 5350 | W30: 6850 | X30: 6255 | Y30: 5170 | Z30: 5560 | AA30: 5834 | AB30: 7675 | AC30: 4610 | AD30: 8965 | AE30: 8655 | AF30: 5215 | AG30: =SUM(B30:AF30) -> 161780 | AH30: =IFERROR(AVERAGE(B30:AF30),0) -> 5218.7097 | AI30: =IFERROR((AH30/$AH$32)*100,0) -> 55.405628
A31: Cash | B31: =B32-B30 -> 5052 | C31: =C32-C30 -> 3475 | D31: =D32-D30 -> 3550 | E31: =E32-E30 -> 4435 | F31: =F32-F30 -> 2240 | G31: =G32-G30 -> 0 | H31: =H32-H30 -> 1115 | I31: =I32-I30 -> 1695 | ... AF31: =AF32-AF30 -> 11240 | AG31: =SUM(B31:AF31) -> 130212 | AH31: =IFERROR(AVERAGE(B31:AF31),0) -> 4200.3871 | AI31: =IFERROR((AH31/$AH$32)*100,0) -> 44.594372
A32: Total Sale | B32: 8727 | C32: 10190 | D32: 6700 | E32: 7520 | F32: 7445 | G32: 0 | H32: 5725 | I32: 9815 | J32: 11325 | K32: 4665 | L32: 7245 | M32: 11270 | N32: 7780 | O32: 17470 | P32: 12475 | Q32: 15785 | R32: 0 | S32: 6850 | T32: 5445 | U32: 11460 | V32: 9305 | W32: 13715 | X32: 10055 | Y32: 9100 | Z32: 7830 | AA32: 8385 | AB32: 13380 | AC32: 11105 | AD32: 12735 | AE32: 12035 | AF32: 16455 | AG32: =SUM(B32:AF32) -> 291992 | AH32: =IFERROR(AVERAGE(B32:AF32),0) -> 9419.0968 | AI32: =IFERROR((AH32/$AH$32)*100,0) -> 100
A33: Profit or Loss | B33: =B32-B29 -> -4243.8621 | C33: =C32-C29 -> -3325.8621 | D33: =D32-D29 -> -5175.8621 | E33: =E32-E29 -> -5365.8621 | F33: =F32-F29 -> -4264.8621 | G33: =G32-G29 -> 0 | H33: =H32-H29 -> -6280.8621 | I33: =I32-I29 -> -3575.8621 | ... AF33: =AF32-AF29 -> 1809.1379 | AG33: =SUM(B33:AF33)+B40+B41 -> -41453 | AH33: =AVERAGE(B33:AF33,B40,B41) -> -1256.1515
A35: Monthy Expenses | B35: =SUM(B29:AF29) -> 360443
A36: Monthly UPI | B36: =SUM(B30:AF30) -> 161780 | I36: Gas repair | J36: mirchi p | AA36: sounf/tooth
A37: Monthly Cash | B37: =SUM(B31:AF31) -> 130212
A38: Monthly Sales | B38: =SUM(B32:AF32) -> 291992
A39: Rent, Salaries & others | B39: =Expenses!G20 -> 94022
A40: Swiggy | B40: =4304+3990+3150+3204 -> 14648
A41: Zomato | B41: =1853+4205+3416+2876 -> 12350
A42: Stock | B42: =Stock!M72 -> 54083
A43: Actual P/L | B43: =B38-B35+B40+B41 -> -41453
A45: Chefs amount from Javeed | B45: 1000 | C45: 1000 | D45: 1000 | E45: 3200 | F45: 2300 | G45: 0 | H45: 3200 | I45: 3200 | J45: 0 | K45: 2900 | L45: 2000 | M45: 0 | N45: 0 | O45: 0 | P45: 0 | Q45: 0 | R45: 0 | S45: 0 | T45: 0 | U45: 0 | V45: 0 | W45: 0 | X45: 0 | Y45: 0 | Z45: 2900 | AA45: 2900 | AB45: 0 | AC45: 0 | AD45: 0 | AE45: 2900 | AF45: 0 | AG45: =SUM(B45:AF45) -> 28500
A46: Market from Javeed | B46: 0 | C46: 1000 | D46: 0 | E46: 500 | F46: 0 | G46: 0 | H46: 600 | I46: 2000 | J46: 1200 | K46: 600 | L46: 700 | M46: 1300 | N46: 0 | O46: 0 | P46: 0 | Q46: 800 | R46: 0 | S46: 0 | T46: 1000 | U46: 0 | V46: 600 | W46: 0 | X46: 800 | Y46: 2200 | Z46: 0 | AA46: 0 | AB46: 600 | AC46: 0 | AD46: 0 | AE46: 2100 | AF46: 1000 | AG46: =SUM(B46:AF46) -> 17000
A47: Javeed's Expenses | B47: =B4+B3+B7+B8+(SUM(B20:B22))+B45+B46 -> 7415.8621 | C47: =C4+C3+C7+C8+(SUM(C20:C22))+C45+C46 -> 8415.8621 | D47: =D4+D3+D7+D8+(SUM(D20:D22))+D45+D46 -> 7415.8621 | E47: =E4+E3+E7+E8+(SUM(E20:E22))+E45+E46 -> 10115.862 | F47: =F4+F3+F7+F8+(SUM(F20:F22))+F45+F46 -> 8715.8621 | G47: =G4+G3+G7+G8+(SUM(G20:G22))+G45+G46 -> 0 | H47: =H4+H3+H7+H8+(SUM(H20:H22))+H45+H46 -> 10215.862 | I47: =I4+I3+I7+I8+(SUM(I20:I22))+I45+I46 -> 11615.862 | ... AF47: =AF4+AF3+AF7+AF8+(SUM(AF20:AF22))+AF45+AF46 -> 7415.8621 | AG47: =SUM(B47:AF47) -> 231560
A48: Counter Cash | B48: =B31-B29+B47+10277 -> 9774 | C48: =B48+C31-C29+C47 -> 8149 | D48: =C48+D31-D29+D47 -> 7239 | E48: =D48+E31-E29+E47 -> 8904 | F48: =E48+F31-F29+F47 -> 8150 | G48: =F48+G31-G29+G47 -> 8150 | H48: =G48+H31-H29+H47 -> 7475 | I48: =H48+I31-I29+I47 -> 7395 | J48: =I48+J31-J29+J47 -> 7715 | ... AF48: =AE48+AF31-AF29+AF47 -> 11606
A51: Mutton | B51: =2100+2625 -> 4725
A52: Sea Food | B52: =5000+1730 -> 6730
A53: Gas | B53: =6000+6000+6000+6000 -> 24000
A54: Coal | B54: 2500
A55: Water | B55: 0
B56: =SUM(B51:B55) -> 37955 | J56: Mon | K56: =AF32 -> 16455 | L56: =D32 -> 6700 | M56: =K32 -> 4665 | N56: =R32 -> 0 | O56: =Y32 -> 9100 | P56: =AVERAGEIF(K56:O56,"<>0") -> 9230
J57: Tue | L57: =E32 -> 7520 | M57: =L32 -> 7245 | N57: =S32 -> 6850 | O57: =Z32 -> 7830 | P57: =AVERAGEIF(K57:O57,"<>0") -> 7361.25
J58: Wed | L58: =F32 -> 7445 | M58: =M32 -> 11270 | N58: =T32 -> 5445 | O58: =AA32 -> 8385 | P58: =AVERAGEIF(K58:O58,"<>0") -> 8136.25
A59: Number of Days | B59: 29 | J59: Thu | L59: =G32 -> 0 | M59: =N32 -> 7780 | N59: =U32 -> 11460 | O59: =AB32 -> 13380 | P59: =AVERAGEIF(K59:O59,"<>0") -> 10873.333
J60: Fri | L60: =H32 -> 5725 | M60: =O32 -> 17470 | N60: =V32 -> 9305 | O60: =AC32 -> 11105 | P60: =AVERAGEIF(K60:O60,"<>0") -> 10901.25
J61: Sat | K61: =B32 -> 8727 | L61: =I32 -> 9815 | M61: =P32 -> 12475 | N61: =W32 -> 13715 | O61: =AD32 -> 12735 | P61: =AVERAGEIF(K61:O61,"<>0") -> 11493.4
J62: Sun | K62: =C32 -> 10190 | L62: =J32 -> 11325 | M62: =Q32 -> 15785 | N62: =X32 -> 10055 | O62: =AF32 -> 16455 | P62: =AVERAGEIF(K62:O62,"<>0") -> 12762

Sheet April
B1: 45748 | C1: 45749 | D1: 45750 | E1: 45751 | F1: 45752 | G1: 45753 | H1: 45754 | I1: 45755 | J1: 45756 | K1: 45757 | L1: 45758 | M1: 45759 | N1: 45760 | O1: 45761 | P1: 45762 | Q1: 45763 | R1: 45764 | S1: 45765 | T1: 45766 | U1: 45767 | V1: 45768 | W1: 45769 | X1: 45770 | Y1: 45771 | Z1: 45772 | AA1: 45773 | AB1: 45774 | AC1: 45775 | AD1: 45776 | AE1: 45777 | AF1: Total | AG1: Average | AH1: % Share
A2: Chef | B2: 2900 | C2: 2900 | D2: 2900 | E2: 2900 | F2: 2900 | G2: 0 | H2: 2900 | I2: 2900 | J2: 2900 | K2: 2900 | L2: 2900 | M2: 2900 | N2: 2400 | O2: 2400 | P2: 2400 | Q2: 2400 | R2: 2400 | S2: 2400 | T2: 2400 | U2: 2400 | V2: 0 | W2: 2500 | X2: 2500 | Y2: 2500 | Z2: 2500 | AA2: 2500 | AB2: 2500 | AC2: 2500 | AD2: 2500 | AE2: 2500 | AF2: =SUM(B2:AE2) -> 73600 | AG2: =IFERROR(AVERAGE(B2:AE2),0) -> 2453.3333 | AH2: =(AG2/$AG$29)*100 -> 19.626248
A3: Salaries, Rent and others | B3: =$B$39/$B$59 -> 3214.8571 | C3: =$B$39/$B$59 -> 3214.8571 | D3: =$B$39/$B$59 -> 3214.8571 | E3: =$B$39/$B$59 -> 3214.8571 | F3: =$B$39/$B$59 -> 3214.8571 | G3: 0 | H3: =$B$39/$B$59 -> 3214.8571 | I3: =$B$39/$B$59 -> 3214.8571 | J3: =$B$39/$B$59 -> 3214.8571 | K3: =$B$39/$B$59 -> 3214.8571 | L3: =$B$39/$B$59 -> 3214.8571 | M3: =$B$39/$B$59 -> 3214.8571 | N3: =$B$39/$B$59 -> 3214.8571 | O3: =$B$39/$B$59 -> 3214.8571 | ... U3: =$B$39/$B$59 -> 3214.8571 | V3: 0 | W3: =$B$39/$B$59 -> 3214.8571 | X3: =$B$39/$B$59 -> 3214.8571 | Y3: =$B$39/$B$59 -> 3214.8571 | Z3: =$B$39/$B$59 -> 3214.8571 | AA3: =$B$39/$B$59 -> 3214.8571 | AB3: =$B$39/$B$59 -> 3214.8571 | AC3: =$B$39/$B$59 -> 3214.8571 | AD3: =$B$39/$B$59 -> 3214.8571 | AE3: =$B$39/$B$59 -> 3214.8571 | AF3: =SUM(B3:AE3) -> 90016 | AG3: =IFERROR(AVERAGE(B3:AE3),0) -> 3000.5333 | AH3: =(AG3/$AG$29)*100 -> 24.003755
A4: Stock | B4: =$B$42/$B$59 -> 2524.3571 | C4: =$B$42/$B$59 -> 2524.3571 | D4: =$B$42/$B$59 -> 2524.3571 | E4: =$B$42/$B$59 -> 2524.3571 | F4: =$B$42/$B$59 -> 2524.3571 | G4: 0 | H4: =$B$42/$B$59 -> 2524.3571 | I4: =$B$42/$B$59 -> 2524.3571 | J4: =$B$42/$B$59 -> 2524.3571 | K4: =$B$42/$B$59 -> 2524.3571 | L4: =$B$42/$B$59 -> 2524.3571 | M4: =$B$42/$B$59 -> 2524.3571 | N4: =$B$42/$B$59 -> 2524.3571 | O4: =$B$42/$B$59 -> 2524.3571 | ... U4: =$B$42/$B$59 -> 2524.3571 | V4: 0 | W4: =$B$42/$B$59 -> 2524.3571 | X4: =$B$42/$B$59 -> 2524.3571 | Y4: =$B$42/$B$59 -> 2524.3571 | Z4: =$B$42/$B$59 -> 2524.3571 | AA4: =$B$42/$B$59 -> 2524.3571 | AB4: =$B$42/$B$59 -> 2524.3571 | AC4: =$B$42/$B$59 -> 2524.3571 | AD4: =$B$42/$B$59 -> 2524.3571 | AE4: =$B$42/$B$59 -> 2524.3571 | AF4: =SUM(B4:AE4) -> 70682 | AG4: =IFERROR(AVERAGE(B4:AE4),0) -> 2356.0667 | AH4: =(AG4/$AG$29)*100 -> 18.848131
A5: Meat
A6: Chicken | B6: 3000 | C6: 3500 | D6: 3000 | E6: 3000 | F6: 2500 | G6: 0 | H6: 2500 | I6: 2000 | J6: 2000 | K6: 2000 | L6: 2000 | M6: 2000 | N6: 2000 | O6: 2000 | P6: 1200 | Q6: 2000 | R6: 1500 | S6: 2000 | T6: 2000 | U6: 1900 | V6: 0 | W6: 2000 | X6: 2500 | Y6: 1000 | Z6: 2500 | AA6: 1000 | AB6: 2000 | AC6: 2500 | AD6: 2000 | AE6: 2000 | AF6: =SUM(B6:AE6) -> 59600 | AG6: =IFERROR(AVERAGE(B6:AE6),0) -> 1986.6667 | AH6: =(AG6/$AG$29)*100 -> 15.892994
A7: Mutton | B7: =$B$51/$B$59 -> 53.571429 | C7: =$B$51/$B$59 -> 53.571429 | D7: =$B$51/$B$59 -> 53.571429 | E7: =$B$51/$B$59 -> 53.571429 | F7: =$B$51/$B$59 -> 53.571429 | G7: 0 | H7: =$B$51/$B$59 -> 53.571429 | I7: =$B$51/$B$59 -> 53.571429 | J7: =$B$51/$B$59 -> 53.571429 | K7: =$B$51/$B$59 -> 53.571429 | L7: =$B$51/$B$59 -> 53.571429 | M7: =$B$51/$B$59 -> 53.571429 | N7: =$B$51/$B$59 -> 53.571429 | O7: =$B$51/$B$59 -> 53.571429 | ... U7: =$B$51/$B$59 -> 53.571429 | V7: 0 | W7: =$B$51/$B$59 -> 53.571429 | X7: =$B$51/$B$59 -> 53.571429 | Y7: =$B$51/$B$59 -> 53.571429 | Z7: =$B$51/$B$59 -> 53.571429 | AA7: =$B$51/$B$59 -> 53.571429 | AB7: =$B$51/$B$59 -> 53.571429 | AC7: =$B$51/$B$59 -> 53.571429 | AD7: =$B$51/$B$59 -> 53.571429 | AE7: =$B$51/$B$59 -> 53.571429 | AF7: =SUM(B7:AE7) -> 1500 | AG7: =IFERROR(AVERAGE(B7:AE7),0) -> 50 | AH7: =(AG7/$AG$29)*100 -> 0.39999147
A8: Sea food | B8: =$B$52/$B$59 -> 203.57143 | C8: =$B$52/$B$59 -> 203.57143 | D8: =$B$52/$B$59 -> 203.57143 | E8: =$B$52/$B$59 -> 203.57143 | F8: =$B$52/$B$59 -> 203.57143 | G8: 0 | H8: =$B$52/$B$59 -> 203.57143 | I8: =$B$52/$B$59 -> 203.57143 | J8: =$B$52/$B$59 -> 203.57143 | K8: =$B$52/$B$59 -> 203.57143 | L8: =$B$52/$B$59 -> 203.57143 | M8: =$B$52/$B$59 -> 203.57143 | N8: =$B$52/$B$59 -> 203.57143 | O8: =$B$52/$B$59 -> 203.57143 | ... U8: =$B$52/$B$59 -> 203.57143 | V8: 0 | W8: =$B$52/$B$59 -> 203.57143 | X8: =$B$52/$B$59 -> 203.57143 | Y8: =$B$52/$B$59 -> 203.57143 | Z8: =$B$52/$B$59 -> 203.57143 | AA8: =$B$52/$B$59 -> 203.57143 | AB8: =$B$52/$B$59 -> 203.57143 | AC8: =$B$52/$B$59 -> 203.57143 | AD8: =$B$52/$B$59 -> 203.57143 | AE8: =$B$52/$B$59 -> 203.57143 | AF8: =SUM(B8:AE8) -> 5700 | AG8: =IFERROR(AVERAGE(B8:AE8),0) -> 190 | AH8: =(AG8/$AG$29)*100 -> 1.5199676
A9: Market
A10: All Vegetables | B10: =10+50+40+45+100+50+50 -> 345 | C10: =30+20+30+50+200+30+20+50+20+40 -> 490 | D10: =30+20+50+200+20+30+30+20+30+40+60 -> 530 | E10: =30+20+20+100+120+20+50+30+50 -> 440 | F10: =40+20+30+150+30+40+20+30+30+30 -> 420 | G10: 0 | H10: =30+20+30+130+30+30 -> 270 | I10: =50+20+30+100+30+30+30+20+50 -> 360 | J10: =40+10+40+20+100+30+30+50+40+40 -> 400 | K10: =30+20+50+100+20+30+50+30+30 -> 360 | L10: =40+20+20+100+70+30+30+30 -> 340 | M10: =30+20+40+100+30+40+30+30+40+50 -> 410 | N10: =40+20+50+150+30+30+50+60+50+50+120 -> 650 | O10: =20+20+80+30+30+1350+30+30+50 -> 1640 | P10: =40+20+30+100+30+30+50+50 -> 350 | Q10: =30+20+50+100+30+30+30+50+20+40 -> 400 | R10: =15+15+20+90+50+30+30+50+50 -> 350 | S10: =40+20+20+30+30+200+40+40 -> 420 | T10: =30+20+30+150+30+30+30+30+40+40 -> 430 | U10: =60+20+30+100+30+60+20+50+50 -> 420 | V10: 0 | W10: =40+20+20+30+70+30 -> 210 | X10: =40+20+30+100+40+30+30+30+50+40 -> 410 | Y10: =40+20+20+120+20+30+30+40+40+50 -> 410 | Z10: =40+10+20+120+30+50+20+50+100 -> 440 | AA10: =40+20+30+200+20+30+30+30 -> 400 | AB10: =40+20+50+100+20+30+30+50+50+30 -> 420 | AC10: =40+20+30+100+10+60+60+30+30+50+50 -> 480 | AD10: =40+20+20+120+30+30+10+30+50+50 -> 400 | AE10: =40+20+30+100+30+30+50 -> 300 | AF10: =SUM(B10:AD10) -> 12195 | AG10: =IFERROR(AVERAGE(B10:AE10),0) -> 416.5 | AH10: =(AG10/$AG$29)*100 -> 3.3319289
A11: Curd | B11: 150 | C11: 150 | D11: 250 | E11: 200 | F11: 200 | G11: 0 | H11: 100 | I11: 100 | J11: 150 | K11: 150 | L11: 150 | M11: 100 | N11: 150 | O11: 150 | P11: 100 | Q11: 150 | R11: 150 | S11: 200 | T11: 150 | U11: 250 | V11: 0 | W11: 150 | X11: 200 | Y11: 150 | Z11: 150 | AA11: 250 | AB11: 150 | AC11: 150 | AD11: 200 | AE11: 200 | AF11: =SUM(B11:AD11) -> 4400 | AG11: =IFERROR(AVERAGE(B11:AE11),0) -> 153.33333 | AH11: =(AG11/$AG$29)*100 -> 1.2266405
A12: Milk | B12: 0 | C12: 100 | D12: 100 | E12: 100 | F12: 100 | G12: 0 | H12: 100 | I12: 100 | J12: 100 | K12: 130 | L12: 100 | M12: 100 | N12: 130 | O12: 100 | P12: 100 | Q12: 100 | R12: 100 | S12: 100 | T12: 100 | U12: 130 | V12: 0 | W12: 100 | X12: 100 | Y12: 100 | Z12: 100 | AA12: 100 | AB12: 130 | AC12: 100 | AD12: 100 | AE12: 100 | AF12: =SUM(B12:AD12) -> 2720 | AG12: =IFERROR(AVERAGE(B12:AE12),0) -> 94 | AH12: =(AG12/$AG$29)*100 -> 0.75198396
A13: Paneer | B13: 370 | C13: 0 | D13: 370 | E13: 0 | F13: 370 | G13: 0 | H13: 370 | I13: 370 | J13: 0 | K13: 0 | L13: 370 | M13: 370 | N13: 370 | O13: 370 | P13: 0 | Q13: 0 | R13: 0 | S13: 370 | T13: 370 | U13: 370 | V13: 0 | W13: 0 | X13: 0 | Y13: 0 | Z13: 370 | AA13: 0 | AB13: 370 | AC13: 370 | AD13: 0 | AE13: 370 | AF13: =SUM(B13:AD13) -> 5550 | AG13: =IFERROR(AVERAGE(B13:AE13),0) -> 197.33333 | AH13: =(AG13/$AG$29)*100 -> 1.578633
A14: Mushroom | B14: 0 | C14: 160 | D14: 70 | E14: 120 | F14: 80 | G14: 0 | H14: 0 | I14: 160 | J14: 120 | K14: 0 | L14: 80 | M14: 150 | N14: 100 | O14: 200 | P14: 0 | Q14: 120 | R14: 0 | S14: 0 | T14: 120 | U14: 0 | V14: 0 | W14: 160 | X14: 80 | Y14: 80 | Z14: 0 | AA14: 120 | AB14: 160 | AC14: 80 | AD14: 0 | AE14: 0 | AF14: =SUM(B14:AD14) -> 2160 | AG14: =IFERROR(AVERAGE(B14:AE14),0) -> 72 | AH14: =(AG14/$AG$29)*100 -> 0.57598771
A15: Babycorn | B15: 70 | C15: 0 | D15: 0 | E15: 70 | F15: 105 | G15: 0 | H15: 0 | I15: 0 | J15: 0 | K15: 0 | L15: 70 | M15: 0 | N15: 175 | O15: 0 | P15: 0 | Q15: 0 | R15: 89 | S15: 0 | T15: 140 | U15: 70 | V15: 0 | W15: 70 | X15: 0 | Y15: 140 | Z15: 0 | AA15: 0 | AB15: 70 | AC15: 0 | AD15: 140 | AE15: 0 | AF15: =SUM(B15:AD15) -> 1209 | AG15: =IFERROR(AVERAGE(B15:AE15),0) -> 40.3 | AH15: =(AG15/$AG$29)*100 -> 0.32239312
A16: Eggs | B16: 150 | C16: 0 | D16: 160 | E16: 160 | F16: 160 | G16: 0 | H16: 160 | I16: 0 | J16: 160 | K16: 0 | L16: 160 | M16: 160 | N16: 0 | O16: 160 | P16: 160 | Q16: 0 | R16: 150 | S16: 0 | T16: 150 | U16: 150 | V16: 0 | W16: 0 | X16: 150 | Y16: 150 | Z16: 0 | AA16: 150 | AB16: 150 | AC16: 150 | AD16: 150 | AE16: 0 | AF16: =SUM(B16:AD16) -> 2940 | AG16: =IFERROR(AVERAGE(B16:AE16),0) -> 98 | AH16: =(AG16/$AG$29)*100 -> 0.78398328
A17: Dry Grocery | B17: 89 | C17: 0 | D17: 200 | E17: 0 | F17: 0 | G17: 0 | H17: 0 | I17: 89 | J17: 0 | K17: =89+200+65 -> 354 | L17: 65 | M17: 65 | N17: 65 | O17: =89+600+65+40+40+40+90 -> 964 | P17: =65+65 -> 130 | Q17: =89+200+65 -> 354 | R17: =65+505+120 -> 690 | S17: =65+60 -> 125 | T17: =89+65+75+500 -> 729 | U17: =200+65 -> 265 | V17: 0 | W17: =65+180+108 -> 353 | X17: =65+89+40+40 -> 234 | Y17: =65 -> 65 | Z17: =65+65 -> 130 | AA17: =90+65+200 -> 355 | AB17: =86+65 -> 151 | AC17: 65 | AD17: =65+84 -> 149 | AE17: 80 | AF17: =SUM(B17:AD17) -> 5686 | AG17: =IFERROR(AVERAGE(B17:AE17),0) -> 192.2 | AH17: =(AG17/$AG$29)*100 -> 1.5375672
A18: Garlic | B18: 0 | C18: 70 | D18: 0 | E18: =100+200 -> 300 | F18: 270 | G18: 0 | H18: 0 | I18: 90 | J18: 0 | K18: 75 | L18: 0 | M18: 100 | N18: 220 | O18: 70 | P18: 0 | Q18: 100 | R18: 0 | S18: 70 | T18: 100 | U18: 0 | V18: 0 | W18: 70 | X18: 0 | Y18: 100 | Z18: 240 | AA18: 70 | AB18: 100 | AC18: 0 | AD18: 70 | AE18: 0 | AF18: =SUM(B18:AD18) -> 2115 | AG18: =IFERROR(AVERAGE(B18:AE18),0) -> 70.5 | AH18: =(AG18/$AG$29)*100 -> 0.56398797
A19: Running
A20: Gas | B20: =$B$53/$B$59 -> 857.14286 | C20: =$B$53/$B$59 -> 857.14286 | D20: =$B$53/$B$59 -> 857.14286 | E20: =$B$53/$B$59 -> 857.14286 | F20: =$B$53/$B$59 -> 857.14286 | G20: 0 | H20: =$B$53/$B$59 -> 857.14286 | I20: =$B$53/$B$59 -> 857.14286 | J20: =$B$53/$B$59 -> 857.14286 | K20: =$B$53/$B$59 -> 857.14286 | L20: =$B$53/$B$59 -> 857.14286 | M20: =$B$53/$B$59 -> 857.14286 | N20: =$B$53/$B$59 -> 857.14286 | O20: =$B$53/$B$59 -> 857.14286 | ... U20: =$B$53/$B$59 -> 857.14286 | V20: 0 | W20: =$B$53/$B$59 -> 857.14286 | X20: =$B$53/$B$59 -> 857.14286 | Y20: =$B$53/$B$59 -> 857.14286 | Z20: =$B$53/$B$59 -> 857.14286 | AA20: =$B$53/$B$59 -> 857.14286 | AB20: =$B$53/$B$59 -> 857.14286 | AC20: =$B$53/$B$59 -> 857.14286 | AD20: =$B$53/$B$59 -> 857.14286 | AE20: =$B$53/$B$59 -> 857.14286 | AF20: =SUM(B20:AE20) -> 24000 | AG20: =IFERROR(AVERAGE(B20:AE20),0) -> 800 | AH20: =(AG20/$AG$29)*100 -> 6.3998635
A21: Coal | B21: =$B$54/$B$59 -> 0 | C21: =$B$54/$B$59 -> 0 | D21: =$B$54/$B$59 -> 0 | E21: =$B$54/$B$59 -> 0 | F21: =$B$54/$B$59 -> 0 | G21: 0 | H21: =$B$54/$B$59 -> 0 | I21: =$B$54/$B$59 -> 0 | J21: =$B$54/$B$59 -> 0 | K21: =$B$54/$B$59 -> 0 | L21: =$B$54/$B$59 -> 0 | M21: =$B$54/$B$59 -> 0 | N21: =$B$54/$B$59 -> 0 | O21: =$B$54/$B$59 -> 0 | ... U21: =$B$54/$B$59 -> 0 | V21: 0 | W21: =$B$54/$B$59 -> 0 | X21: =$B$54/$B$59 -> 0 | Y21: =$B$54/$B$59 -> 0 | Z21: =$B$54/$B$59 -> 0 | AA21: =$B$54/$B$59 -> 0 | AB21: =$B$54/$B$59 -> 0 | AC21: =$B$54/$B$59 -> 0 | AD21: =$B$54/$B$59 -> 0 | AE21: =$B$54/$B$59 -> 0 | AF21: =SUM(B21:AE21) -> 0 | AG21: =IFERROR(AVERAGE(B21:AE21),0) -> 0 | AH21: =(AG21/$AG$29)*100 -> 0
A22: Water | B22: =$B$55/$B$59 -> 204.46429 | C22: =$B$55/$B$59 -> 204.46429 | D22: =$B$55/$B$59 -> 204.46429 | E22: =$B$55/$B$59 -> 204.46429 | F22: =$B$55/$B$59 -> 204.46429 | G22: 0 | H22: =$B$55/$B$59 -> 204.46429 | I22: =$B$55/$B$59 -> 204.46429 | J22: =$B$55/$B$59 -> 204.46429 | K22: =$B$55/$B$59 -> 204.46429 | L22: =$B$55/$B$59 -> 204.46429 | M22: =$B$55/$B$59 -> 204.46429 | N22: =$B$55/$B$59 -> 204.46429 | O22: =$B$55/$B$59 -> 204.46429 | ... U22: =$B$55/$B$59 -> 204.46429 | V22: 0 | W22: =$B$55/$B$59 -> 204.46429 | X22: =$B$55/$B$59 -> 204.46429 | Y22: =$B$55/$B$59 -> 204.46429 | Z22: =$B$55/$B$59 -> 204.46429 | AA22: =$B$55/$B$59 -> 204.46429 | AB22: =$B$55/$B$59 -> 204.46429 | AC22: =$B$55/$B$59 -> 204.46429 | AD22: =$B$55/$B$59 -> 204.46429 | AE22: =$B$55/$B$59 -> 204.46429 | AF22: =SUM(B22:AE22) -> 5725 | AG22: =IFERROR(AVERAGE(B22:AE22),0) -> 190.83333 | AH22: =(AG22/$AG$29)*100 -> 1.5266341
A23: Others
A24: Covers | B24: 0 | C24: 0 | D24: 0 | E24: 0 | F24: 0 | G24: 0 | H24: 0 | I24: 0 | J24: 0 | K24: 0 | L24: 0 | M24: 0 | N24: 0 | O24: 0 | P24: 0 | Q24: 0 | R24: 0 | S24: 0 | T24: 0 | U24: 0 | V24: 0 | W24: 0 | X24: 0 | Y24: 0 | Z24: 0 | AA24: 0 | AB24: 660 | AC24: 0 | AD24: 0 | AE24: 0 | AF24: =SUM(B24:AE24) -> 660 | AG24: =IFERROR(AVERAGE(B24:AE24),0) -> 22 | AH24: =(AG24/$AG$29)*100 -> 0.17599625
A25: Tissue Paper | B25: 0 | C25: 0 | D25: 0 | E25: 0 | F25: 0 | G25: 0 | H25: 0 | I25: 0 | J25: 0 | K25: 0 | L25: 520 | M25: 0 | N25: 0 | O25: 0 | P25: 0 | Q25: 0 | R25: 0 | S25: 0 | T25: 0 | U25: 0 | V25: 0 | W25: 0 | X25: 0 | Y25: 0 | Z25: 0 | AA25: 0 | AB25: 0 | AC25: 0 | AD25: 0 | AE25: 0 | AF25: =SUM(B25:AE25) -> 520 | AG25: =IFERROR(AVERAGE(B25:AE25),0) -> 17.333333 | AH25: =(AG25/$AG$29)*100 -> 0.13866371
A26: Utilities | B26: 20 | C26: 280 | D26: 100 | E26: 0 | F26: 0 | G26: 0 | H26: 0 | I26: =250+280 -> 530 | J26: 0 | K26: 0 | L26: 0 | M26: 0 | N26: 0 | O26: =220+100 -> 320 | P26: 0 | Q26: 0 | R26: 0 | S26: 0 | T26: 0 | U26: 220 | V26: 0 | W26: 40 | X26: 40 | Y26: 0 | Z26: 0 | AA26: 0 | AB26: 280 | AC26: 0 | AD26: 0 | AE26: 250 | AF26: =SUM(B26:AE26) -> 2080 | AG26: =IFERROR(AVERAGE(B26:AE26),0) -> 69.333333 | AH26: =(AG26/$AG$29)*100 -> 0.55465483
A27: Worker | B27: 0 | C27: 0 | D27: 0 | E27: 0 | F27: 0 | G27: 0 | H27: 400 | I27: 0 | J27: 0 | K27: 0 | L27: 0 | M27: 0 | N27: 0 | O27: 0 | P27: 0 | Q27: 0 | R27: 0 | S27: 0 | T27: 0 | U27: 0 | V27: 0 | W27: 0 | X27: 0 | Y27: 0 | Z27: 0 | AA27: 0 | AB27: 0 | AC27: 0 | AD27: 500 | AE27: 0 | AF27: =SUM(B27:AE27) -> 900 | AG27: =IFERROR(AVERAGE(B27:AE27),0) -> 30 | AH27: =(AG27/$AG$29)*100 -> 0.23999488
A28: Stationery | B28: 0 | C28: 0 | D28: 0 | E28: 0 | F28: 0 | G28: 0 | H28: 0 | I28: 0 | J28: 0 | K28: 0 | L28: 0 | M28: 0 | N28: 0 | O28: 0 | P28: 0 | Q28: 0 | R28: 0 | S28: 0 | T28: 0 | U28: 0 | V28: 0 | W28: 0 | X28: 0 | Y28: 0 | Z28: 0 | AA28: 0 | AB28: 0 | AC28: 0 | AD28: 0 | AE28: 0 | AF28: =SUM(B28:AE28) -> 0 | AG28: =IFERROR(AVERAGE(B28:AE28),0) -> 0 | AH28: =(AG28/$AG$29)*100 -> 0
A29: Total | B29: =SUM(B2:B28) -> 14151.964 | C29: =SUM(C2:C28) -> 14707.964 | D29: =SUM(D2:D28) -> 14737.964 | E29: =SUM(E2:E28) -> 14347.964 | F29: =SUM(F2:F28) -> 14162.964 | G29: =SUM(G2:G28) -> 0 | H29: =SUM(H2:H28) -> 13857.964 | I29: =SUM(I2:I28) -> 13756.964 | ... AE29: =SUM(AE2:AE28) -> 12857.964 | AF29: =SUM(B29:AE29) -> 375008 | AG29: =AVERAGE(B29:AE29) -> 12500.267 | AH29: =(AG29/$AG$29)*100 -> 100
A30: UPI | B30: 5290 | C30: 6980 | D30: 7960 | E30: 4800 | F30: 5395 | G30: 0 | H30: 7555 | I30: 6750 | J30: 5385 | K30: 3415 | L30: 7520 | M30: 5810 | N30: 12585 | O30: 2180 | P30: 6380 | Q30: 8110 | R30: 4175 | S30: 7745 | T30: 8910 | U30: 5563 | V30: 0 | W30: 8425 | X30: 2690 | Y30: 3065 | Z30: 9240 | AA30: 5930 | AB30: 10645 | AC30: 8090 | AD30: 4810 | AE30: 3790 | AF30: =SUM(B30:AE30) -> 179193 | AG30: =IFERROR(AVERAGE(B30:AE30),0) -> 5973.1 | AH30: =IFERROR((AG30/$AG$32)*100,0) -> 50.632078
A31: Cash | B31: =B32-B30 -> 13630 | C31: =C32-C30 -> 8970 | D31: =D32-D30 -> 7385 | E31: =E32-E30 -> 11287 | F31: =F32-F30 -> 5090 | G31: =G32-G30 -> 0 | H31: =H32-H30 -> 3585 | I31: =I32-I30 -> 7107 | ... AE31: =AE32-AE30 -> 3265 | AF31: =SUM(B31:AE31) -> 174719 | AG31: =IFERROR(AVERAGE(B31:AE31),0) -> 5823.9667 | AH31: =IFERROR((AG31/$AG$32)*100,0) -> 49.367922
A32: Total Sale | B32: 18920 | C32: 15950 | D32: 15345 | E32: 16087 | F32: 10485 | G32: 0 | H32: 11140 | I32: 13857 | J32: 9775 | K32: 8452 | L32: 13210 | M32: 12055 | N32: 16660 | O32: 6135 | P32: 12050 | Q32: 11100 | R32: 6645 | S32: 15540 | T32: 16905 | U32: 8783 | V32: 0 | W32: 15580 | X32: 9200 | Y32: 7705 | Z32: 17280 | AA32: 14560 | AB32: 14920 | AC32: 19400 | AD32: 9118 | AE32: 7055 | AF32: =SUM(B32:AE32) -> 353912 | AG32: =IFERROR(AVERAGE(B32:AE32),0) -> 11797.067 | AH32: =IFERROR((AG32/$AG$32)*100,0) -> 100
A33: Profit or Loss | B33: =B32-B29 -> 4768.0357 | C33: =C32-C29 -> 1242.0357 | D33: =D32-D29 -> 607.03571 | E33: =E32-E29 -> 1739.0357 | F33: =F32-F29 -> -3677.9643 | G33: =G32-G29 -> 0 | H33: =H32-H29 -> -2717.9643 | I33: =I32-I29 -> 100.03571 | ... AE33: =AE32-AE29 -> -5802.9643 | AF33: =SUM(B33:AE33)+B40+B41 -> 6777 | AG33: =AVERAGE(B33:AE33,B40,B41) -> 211.78125
A35: Monthy Expenses | B35: =SUM(B29:AE29) -> 375008
A36: Monthly UPI | B36: =SUM(B30:AE30) -> 179193 | I36: spray
A37: Monthly Cash | B37: =SUM(B31:AE31) -> 174719 | T37: m powder | U37: Soap Oil
A38: Monthly Sales | B38: =SUM(B32:AE32) -> 353912 | AB38: Soap Oil | AE38: rice auto
A39: Rent, Salaries & others | B39: =Expenses!H20 -> 90016
A40: Swiggy | B40: =1197+1938+2863+3924+2163 -> 12085
A41: Zomato | B41: =3566+3919+4575+3728 -> 15788
A42: Stock | B42: =Stock!R72 -> 70682
A43: Actual P/L | B43: =B38-B35+B40+B41 -> 6777
A45: Chefs amount from Javeed | B45: 0 | C45: 0 | D45: 0 | E45: 0 | F45: 0 | G45: 0 | H45: 0 | I45: 2900 | J45: 0 | K45: 0 | L45: 0 | M45: 0 | N45: 1000 | O45: 1000 | P45: 1000 | Q45: 0 | R45: 0 | S45: 0 | T45: 0 | U45: 2400 | V45: 0 | W45: 0 | X45: 0 | Y45: 0 | Z45: 0 | AA45: 0 | AB45: 0 | AC45: 0 | AD45: 0 | AE45: 0 | AF45: =SUM(B45:AE45) -> 8300
A46: Market from Javeed | B46: 500 | C46: 0 | D46: 0 | E46: 0 | F46: -5630 | G46: 0 | H46: 0 | I46: 1300 | J46: 0 | K46: 0 | L46: 0 | M46: 0 | N46: 0 | O46: 0 | P46: 0 | Q46: 1300 | R46: 500 | S46: 1200 | T46: 0 | U46: 1900 | V46: 0 | W46: 1200 | X46: 300 | Y46: 0 | Z46: 0 | AA46: 0 | AB46: 660 | AC46: 0 | AD46: 0 | AE46: 700 | AF46: =SUM(B46:AE46) -> 3930
A47: Javeed's Expenses | B47: =B4+B3+B7+B8+(SUM(B20:B22))+B45+B46 -> 7557.9643 | C47: =C4+C3+C7+C8+(SUM(C20:C22))+C45+C46 -> 7057.9643 | D47: =D4+D3+D7+D8+(SUM(D20:D22))+D45+D46 -> 7057.9643 | E47: =E4+E3+E7+E8+(SUM(E20:E22))+E45+E46 -> 7057.9643 | F47: =F4+F3+F7+F8+(SUM(F20:F22))+F45+F46 -> 1427.9643 | G47: =G4+G3+G7+G8+(SUM(G20:G22))+G45+G46 -> 0 | H47: =H4+H3+H7+H8+(SUM(H20:H22))+H45+H46 -> 7057.9643 | I47: =I4+I3+I7+I8+(SUM(I20:I22))+I45+I46 -> 11257.964 | ... AE47: =AE4+AE3+AE7+AE8+(SUM(AE20:AE22))+AE45+AE46 -> 7757.9643 | AF47: =SUM(B47:AE47) -> 209853
A48: Counter Cash | B48: =B31-B29+B47+11606 -> 18642 | C48: =B48+C31-C29+C47 -> 19962 | D48: =C48+D31-D29+D47 -> 19667 | E48: =D48+E31-E29+E47 -> 23664 | F48: =E48+F31-F29+F47 -> 16019 | G48: =F48+G31-G29+G47 -> 16019 | H48: =G48+H31-H29+H47 -> 12804 | I48: =H48+I31-I29+I47 -> 17412 | J48: =I48+J31-J29+J47 -> 15972 | ... AE48: =AD48+AE31-AE29+AE47 -> 21170
A51: Mutton | B51: 1500
A52: Sea Food | B52: 5700
A53: Gas | B53: 24000
A54: Coal | B54: 0
A55: Water | B55: 5725
B56: =SUM(B51:B55) -> 36925 | J56: Mon | L56: =H32 -> 11140 | M56: =O32 -> 6135 | N56: =V32 -> 0 | O56: =AC32 -> 19400 | P56: =AVERAGEIF(K56:O56,"<>0") -> 12225
J57: Tue | K57: =B32 -> 18920 | L57: =I32 -> 13857 | M57: =P32 -> 12050 | N57: =W32 -> 15580 | O57: =AD32 -> 9118 | P57: =AVERAGEIF(K57:O57,"<>0") -> 13905
J58: Wed | K58: =C32 -> 15950 | L58: =J32 -> 9775 | M58: =Q32 -> 11100 | N58: =X32 -> 9200 | O58: =AE32 -> 7055 | P58: =AVERAGEIF(K58:O58,"<>0") -> 10616
A59: Number of Days | B59: 28 | J59: Thu | K59: =D32 -> 15345 | L59: =K32 -> 8452 | M59: =R32 -> 6645 | N59: =Y32 -> 7705 | P59: =AVERAGEIF(K59:O59,"<>0") -> 9536.75
J60: Fri | K60: =E32 -> 16087 | L60: =L32 -> 13210 | M60: =S32 -> 15540 | N60: =Z32 -> 17280 | P60: =AVERAGEIF(K60:O60,"<>0") -> 15529.25
J61: Sat | K61: =F32 -> 10485 | L61: =M32 -> 12055 | M61: =T32 -> 16905 | N61: =AA32 -> 14560 | P61: =AVERAGEIF(K61:O61,"<>0") -> 13501.25
J62: Sun | K62: =G32 -> 0 | L62: =N32 -> 16660 | M62: =U32 -> 8783 | N62: =AB32 -> 14920 | P62: =AVERAGEIF(K62:O62,"<>0") -> 13454.333

Sheet May
B1: 45778 | C1: 45779 | D1: 45780 | E1: 45781 | F1: 45782 | G1: 45783 | H1: 45784 | I1: 45785 | J1: 45786 | K1: 45787 | L1: 45788 | M1: 45789 | N1: 45790 | O1: 45791 | P1: 45792 | Q1: 45793 | R1: 45794 | S1: 45795 | T1: 45796 | U1: 45797 | V1: 45798 | W1: 45799 | X1: 45800 | Y1: 45801 | Z1: 45802 | AA1: 45803 | AB1: 45804 | AC1: 45805 | AD1: 45806 | AE1: 45807 | AF1: 45808 | AG1: Total | AH1: Average | AI1: % Share
A2: Chef | B2: =1100+1000+600 -> 2700 | C2: =1100+1000+600 -> 2700 | D2: =1100+1000+600 -> 2700 | E2: =1100+1000+600 -> 2700 | F2: =1100+1000+600 -> 2700 | G2: =1100+1000+600 -> 2700 | H2: =1100+1000+600 -> 2700 | I2: =1100+1000+600 -> 2700 | ... S2: =1100+1000+600 -> 2700 | T2: 0 | U2: =1100+1000+600 -> 2700 | V2: =1100+1000+600 -> 2700 | W2: =1100+1000+600 -> 2700 | X2: =1100+1000+600 -> 2700 | Y2: =1100+1000+600 -> 2700 | Z2: =1100+1000+600 -> 2700 | AA2: =1100+1000+600 -> 2700 | AB2: =1100+1000+600 -> 2700 | ... AF2: =1100+1000+600 -> 2700 | AG2: =SUM(B2:AF2) -> 81000 | AH2: =IFERROR(AVERAGE(B2:AF2),0) -> 2612.9032 | AI2: =(AH2/$AH$29)*100 -> 19.129264
A3: Salaries, Rent and others | B3: =$B$39/$B$59 -> 3270.0667 | C3: =$B$39/$B$59 -> 3270.0667 | D3: =$B$39/$B$59 -> 3270.0667 | E3: =$B$39/$B$59 -> 3270.0667 | F3: =$B$39/$B$59 -> 3270.0667 | G3: =$B$39/$B$59 -> 3270.0667 | H3: =$B$39/$B$59 -> 3270.0667 | I3: =$B$39/$B$59 -> 3270.0667 | ... S3: =$B$39/$B$59 -> 3270.0667 | T3: 0 | U3: =$B$39/$B$59 -> 3270.0667 | V3: =$B$39/$B$59 -> 3270.0667 | W3: =$B$39/$B$59 -> 3270.0667 | X3: =$B$39/$B$59 -> 3270.0667 | Y3: =$B$39/$B$59 -> 3270.0667 | Z3: =$B$39/$B$59 -> 3270.0667 | AA3: =$B$39/$B$59 -> 3270.0667 | AB3: =$B$39/$B$59 -> 3270.0667 | ... AF3: =$B$39/$B$59 -> 3270.0667 | AG3: =SUM(B3:AF3) -> 98102 | AH3: =IFERROR(AVERAGE(B3:AF3),0) -> 3164.5806 | AI3: =(AH3/$AH$29)*100 -> 23.168137
A4: Stock | B4: =$B$42/$B$59 -> 3194.2333 | C4: =$B$42/$B$59 -> 3194.2333 | D4: =$B$42/$B$59 -> 3194.2333 | E4: =$B$42/$B$59 -> 3194.2333 | F4: =$B$42/$B$59 -> 3194.2333 | G4: =$B$42/$B$59 -> 3194.2333 | H4: =$B$42/$B$59 -> 3194.2333 | I4: =$B$42/$B$59 -> 3194.2333 | ... S4: =$B$42/$B$59 -> 3194.2333 | T4: 0 | U4: =$B$42/$B$59 -> 3194.2333 | V4: =$B$42/$B$59 -> 3194.2333 | W4: =$B$42/$B$59 -> 3194.2333 | X4: =$B$42/$B$59 -> 3194.2333 | Y4: =$B$42/$B$59 -> 3194.2333 | Z4: =$B$42/$B$59 -> 3194.2333 | AA4: =$B$42/$B$59 -> 3194.2333 | AB4: =$B$42/$B$59 -> 3194.2333 | ... AF4: =$B$42/$B$59 -> 3194.2333 | AG4: =SUM(B4:AF4) -> 95827 | AH4: =IFERROR(AVERAGE(B4:AF4),0) -> 3091.1935 | AI4: =(AH4/$AH$29)*100 -> 22.630864
A5: Meat
